Workbook

Sheet ReservesUSDT
A1: Date | B1: TETHER Total Assets | C1: USDT Issued | D1: Excess Reserves (Equity) | E1: Tether Equity % | F1: CIRCLE Total Assets | G1: USDC Issued | H1: Circle Equity %
A2: 44377 | B2: 62773190075 | C2: 62610829196 | D2: =B2-C2 -> 162360879 | E2: =D2/C2 -> 0.0025931757 | F2: 25158531650 | G2: 25158531650 | H2: =(F2-G2)/G2 -> 0
A3: 44469 | B3: 69156771674 | C3: 68994393701 | D3: =B3-C3 -> 162377973 | E3: =D3/C3 -> 0.0023534952 | F3: 31652676021 | G3: 31652676021 | H3: =(F3-G3)/G3 -> 0
A4: 44561 | B4: 78675642677 | C4: 78480852949 | D4: =B4-C4 -> 194789728 | E4: =D4/C4 -> 0.0024820032 | F4: 42416160651 | G4: 42416160651 | H4: =(F4-G4)/G4 -> 0
A5: 44651 | B5: 82424821101 | C5: 82188190813 | D5: =B5-C5 -> 236630288 | E5: =D5/C5 -> 0.0028791276 | F5: 51388555903 | G5: 51388555903 | H5: =(F5-G5)/G5 -> 0
A6: 44742 | B6: 66409619424 | C6: 66204234509 | D6: =B6-C6 -> 205384915 | E6: =D6/C6 -> 0.0031022927 | F6: 55569660586 | G6: 55569660586 | H6: =(F6-G6)/G6 -> 0
A7: 44834 | B7: 68061618458 | C7: 67805112981 | D7: =B7-C7 -> 256505477 | E7: =D7/C7 -> 0.0037829813 | F7: 47479523936 | G7: 47261819834 | H7: =(F7-G7)/G7 -> 0.0046063419
A8: 44926 | B8: 67044148175 | C8: 66057260169 | D8: =B8-C8 -> 986888006 | E8: =D8/C8 -> 0.014939887 | F8: 44693963701 | G8: 44553543212 | H8: =(F8-G8)/G8 -> 0.0031517244
A9: 45016 | B9: 81833149345 | C9: 79372401626 | D9: =B9-C9 -> 2460747719 | E9: =D9/C9 -> 0.031002561 | F9: 32518607650 | G9: 32518607650 | H9: =(F9-G9)/G9 -> 0
A10: 45107 | B10: 86499251218 | C10: 83178020411 | D10: =B10-C10 -> 3321230807 | E10: =D10/C10 -> 0.039929188 | F10: 27439541303 | G10: 27384351887 | H10: =(F10-G10)/G10 -> 0.0020153632
A11: 45199 | B11: 86384653832 | C11: 83153363663 | D11: =B11-C11 -> 3231290169 | E11: =D11/C11 -> 0.038859404 | F11: 25025027673 | G11: 24973159027 | H11: =(F11-G11)/G11 -> 0.0020769758
A12: 45291 | B12: 97020394556 | C12: 91572956801 | D12: =B12-C12 -> 5447437755 | E12: =D12/C12 -> 0.059487407 | F12: 24693288222 | G12: 24641390742 | H12: =(F12-G12)/G12 -> 0.00210611
A13: 45382 | B13: 110289406409 | C13: 104019279735 | D13: =B13-C13 -> 6270126674 | E13: =D13/C13 -> 0.060278505 | F13: 32425876781 | G13: 32374547608 | H13: =(F13-G13)/G13 -> 0.0015854792
... A20: 46022 | B20: 192877729144 | C20: 186450610920 | D20: =B20-C20 -> 6427118224 | E20: =D20/C20 -> 0.034470889 | F20: 75332981976 | G20: 75266033823 | H20: =(F20-G20)/G20 -> 0.00088948693

Sheet USDT_FinalReserves
A1: Date | B1: Tether Total Assets | C1: USDT Market Cap | D1: Daily Change | F1: New Estimate Reserves
A2: 44834 | B2: 6.8070818e+10 | C2: 6.8018937e+10 | D2: =0 -> 0 | E2: =C2*(1+ReservesUSDT!$E$7) -> 6.8276251e+10 | F2: =E2*(D2+1) -> 6.8276251e+10 | G2: =F2-C2 -> 2.5731437e+08 | H2: =IF(G2>0,1,0) -> 1
A3: 44835 | B3: 6.8056797e+10 | C3: 6.8032464e+10 | D3: =(B3-B2)/B2 -> -0.00020596756 | E3: =C3*(1+ReservesUSDT!$E$7) -> 6.8289829e+10 | F3: =E3*(D3+1) -> 6.8275764e+10 | G3: =F3-C3 -> 2.4330005e+08 | H3: =IF(G3>0,1,0) -> 1
A4: 44836 | B4: 6.8055327e+10 | C4: 6.7985211e+10 | D4: =(B4-B3)/B3 -> -2.1602254e-05 | E4: =C4*(1+ReservesUSDT!$E$7) -> 6.8242398e+10 | F4: =E4*(D4+1) -> 6.8240924e+10 | G4: =F4-C4 -> 2.557126e+08 | H4: =IF(G4>0,1,0) -> 1
A5: 44837 | B5: 6.8360279e+10 | C5: 6.7852871e+10 | D5: =(B5-B4)/B4 -> 0.0044809347 | E5: =C5*(1+ReservesUSDT!$E$7) -> 6.8109557e+10 | F5: =E5*(D5+1) -> 6.8414751e+10 | G5: =F5-C5 -> 5.6188062e+08 | H5: =IF(G5>0,1,0) -> 1
A6: 44838 | B6: 6.7699719e+10 | C6: 6.7955488e+10 | D6: =(B6-B5)/B5 -> -0.0096629154 | E6: =C6*(1+ReservesUSDT!$E$7) -> 6.8212562e+10 | F6: =E6*(D6+1) -> 6.755343e+10 | G6: =F6-C6 -> -4.0205787e+08 | H6: =IF(G6>0,1,0) -> 0
A7: 44839 | B7: 6.7697961e+10 | C7: 6.8146473e+10 | D7: =(B7-B6)/B6 -> -2.5963498e-05 | E7: =C7*(1+ReservesUSDT!$E$7) -> 6.840427e+10 | F7: =E7*(D7+1) -> 6.8402494e+10 | G7: =F7-C7 -> 2.5602082e+08 | H7: =IF(G7>0,1,0) -> 1
A8: 44840 | B8: 6.7664362e+10 | C8: 6.8249512e+10 | D8: =(B8-B7)/B7 -> -0.0004963142 | E8: =C8*(1+ReservesUSDT!$E$7) -> 6.8507699e+10 | F8: =E8*(D8+1) -> 6.8473697e+10 | G8: =F8-C8 -> 2.2418529e+08 | H8: =IF(G8>0,1,0) -> 1
A9: 44841 | B9: 6.7689547e+10 | C9: 6.8240187e+10 | D9: =(B9-B8)/B8 -> 0.00037220743 | E9: =C9*(1+ReservesUSDT!$E$7) -> 6.8498338e+10 | F9: =E9*(D9+1) -> 6.8523834e+10 | G9: =F9-C9 -> 2.8364694e+08 | H9: =IF(G9>0,1,0) -> 1
A10: 44842 | B10: 6.7681807e+10 | C10: 6.8360023e+10 | D10: =(B10-B9)/B9 -> -0.00011433949 | E10: =C10*(1+ReservesUSDT!$E$7) -> 6.8618628e+10 | F10: =E10*(D10+1) -> 6.8610782e+10 | G10: =F10-C10 -> 2.5075887e+08 | H10: =IF(G10>0,1,0) -> 1
A11: 44843 | B11: 6.7684175e+10 | C11: 6.838466e+10 | D11: =(B11-B10)/B10 -> 3.4985781e-05 | E11: =C11*(1+ReservesUSDT!$E$7) -> 6.8643358e+10 | F11: =E11*(D11+1) -> 6.8645759e+10 | G11: =F11-C11 -> 2.6109943e+08 | H11: =IF(G11>0,1,0) -> 1
A12: 44844 | B12: 6.7616413e+10 | C12: 6.8308302e+10 | D12: =(B12-B11)/B11 -> -0.0010011544 | E12: =C12*(1+ReservesUSDT!$E$7) -> 6.8566711e+10 | F12: =E12*(D12+1) -> 6.8498065e+10 | G12: =F12-C12 -> 1.8976317e+08 | H12: =IF(G12>0,1,0) -> 1
A13: 44845 | B13: 6.7171357e+10 | C13: 6.846553e+10 | D13: =(B13-B12)/B12 -> -0.0065820745 | E13: =C13*(1+ReservesUSDT!$E$7) -> 6.8724534e+10 | F13: =E13*(D13+1) -> 6.8272184e+10 | G13: =F13-C13 -> -1.9334618e+08 | H13: =IF(G13>0,1,0) -> 0
A14: 44846 | B14: 6.6329591e+10 | C14: 6.8428562e+10 | D14: =(B14-B13)/B13 -> -0.012531614 | E14: =C14*(1+ReservesUSDT!$E$7) -> 6.8687426e+10 | F14: =E14*(D14+1) -> 6.7826661e+10 | G14: =F14-C14 -> -6.019003e+08 | H14: =IF(G14>0,1,0) -> 0
... A93: 44925 | B93: 6.2761996e+10 | C93: 6.6255816e+10 | D93: =(B93-B92)/B92 -> 0.0012852454 | E93: =C93*(1+ReservesUSDT!$E$7) -> 6.650646e+10 | F93: =E93*(D93+1) -> 6.6591937e+10 | G93: =F93-C93 -> 3.3612164e+08 | H93: =IF(G93>0,1,0) -> 1
A94: 44926 | B94: 6.7035861e+10 | C94: 6.6279044e+10 | D94: =0 -> 0 | E94: =C94*(1+ReservesUSDT!$E$8) -> 6.7269245e+10 | F94: =E94*(D94+1) -> 6.7269245e+10 | G94: =F94-C94 -> 9.9020142e+08 | H94: =IF(G94>0,1,0) -> 1
A95: 44927 | B95: 6.704198e+10 | C95: 6.6226452e+10 | D95: =(B95-B94)/B94 -> 9.1282944e-05 | E95: =C95*(1+ReservesUSDT!$E$8) -> 6.7215867e+10 | F95: =E95*(D95+1) -> 6.7222003e+10 | G95: =F95-C95 -> 9.9555137e+08 | H95: =IF(G95>0,1,0) -> 1
A96: 44928 | B96: 6.7056356e+10 | C96: 6.6301858e+10 | D96: =(B96-B95)/B95 -> 0.00021442955 | E96: =C96*(1+ReservesUSDT!$E$8) -> 6.7292401e+10 | F96: =E96*(D96+1) -> 6.730683e+10 | G96: =F96-C96 -> 1.0049718e+09 | H96: =IF(G96>0,1,0) -> 1
A97: 44929 | B97: 6.7117597e+10 | C97: 6.6223252e+10 | D97: =(B97-B96)/B96 -> 0.00091327611 | E97: =C97*(1+ReservesUSDT!$E$8) -> 6.721262e+10 | F97: =E97*(D97+1) -> 6.7274003e+10 | G97: =F97-C97 -> 1.0507516e+09 | H97: =IF(G97>0,1,0) -> 1
A98: 44930 | B98: 6.6235291e+10 | C98: 6.6274059e+10 | D98: =(B98-B97)/B97 -> -0.013145663 | E98: =C98*(1+ReservesUSDT!$E$8) -> 6.7264186e+10 | F98: =E98*(D98+1) -> 6.6379954e+10 | G98: =F98-C98 -> 1.0589465e+08 | H98: =IF(G98>0,1,0) -> 1
A99: 44931 | B99: 6.5538973e+10 | C99: 6.6245546e+10 | D99: =(B99-B98)/B98 -> -0.010512795 | E99: =C99*(1+ReservesUSDT!$E$8) -> 6.7235247e+10 | F99: =E99*(D99+1) -> 6.6528416e+10 | G99: =F99-C99 -> 2.828706e+08 | H99: =IF(G99>0,1,0) -> 1
A100: 44932 | B100: 6.5648024e+10 | C100: 6.6278649e+10 | D100: =(B100-B99)/B99 -> 0.0016639054 | E100: =C100*(1+ReservesUSDT!$E$8) -> 6.7268844e+10 | F100: =E100*(D100+1) -> 6.7380773e+10 | G100: =F100-C100 -> 1.1021245e+09 | H100: =IF(G100>0,1,0) -> 1
A101: 44933 | B101: 6.564906e+10 | C101: 6.6263334e+10 | D101: =(B101-B100)/B100 -> 1.5784001e-05 | E101: =C101*(1+ReservesUSDT!$E$8) -> 6.7253301e+10 | F101: =E101*(D101+1) -> 6.7254363e+10 | G101: =F101-C101 -> 9.9102826e+08 | H101: =IF(G101>0,1,0) -> 1
A102: 44934 | B102: 6.5650816e+10 | C102: 6.6272452e+10 | D102: =(B102-B101)/B101 -> 2.6739358e-05 | E102: =C102*(1+ReservesUSDT!$E$8) -> 6.7262555e+10 | F102: =E102*(D102+1) -> 6.7264353e+10 | G102: =F102-C102 -> 9.919015e+08 | H102: =IF(G102>0,1,0) -> 1
A103: 44935 | B103: 6.5665575e+10 | C103: 6.629536e+10 | D103: =(B103-B102)/B102 -> 0.00022482553 | E103: =C103*(1+ReservesUSDT!$E$8) -> 6.7285805e+10 | F103: =E103*(D103+1) -> 6.7300933e+10 | G103: =F103-C103 -> 1.0055728e+09 | H103: =IF(G103>0,1,0) -> 1
A104: 44936 | B104: 6.5681509e+10 | C104: 6.6315047e+10 | D104: =(B104-B103)/B103 -> 0.00024264164 | E104: =C104*(1+ReservesUSDT!$E$8) -> 6.7305786e+10 | F104: =E104*(D104+1) -> 6.7322118e+10 | G104: =F104-C104 -> 1.0070705e+09 | H104: =IF(G104>0,1,0) -> 1
A105: 44937 | B105: 6.5331725e+10 | C105: 6.6307829e+10 | D105: =(B105-B104)/B104 -> -0.0053254523 | E105: =C105*(1+ReservesUSDT!$E$8) -> 6.729846e+10 | F105: =E105*(D105+1) -> 6.6940066e+10 | G105: =F105-C105 -> 6.3223673e+08 | H105: =IF(G105>0,1,0) -> 1
A106: 44938 | B106: 6.5983066e+10 | C106: 6.5470424e+10 | D106: =(B106-B105)/B105 -> 0.0099697574 | E106: =C106*(1+ReservesUSDT!$E$8) -> 6.6448545e+10 | F106: =E106*(D106+1) -> 6.7111021e+10 | G106: =F106-C106 -> 1.6405966e+09 | H106: =IF(G106>0,1,0) -> 1
... A183: 45015 | B183: 6.5401381e+10 | C183: 7.963637e+10 | D183: =(B183-B182)/B182 -> -0.0069694713 | E183: =C183*(1+ReservesUSDT!$E$8) -> 8.0826129e+10 | F183: =E183*(D183+1) -> 8.0262813e+10 | G183: =F183-C183 -> 6.26443e+08 | H183: =IF(G183>0,1,0) -> 1
A184: 45016 | B184: 8.183232e+10 | C184: 7.9708195e+10 | D184: 0 | E184: =C184*(1+ReservesUSDT!$E$9) -> 8.2179353e+10 | F184: =E184*(D184+1) -> 8.2179353e+10 | G184: =F184-C184 -> 2.4711582e+09 | H184: =IF(G184>0,1,0) -> 1
A185: 45017 | B185: 8.1835936e+10 | C185: 7.9808588e+10 | D185: =(B185-B184)/B184 -> 4.4177259e-05 | E185: =C185*(1+ReservesUSDT!$E$9) -> 8.2282859e+10 | F185: =E185*(D185+1) -> 8.2286494e+10 | G185: =F185-C185 -> 2.4779056e+09 | H185: =IF(G185>0,1,0) -> 1
A186: 45018 | B186: 8.181551e+10 | C186: 7.9772057e+10 | D186: =(B186-B185)/B185 -> -0.00024958694 | E186: =C186*(1+ReservesUSDT!$E$9) -> 8.2245195e+10 | F186: =E186*(D186+1) -> 8.2224667e+10 | G186: =F186-C186 -> 2.4526107e+09 | H186: =IF(G186>0,1,0) -> 1
A187: 45019 | B187: 8.1726132e+10 | C187: 7.9792661e+10 | D187: =(B187-B186)/B186 -> -0.0010924404 | E187: =C187*(1+ReservesUSDT!$E$9) -> 8.2266437e+10 | F187: =E187*(D187+1) -> 8.2176566e+10 | G187: =F187-C187 -> 2.3839056e+09 | H187: =IF(G187>0,1,0) -> 1
A188: 45020 | B188: 8.1244193e+10 | C188: 7.9874799e+10 | D188: =(B188-B187)/B187 -> -0.0058969921 | E188: =C188*(1+ReservesUSDT!$E$9) -> 8.2351123e+10 | F188: =E188*(D188+1) -> 8.1865499e+10 | G188: =F188-C188 -> 1.9906994e+09 | H188: =IF(G188>0,1,0) -> 1
A189: 45021 | B189: 8.0917394e+10 | C189: 8.0081067e+10 | D189: =(B189-B188)/B188 -> -0.0040224374 | E189: =C189*(1+ReservesUSDT!$E$9) -> 8.2563786e+10 | F189: =E189*(D189+1) -> 8.2231678e+10 | G189: =F189-C189 -> 2.1506105e+09 | H189: =IF(G189>0,1,0) -> 1
A190: 45022 | B190: 8.0721388e+10 | C190: 8.0140267e+10 | D190: =(B190-B189)/B189 -> -0.0024222982 | E190: =C190*(1+ReservesUSDT!$E$9) -> 8.262482e+10 | F190: =E190*(D190+1) -> 8.2424678e+10 | G190: =F190-C190 -> 2.2844116e+09 | H190: =IF(G190>0,1,0) -> 1
A191: 45023 | B191: 8.0456132e+10 | C191: 8.0188675e+10 | D191: =(B191-B190)/B190 -> -0.0032860592 | E191: =C191*(1+ReservesUSDT!$E$9) -> 8.267473e+10 | F191: =E191*(D191+1) -> 8.2403056e+10 | G191: =F191-C191 -> 2.2143802e+09 | H191: =IF(G191>0,1,0) -> 1
A192: 45024 | B192: 8.0458353e+10 | C192: 8.0268298e+10 | D192: =(B192-B191)/B191 -> 2.7601547e-05 | E192: =C192*(1+ReservesUSDT!$E$9) -> 8.2756821e+10 | F192: =E192*(D192+1) -> 8.2759105e+10 | G192: =F192-C192 -> 2.490807e+09 | H192: =IF(G192>0,1,0) -> 1
A193: 45025 | B193: 8.0469126e+10 | C193: 8.0306858e+10 | D193: =(B193-B192)/B192 -> 0.0001338894 | E193: =C193*(1+ReservesUSDT!$E$9) -> 8.2796576e+10 | F193: =E193*(D193+1) -> 8.2807662e+10 | G193: =F193-C193 -> 2.5008038e+09 | H193: =IF(G193>0,1,0) -> 1
A194: 45026 | B194: 7.8738922e+10 | C194: 8.0310814e+10 | D194: =(B194-B193)/B193 -> -0.021501465 | E194: =C194*(1+ReservesUSDT!$E$9) -> 8.2800655e+10 | F194: =E194*(D194+1) -> 8.102032e+10 | G194: =F194-C194 -> 7.0950552e+08 | H194: =IF(G194>0,1,0) -> 1
A195: 45027 | B195: 7.8862848e+10 | C195: 8.0390805e+10 | D195: =(B195-B194)/B194 -> 0.0015738914 | E195: =C195*(1+ReservesUSDT!$E$9) -> 8.2883126e+10 | F195: =E195*(D195+1) -> 8.3013575e+10 | G195: =F195-C195 -> 2.6227699e+09 | H195: =IF(G195>0,1,0) -> 1
A196: 45028 | B196: 7.8632698e+10 | C196: 8.0526255e+10 | D196: =(B196-B195)/B195 -> -0.002918355 | E196: =C196*(1+ReservesUSDT!$E$9) -> 8.3022775e+10 | F196: =E196*(D196+1) -> 8.2780486e+10 | G196: =F196-C196 -> 2.2542302e+09 | H196: =IF(G196>0,1,0) -> 1
... A274: 45106 | B274: 7.4224045e+10 | C274: 8.3317728e+10 | D274: =(B274-B273)/B273 -> 0.00029748543 | E274: =C274*(1+ReservesUSDT!$E$9) -> 8.5900791e+10 | F274: =E274*(D274+1) -> 8.5926346e+10 | G274: =F274-C274 -> 2.6086172e+09 | H274: =IF(G274>0,1,0) -> 1
A275: 45107 | B275: 8.6483856e+10 | C275: 8.3395956e+10 | D275: 0 | E275: =C275*(1+ReservesUSDT!$E$10) -> 8.6725889e+10 | F275: =E275*(D275+1) -> 8.6725889e+10 | G275: =F275-C275 -> 3.3299328e+09 | H275: =IF(G275>0,1,0) -> 1
A276: 45108 | B276: 8.6499469e+10 | C276: 8.3284622e+10 | D276: =(B276-B275)/B275 -> 0.00018052337 | E276: =C276*(1+ReservesUSDT!$E$10) -> 8.6610109e+10 | F276: =E276*(D276+1) -> 8.6625744e+10 | G276: =F276-C276 -> 3.3411225e+09 | H276: =IF(G276>0,1,0) -> 1
A277: 45109 | B277: 8.6499426e+10 | C277: 8.3335613e+10 | D277: =(B277-B276)/B276 -> -4.916787e-07 | E277: =C277*(1+ReservesUSDT!$E$10) -> 8.6663137e+10 | F277: =E277*(D277+1) -> 8.6663094e+10 | G277: =F277-C277 -> 3.3274808e+09 | H277: =IF(G277>0,1,0) -> 1
A278: 45110 | B278: 8.6491707e+10 | C278: 8.3275413e+10 | D278: =(B278-B277)/B277 -> -8.9235424e-05 | E278: =C278*(1+ReservesUSDT!$E$10) -> 8.6600533e+10 | F278: =E278*(D278+1) -> 8.6592805e+10 | G278: =F278-C278 -> 3.3173918e+09 | H278: =IF(G278>0,1,0) -> 1
A279: 45111 | B279: 8.5901928e+10 | C279: 8.334056e+10 | D279: =(B279-B278)/B278 -> -0.0068189048 | E279: =C279*(1+ReservesUSDT!$E$10) -> 8.6668281e+10 | F279: =E279*(D279+1) -> 8.6077298e+10 | G279: =F279-C279 -> 2.7367381e+09 | H279: =IF(G279>0,1,0) -> 1
A280: 45112 | B280: 8.5787959e+10 | C280: 8.3379982e+10 | D280: =(B280-B279)/B279 -> -0.001326737 | E280: =C280*(1+ReservesUSDT!$E$10) -> 8.6709277e+10 | F280: =E280*(D280+1) -> 8.6594237e+10 | G280: =F280-C280 -> 3.2142546e+09 | H280: =IF(G280>0,1,0) -> 1
A281: 45113 | B281: 8.559757e+10 | C281: 8.3318318e+10 | D281: =(B281-B280)/B280 -> -0.0022193015 | E281: =C281*(1+ReservesUSDT!$E$10) -> 8.6645151e+10 | F281: =E281*(D281+1) -> 8.645286e+10 | G281: =F281-C281 -> 3.1345411e+09 | H281: =IF(G281>0,1,0) -> 1
A282: 45114 | B282: 8.5561749e+10 | C282: 8.3485321e+10 | D282: =(B282-B281)/B281 -> -0.00041847512 | E282: =C282*(1+ReservesUSDT!$E$10) -> 8.6818822e+10 | F282: =E282*(D282+1) -> 8.6782491e+10 | G282: =F282-C282 -> 3.2971696e+09 | H282: =IF(G282>0,1,0) -> 1
A283: 45115 | B283: 8.5553304e+10 | C283: 8.3361581e+10 | D283: =(B283-B282)/B282 -> -9.8708526e-05 | E283: =C283*(1+ReservesUSDT!$E$10) -> 8.6690141e+10 | F283: =E283*(D283+1) -> 8.6681584e+10 | G283: =F283-C283 -> 3.3200032e+09 | H283: =IF(G283>0,1,0) -> 1
A284: 45116 | B284: 8.555624e+10 | C284: 8.3400095e+10 | D284: =(B284-B283)/B283 -> 3.4319106e-05 | E284: =C284*(1+ReservesUSDT!$E$10) -> 8.6730193e+10 | F284: =E284*(D284+1) -> 8.673317e+10 | G284: =F284-C284 -> 3.3330746e+09 | H284: =IF(G284>0,1,0) -> 1
A285: 45117 | B285: 8.5590989e+10 | C285: 8.3401942e+10 | D285: =(B285-B284)/B284 -> 0.00040615078 | E285: =C285*(1+ReservesUSDT!$E$10) -> 8.6732114e+10 | F285: =E285*(D285+1) -> 8.676734e+10 | G285: =F285-C285 -> 3.3653981e+09 | H285: =IF(G285>0,1,0) -> 1
A286: 45118 | B286: 8.5091855e+10 | C286: 8.3357075e+10 | D286: =(B286-B285)/B285 -> -0.005831612 | E286: =C286*(1+ReservesUSDT!$E$10) -> 8.6685455e+10 | F286: =E286*(D286+1) -> 8.617994e+10 | G286: =F286-C286 -> 2.8228644e+09 | H286: =IF(G286>0,1,0) -> 1
A287: 45119 | B287: 8.5330325e+10 | C287: 8.3401281e+10 | D287: =(B287-B286)/B286 -> 0.0028024963 | E287: =C287*(1+ReservesUSDT!$E$10) -> 8.6731426e+10 | F287: =E287*(D287+1) -> 8.697449e+10 | G287: =F287-C287 -> 3.5732099e+09 | H287: =IF(G287>0,1,0) -> 1
... A366: 45198 | B366: 8.3922418e+10 | C366: 8.3267423e+10 | D366: =(B366-B365)/B365 -> 0.0017172095 | E366: =C366*(1+ReservesUSDT!$E$10) -> 8.6592224e+10 | F366: =E366*(D366+1) -> 8.6740921e+10 | G366: =F366-C366 -> 3.4734976e+09 | H366: =IF(G366>0,1,0) -> 1
A367: 45199 | B367: 8.633058e+10 | C367: 8.3267971e+10 | D367: 0 | E367: =C367*(1+ReservesUSDT!$E$11) -> 8.6503715e+10 | F367: =E367*(D367+1) -> 8.6503715e+10 | G367: =F367-C367 -> 3.2357437e+09 | H367: =IF(G367>0,1,0) -> 1
A368: 45200 | B368: 8.6333084e+10 | C368: 8.3258002e+10 | D368: =(B368-B367)/B367 -> 2.8997214e-05 | E368: =C368*(1+ReservesUSDT!$E$11) -> 8.6493358e+10 | F368: =E368*(D368+1) -> 8.6495866e+10 | G368: =F368-C368 -> 3.2378644e+09 | H368: =IF(G368>0,1,0) -> 1
A369: 45201 | B369: 8.6126107e+10 | C369: 8.3251476e+10 | D369: =(B369-B368)/B368 -> -0.0023974173 | E369: =C369*(1+ReservesUSDT!$E$11) -> 8.6486579e+10 | F369: =E369*(D369+1) -> 8.6279234e+10 | G369: =F369-C369 -> 3.0277583e+09 | H369: =IF(G369>0,1,0) -> 1
A370: 45202 | B370: 8.5661887e+10 | C370: 8.3273337e+10 | D370: =(B370-B369)/B369 -> -0.0053900037 | E370: =C370*(1+ReservesUSDT!$E$11) -> 8.6509289e+10 | F370: =E370*(D370+1) -> 8.6043004e+10 | G370: =F370-C370 -> 2.7696669e+09 | H370: =IF(G370>0,1,0) -> 1
A371: 45203 | B371: 8.5611819e+10 | C371: 8.335237e+10 | D371: =(B371-B370)/B370 -> -0.00058448294 | E371: =C371*(1+ReservesUSDT!$E$11) -> 8.6591393e+10 | F371: =E371*(D371+1) -> 8.6540782e+10 | G371: =F371-C371 -> 3.1884122e+09 | H371: =IF(G371>0,1,0) -> 1
A372: 45204 | B372: 8.5605116e+10 | C372: 8.3356125e+10 | D372: =(B372-B371)/B371 -> -7.8297519e-05 | E372: =C372*(1+ReservesUSDT!$E$11) -> 8.6595295e+10 | F372: =E372*(D372+1) -> 8.6588515e+10 | G372: =F372-C372 -> 3.2323892e+09 | H372: =IF(G372>0,1,0) -> 1
A373: 45205 | B373: 8.55144e+10 | C373: 8.3359091e+10 | D373: =(B373-B372)/B372 -> -0.0010597078 | E373: =C373*(1+ReservesUSDT!$E$11) -> 8.6598376e+10 | F373: =E373*(D373+1) -> 8.6506607e+10 | G373: =F373-C373 -> 3.1475157e+09 | H373: =IF(G373>0,1,0) -> 1
A374: 45206 | B374: 8.5510967e+10 | C374: 8.3413565e+10 | D374: =(B374-B373)/B373 -> -4.0143195e-05 | E374: =C374*(1+ReservesUSDT!$E$11) -> 8.6654967e+10 | F374: =E374*(D374+1) -> 8.6651488e+10 | G374: =F374-C374 -> 3.2379228e+09 | H374: =IF(G374>0,1,0) -> 1
A375: 45207 | B375: 8.5510133e+10 | C375: 8.3525461e+10 | D375: =(B375-B374)/B374 -> -9.7514374e-06 | E375: =C375*(1+ReservesUSDT!$E$11) -> 8.677121e+10 | F375: =E375*(D375+1) -> 8.6770364e+10 | G375: =F375-C375 -> 3.2449035e+09 | H375: =IF(G375>0,1,0) -> 1
A376: 45208 | B376: 8.5537916e+10 | C376: 8.3516001e+10 | D376: =(B376-B375)/B375 -> 0.00032490303 | E376: =C376*(1+ReservesUSDT!$E$11) -> 8.6761383e+10 | F376: =E376*(D376+1) -> 8.6789572e+10 | G376: =F376-C376 -> 3.2735711e+09 | H376: =IF(G376>0,1,0) -> 1
A377: 45209 | B377: 8.5838578e+10 | C377: 8.3524067e+10 | D377: =(B377-B376)/B376 -> 0.0035149646 | E377: =C377*(1+ReservesUSDT!$E$11) -> 8.6769762e+10 | F377: =E377*(D377+1) -> 8.7074755e+10 | G377: =F377-C377 -> 3.5506881e+09 | H377: =IF(G377>0,1,0) -> 1
A378: 45210 | B378: 8.5655928e+10 | C378: 8.3483901e+10 | D378: =(B378-B377)/B377 -> -0.0021278373 | E378: =C378*(1+ReservesUSDT!$E$11) -> 8.6728035e+10 | F378: =E378*(D378+1) -> 8.6543492e+10 | G378: =F378-C378 -> 3.0595915e+09 | H378: =IF(G378>0,1,0) -> 1
A379: 45211 | B379: 8.5586888e+10 | C379: 8.3499673e+10 | D379: =(B379-B378)/B378 -> -0.00080601325 | E379: =C379*(1+ReservesUSDT!$E$11) -> 8.6744421e+10 | F379: =E379*(D379+1) -> 8.6674503e+10 | G379: =F379-C379 -> 3.1748304e+09 | H379: =IF(G379>0,1,0) -> 1
... A458: 45290 | B458: 8.9201696e+10 | C458: 91575330091 | D458: =(B458-B457)/B457 -> 0.00024501147 | E458: =C458*(1+ReservesUSDT!$E$11) -> 9.5133893e+10 | F458: =E458*(D458+1) -> 9.5157202e+10 | G458: =F458-C458 -> 3.5818717e+09 | H458: =IF(G458>0,1,0) -> 1
A459: 45291 | B459: 9.6914457e+10 | C459: 9.1696771e+10 | D459: 0 | E459: =C459*(1+ReservesUSDT!$E$12) -> 9.7151575e+10 | F459: =E459*(D459+1) -> 9.7151575e+10 | G459: =F459-C459 -> 5.4548032e+09 | H459: =IF(G459>0,1,0) -> 1
A460: 45292 | B460: 9.6986004e+10 | C460: 9.1724474e+10 | D460: =(B460-B459)/B459 -> 0.00073824331 | E460: =C460*(1+ReservesUSDT!$E$12) -> 9.7180926e+10 | F460: =E460*(D460+1) -> 9.7252669e+10 | G460: =F460-C460 -> 5.5281943e+09 | H460: =IF(G460>0,1,0) -> 1
A461: 45293 | B461: 9.6722539e+10 | C461: 9.1730242e+10 | D461: =(B461-B460)/B460 -> -0.002716523 | E461: =C461*(1+ReservesUSDT!$E$12) -> 9.7187036e+10 | F461: =E461*(D461+1) -> 9.6923026e+10 | G461: =F461-C461 -> 5.1927834e+09 | H461: =IF(G461>0,1,0) -> 1
A462: 45294 | B462: 9.6204459e+10 | C462: 9.1717781e+10 | D462: =(B462-B461)/B461 -> -0.005356357 | E462: =C462*(1+ReservesUSDT!$E$12) -> 9.7173834e+10 | F462: =E462*(D462+1) -> 9.6653336e+10 | G462: =F462-C462 -> 4.9355552e+09 | H462: =IF(G462>0,1,0) -> 1
A463: 45295 | B463: 9.6309054e+10 | C463: 9.2142753e+10 | D463: =(B463-B462)/B462 -> 0.0010872215 | E463: =C463*(1+ReservesUSDT!$E$12) -> 9.7624087e+10 | F463: =E463*(D463+1) -> 9.7730226e+10 | G463: =F463-C463 -> 5.5874725e+09 | H463: =IF(G463>0,1,0) -> 1
A464: 45296 | B464: 9.6467403e+10 | C464: 9.2526809e+10 | D464: =(B464-B463)/B463 -> 0.0016441768 | E464: =C464*(1+ReservesUSDT!$E$12) -> 9.8030989e+10 | F464: =E464*(D464+1) -> 9.819217e+10 | G464: =F464-C464 -> 5.6653602e+09 | H464: =IF(G464>0,1,0) -> 1
A465: 45297 | B465: 9.646427e+10 | C465: 9.2858801e+10 | D465: =(B465-B464)/B464 -> -3.2479677e-05 | E465: =C465*(1+ReservesUSDT!$E$12) -> 9.838273e+10 | F465: =E465*(D465+1) -> 9.8379535e+10 | G465: =F465-C465 -> 5.5207339e+09 | H465: =IF(G465>0,1,0) -> 1
A466: 45298 | B466: 9.6485792e+10 | C466: 9.3445428e+10 | D466: =(B466-B465)/B465 -> 0.00022310894 | E466: =C466*(1+ReservesUSDT!$E$12) -> 9.9004254e+10 | F466: =E466*(D466+1) -> 9.9026343e+10 | G466: =F466-C466 -> 5.5809149e+09 | H466: =IF(G466>0,1,0) -> 1
A467: 45299 | B467: 9.6524603e+10 | C467: 9.3704953e+10 | D467: =(B467-B466)/B466 -> 0.00040224628 | E467: =C467*(1+ReservesUSDT!$E$12) -> 9.9279217e+10 | F467: =E467*(D467+1) -> 9.9319152e+10 | G467: =F467-C467 -> 5.6141993e+09 | H467: =IF(G467>0,1,0) -> 1
A468: 45300 | B468: 9.6480021e+10 | C468: 9.4083713e+10 | D468: =(B468-B467)/B467 -> -0.00046187246 | E468: =C468*(1+ReservesUSDT!$E$12) -> 9.968051e+10 | F468: =E468*(D468+1) -> 9.963447e+10 | G468: =F468-C468 -> 5.5507565e+09 | H468: =IF(G468>0,1,0) -> 1
A469: 45301 | B469: 9.6502461e+10 | C469: 9.4064206e+10 | D469: =(B469-B468)/B468 -> 0.00023259151 | E469: =C469*(1+ReservesUSDT!$E$12) -> 9.9659842e+10 | F469: =E469*(D469+1) -> 9.9683022e+10 | G469: =F469-C469 -> 5.6188157e+09 | H469: =IF(G469>0,1,0) -> 1
A470: 45302 | B470: 9.6620492e+10 | C470: 9.4504766e+10 | D470: =(B470-B469)/B469 -> 0.001223087 | E470: =C470*(1+ReservesUSDT!$E$12) -> 1.0012661e+11 | F470: =E470*(D470+1) -> 1.0024907e+11 | G470: =F470-C470 -> 5.744307e+09 | H470: =IF(G470>0,1,0) -> 1
A471: 45303 | B471: 9.664493e+10 | C471: 9.506262e+10 | D471: =(B471-B470)/B470 -> 0.00025291876 | E471: =C471*(1+ReservesUSDT!$E$12) -> 1.0071765e+11 | F471: =E471*(D471+1) -> 1.0074312e+11 | G471: =F471-C471 -> 5.6805022e+09 | H471: =IF(G471>0,1,0) -> 1
... A549: 45381 | B549: 9.8526999e+10 | C549: 1.0455308e+11 | D549: =(B549-B548)/B548 -> 0.0001315493 | E549: =C549*(1+ReservesUSDT!$E$12) -> 1.1077267e+11 | F549: =E549*(D549+1) -> 1.1078724e+11 | G549: =F549-C549 -> 6.2341635e+09 | H549: =IF(G549>0,1,0) -> 1
A550: 45382 | B550: 1.1025322e+11 | C550: 1.0453835e+11 | D550: 0 | E550: =C550*(1+ReservesUSDT!$E$13) -> 1.1083977e+11 | F550: =E550*(D550+1) -> 1.1083977e+11 | G550: =F550-C550 -> 6.3014155e+09 | H550: =IF(G550>0,1,0) -> 1
A551: 45383 | B551: 1.1012957e+11 | C551: 1.0451035e+11 | D551: =(B551-B550)/B550 -> -0.0011215202 | E551: =C551*(1+ReservesUSDT!$E$13) -> 1.1081007e+11 | F551: =E551*(D551+1) -> 1.106858e+11 | G551: =F551-C551 -> 6.1754517e+09 | H551: =IF(G551>0,1,0) -> 1
A552: 45384 | B552: 1.1005796e+11 | C552: 1.0446627e+11 | D552: =(B552-B551)/B551 -> -0.00065023084 | E552: =C552*(1+ReservesUSDT!$E$13) -> 1.1076334e+11 | F552: =E552*(D552+1) -> 1.1069132e+11 | G552: =F552-C552 -> 6.2250488e+09 | H552: =IF(G552>0,1,0) -> 1
A553: 45385 | B553: 1.1007462e+11 | C553: 1.046659e+11 | D553: =(B553-B552)/B552 -> 0.00015137192 | E553: =C553*(1+ReservesUSDT!$E$13) -> 1.1097501e+11 | F553: =E553*(D553+1) -> 1.109918e+11 | G553: =F553-C553 -> 6.3259026e+09 | H553: =IF(G553>0,1,0) -> 1
A554: 45386 | B554: 1.1032252e+11 | C554: 1.0533196e+11 | D554: =(B554-B553)/B553 -> 0.0022521474 | E554: =C554*(1+ReservesUSDT!$E$13) -> 1.1168121e+11 | F554: =E554*(D554+1) -> 1.1193273e+11 | G554: =F554-C554 -> 6.6007754e+09 | H554: =IF(G554>0,1,0) -> 1
A555: 45387 | B555: 1.1013908e+11 | C555: 1.0623293e+11 | D555: =(B555-B554)/B554 -> -0.0016627319 | E555: =C555*(1+ReservesUSDT!$E$13) -> 1.1263649e+11 | F555: =E555*(D555+1) -> 1.124492e+11 | G555: =F555-C555 -> 6.2162776e+09 | H555: =IF(G555>0,1,0) -> 1
A556: 45388 | B556: 1.1019549e+11 | C556: 1.0668897e+11 | D556: =(B556-B555)/B555 -> 0.00051217325 | E556: =C556*(1+ReservesUSDT!$E$13) -> 1.1312002e+11 | F556: =E556*(D556+1) -> 1.1317795e+11 | G556: =F556-C556 -> 6.4889884e+09 | H556: =IF(G556>0,1,0) -> 1
A557: 45389 | B557: 1.10264e+11 | C557: 1.0679333e+11 | D557: =(B557-B556)/B556 -> 0.00062168542 | E557: =C557*(1+ReservesUSDT!$E$13) -> 1.1323067e+11 | F557: =E557*(D557+1) -> 1.1330106e+11 | G557: =F557-C557 -> 6.5077359e+09 | H557: =IF(G557>0,1,0) -> 1
A558: 45390 | B558: 1.1040244e+11 | C558: 1.0690868e+11 | D558: =(B558-B557)/B557 -> 0.001255556 | E558: =C558*(1+ReservesUSDT!$E$13) -> 1.1335298e+11 | F558: =E558*(D558+1) -> 1.134953e+11 | G558: =F558-C558 -> 6.5866165e+09 | H558: =IF(G558>0,1,0) -> 1
A559: 45391 | B559: 1.1047194e+11 | C559: 1.0705101e+11 | D559: =(B559-B558)/B558 -> 0.00062950789 | E559: =C559*(1+ReservesUSDT!$E$13) -> 1.1350389e+11 | F559: =E559*(D559+1) -> 1.1357534e+11 | G559: =F559-C559 -> 6.5243265e+09 | H559: =IF(G559>0,1,0) -> 1
A560: 45392 | B560: 1.0964862e+11 | C560: 1.0712465e+11 | D560: =(B560-B559)/B559 -> -0.0074527838 | E560: =C560*(1+ReservesUSDT!$E$13) -> 1.1358196e+11 | F560: =E560*(D560+1) -> 1.1273546e+11 | G560: =F560-C560 -> 5.6108119e+09 | H560: =IF(G560>0,1,0) -> 1
A561: 45393 | B561: 1.0987038e+11 | C561: 1.0716595e+11 | D561: =(B561-B560)/B560 -> 0.0020224409 | E561: =C561*(1+ReservesUSDT!$E$13) -> 1.1362575e+11 | F561: =E561*(D561+1) -> 1.1385555e+11 | G561: =F561-C561 -> 6.6896046e+09 | H561: =IF(G561>0,1,0) -> 1
A562: 45394 | B562: 1.0979199e+11 | C562: 1.0732538e+11 | D562: =(B562-B561)/B561 -> -0.00071341894 | E562: =C562*(1+ReservesUSDT!$E$13) -> 1.1379479e+11 | F562: =E562*(D562+1) -> 1.1371361e+11 | G562: =F562-C562 -> 6.3882301e+09 | H562: =IF(G562>0,1,0) -> 1
... A640: 45472 | B640: 1.0987138e+11 | C640: 1.1260379e+11 | D640: =(B640-B639)/B639 -> 0.00057063031 | E640: =C640*(1+ReservesUSDT!$E$13) -> 1.1939137e+11 | F640: =E640*(D640+1) -> 1.194595e+11 | G640: =F640-C640 -> 6.8557162e+09 | H640: =IF(G640>0,1,0) -> 1
A641: 45473 | B641: 1.1836708e+11 | C641: 1.1262726e+11 | D641: 0 | E641: =C641*(1+ReservesUSDT!$E$14) -> 1.1868061e+11 | F641: =E641*(D641+1) -> 1.1868061e+11 | G641: =F641-C641 -> 6.0533497e+09 | H641: =IF(G641>0,1,0) -> 1
...

Sheet USDC_Final Reserve
A1: Date | B1: Circle Total Assets | C1: market_cap | D1: Daily Change | F1: New Estimate Reserves | G1: Change
A2: 44834 | B2: 47479523938 | C2: 47479523938 | D2: =0 -> 0 | E2: =C2*(1+ReservesUSDT!$H$7) -> 4.7698231e+10 | F2: =E2*(D2+1) -> 4.7698231e+10 | I2: =F2-C2 -> 2.1870692e+08 | J2: =IF(I2>0,1,0) -> 1
A3: 44835 | B3: 47479523938 | C3: 4.7317567e+10 | D3: =(B3-B2)/B2 -> 0 | E3: =C3*(1+ReservesUSDT!$H$7) -> 4.7535527e+10 | F3: =E3*(D3+1) -> 4.7535527e+10 | G3: =(F3-F2)/F2 -> -0.0034110998 | I3: =F3-C3 -> 2.1796089e+08 | J3: =IF(I3>0,1,0) -> 1
A4: 44836 | B4: 47479523938 | C4: 4.7217028e+10 | D4: =(B4-B3)/B3 -> 0 | E4: =C4*(1+ReservesUSDT!$H$7) -> 4.7434526e+10 | F4: =E4*(D4+1) -> 4.7434526e+10 | G4: =(F4-F3)/F3 -> -0.0021247532 | I4: =F4-C4 -> 2.1749778e+08 | J4: =IF(I4>0,1,0) -> 1
A5: 44837 | B5: 4.7862191e+10 | C5: 4.7429206e+10 | D5: =(B5-B4)/B4 -> 0.0080596145 | E5: =C5*(1+ReservesUSDT!$H$7) -> 4.7647681e+10 | F5: =E5*(D5+1) -> 4.8031703e+10 | G5: =(F5-F4)/F4 -> 0.01258949 | I5: =F5-C5 -> 6.0249708e+08 | J5: =IF(I5>0,1,0) -> 1
A6: 44838 | B6: 4.6383854e+10 | C6: 4.7127777e+10 | D6: =(B6-B5)/B5 -> -0.030887365 | E6: =C6*(1+ReservesUSDT!$H$7) -> 4.7344864e+10 | F6: =E6*(D6+1) -> 4.5882506e+10 | G6: =(F6-F5)/F5 -> -0.044745377 | I6: =F6-C6 -> -1.2452715e+09 | J6: =IF(I6>0,1,0) -> 0
A7: 44839 | B7: 4.6476781e+10 | C7: 4.6767463e+10 | D7: =(B7-B6)/B6 -> 0.0020034448 | E7: =C7*(1+ReservesUSDT!$H$7) -> 4.698289e+10 | F7: =E7*(D7+1) -> 4.7077017e+10 | G7: =(F7-F6)/F6 -> 0.026034136 | I7: =F7-C7 -> 3.0955455e+08 | J7: =IF(I7>0,1,0) -> 1
A8: 44840 | B8: 4.6430201e+10 | C8: 4.6412465e+10 | D8: =(B8-B7)/B7 -> -0.0010022188 | E8: =C8*(1+ReservesUSDT!$H$7) -> 4.6626257e+10 | F8: =E8*(D8+1) -> 4.6579527e+10 | G8: =(F8-F7)/F7 -> -0.01056758 | I8: =F8-C8 -> 1.6706197e+08 | J8: =IF(I8>0,1,0) -> 1
A9: 44841 | B9: 4.6634897e+10 | C9: 4.6188993e+10 | D9: =(B9-B8)/B8 -> 0.004408669 | E9: =C9*(1+ReservesUSDT!$H$7) -> 4.6401756e+10 | F9: =E9*(D9+1) -> 4.6606326e+10 | G9: =(F9-F8)/F8 -> 0.00057532732 | I9: =F9-C9 -> 4.1733228e+08 | J9: =IF(I9>0,1,0) -> 1
A10: 44842 | B10: 4.6634897e+10 | C10: 4.6210938e+10 | D10: =(B10-B9)/B9 -> 0 | E10: =C10*(1+ReservesUSDT!$H$7) -> 4.6423801e+10 | F10: =E10*(D10+1) -> 4.6423801e+10 | G10: =(F10-F9)/F9 -> -0.0039163074 | I10: =F10-C10 -> 2.1286338e+08 | J10: =IF(I10>0,1,0) -> 1
A11: 44843 | B11: 4.6634897e+10 | C11: 4.6054962e+10 | D11: =(B11-B10)/B10 -> 0 | E11: =C11*(1+ReservesUSDT!$H$7) -> 4.6267106e+10 | F11: =E11*(D11+1) -> 4.6267106e+10 | G11: =(F11-F10)/F10 -> -0.0033753078 | I11: =F11-C11 -> 2.121449e+08 | J11: =IF(I11>0,1,0) -> 1
A12: 44844 | B12: 4.6634897e+10 | C12: 4.5974636e+10 | D12: =(B12-B11)/B11 -> 0 | E12: =C12*(1+ReservesUSDT!$H$7) -> 4.6186411e+10 | F12: =E12*(D12+1) -> 4.6186411e+10 | G12: =(F12-F11)/F11 -> -0.0017441119 | I12: =F12-C12 -> 2.117749e+08 | J12: =IF(I12>0,1,0) -> 1
A13: 44845 | B13: 4.5849034e+10 | C13: 4.5967669e+10 | D13: =(B13-B12)/B12 -> -0.01685139 | E13: =C13*(1+ReservesUSDT!$H$7) -> 4.6179412e+10 | F13: =E13*(D13+1) -> 4.5401225e+10 | G13: =(F13-F12)/F12 -> -0.017000383 | I13: =F13-C13 -> -5.6644446e+08 | J13: =IF(I13>0,1,0) -> 0
A14: 44846 | B14: 4.4237042e+10 | C14: 4.5948598e+10 | D14: =(B14-B13)/B13 -> -0.035158685 | E14: =C14*(1+ReservesUSDT!$H$7) -> 4.6160253e+10 | F14: =E14*(D14+1) -> 4.4537319e+10 | G14: =(F14-F13)/F13 -> -0.019028238 | I14: =F14-C14 -> -1.4112788e+09 | J14: =IF(I14>0,1,0) -> 0
... A93: 44925 | B93: 3.8094662e+10 | C93: 4.440697e+10 | D93: =(B93-B92)/B92 -> 0.0030297045 | E93: =C93*(1+ReservesUSDT!$H$7) -> 4.4611524e+10 | F93: =E93*(D93+1) -> 4.4746683e+10 | G93: =(F93-F92)/F92 -> -0.0067558396 | I93: =F93-C93 -> 3.3971342e+08 | J93: =IF(I93>0,1,0) -> 1
A94: 44926 | B94: 44693963701 | C94: 4.4523298e+10 | D94: 0 | E94: =C94*(1+ReservesUSDT!$H$8) -> 4.4663623e+10 | F94: =E94*(D94+1) -> 4.4663623e+10 | G94: =(F94-F93)/F93 -> -0.0018562346 | I94: =F94-C94 -> 1.4032516e+08 | J94: =IF(I94>0,1,0) -> 1
A95: 44927 | B95: 44693963701 | C95: 4.4528657e+10 | D95: =(B95-B94)/B94 -> 0 | E95: =C95*(1+ReservesUSDT!$H$8) -> 4.4668999e+10 | F95: =E95*(D95+1) -> 4.4668999e+10 | G95: =(F95-F94)/F94 -> 0.00012037388 | I95: =F95-C95 -> 1.4034206e+08 | J95: =IF(I95>0,1,0) -> 1
A96: 44928 | B96: 44693963701 | C96: 4.4601804e+10 | D96: =(B96-B95)/B95 -> 0 | E96: =C96*(1+ReservesUSDT!$H$8) -> 4.4742376e+10 | F96: =E96*(D96+1) -> 4.4742376e+10 | G96: =(F96-F95)/F95 -> 0.0016426871 | I96: =F96-C96 -> 1.4057259e+08 | J96: =IF(I96>0,1,0) -> 1
A97: 44929 | B97: 4.4745122e+10 | C97: 4.4694019e+10 | D97: =(B97-B96)/B96 -> 0.0011446353 | E97: =C97*(1+ReservesUSDT!$H$8) -> 4.4834882e+10 | F97: =E97*(D97+1) -> 4.4886202e+10 | G97: =(F97-F96)/F96 -> 0.0032145263 | I97: =F97-C97 -> 1.9218282e+08 | J97: =IF(I97>0,1,0) -> 1
A98: 44930 | B98: 4.3541099e+10 | C98: 4.4202124e+10 | D98: =(B98-B97)/B97 -> -0.026908477 | E98: =C98*(1+ReservesUSDT!$H$8) -> 4.4341437e+10 | F98: =E98*(D98+1) -> 4.3148276e+10 | G98: =(F98-F97)/F97 -> -0.03871848 | I98: =F98-C98 -> -1.0538476e+09 | J98: =IF(I98>0,1,0) -> 0
A99: 44931 | B99: 4.2700806e+10 | C99: 4.4135426e+10 | D99: =(B99-B98)/B98 -> -0.019298843 | E99: =C99*(1+ReservesUSDT!$H$8) -> 4.4274529e+10 | F99: =E99*(D99+1) -> 4.3420081e+10 | G99: =(F99-F98)/F98 -> 0.0062993227 | I99: =F99-C99 -> -7.1534447e+08 | J99: =IF(I99>0,1,0) -> 0
A100: 44932 | B100: 4.2748975e+10 | C100: 4.376343e+10 | D100: =(B100-B99)/B99 -> 0.0011280478 | E100: =C100*(1+ReservesUSDT!$H$8) -> 4.390136e+10 | F100: =E100*(D100+1) -> 4.3950883e+10 | G100: =(F100-F99)/F99 -> 0.012224791 | I100: =F100-C100 -> 1.874531e+08 | J100: =IF(I100>0,1,0) -> 1
A101: 44933 | B101: 4.2748975e+10 | C101: 4.3712867e+10 | D101: =(B101-B100)/B100 -> 0 | E101: =C101*(1+ReservesUSDT!$H$8) -> 4.3850638e+10 | F101: =E101*(D101+1) -> 4.3850638e+10 | G101: =(F101-F100)/F100 -> -0.0022808469 | I101: =F101-C101 -> 1.3777091e+08 | J101: =IF(I101>0,1,0) -> 1
A102: 44934 | B102: 4.2748975e+10 | C102: 4.3815414e+10 | D102: =(B102-B101)/B101 -> 0 | E102: =C102*(1+ReservesUSDT!$H$8) -> 4.3953508e+10 | F102: =E102*(D102+1) -> 4.3953508e+10 | G102: =(F102-F101)/F101 -> 0.0023459362 | I102: =F102-C102 -> 1.3809411e+08 | J102: =IF(I102>0,1,0) -> 1
A103: 44935 | B103: 4.2716814e+10 | C103: 4.3973957e+10 | D103: =(B103-B102)/B102 -> -0.00075231128 | E103: =C103*(1+ReservesUSDT!$H$8) -> 4.4112551e+10 | F103: =E103*(D103+1) -> 4.4079364e+10 | G103: =(F103-F102)/F102 -> 0.0028633911 | I103: =F103-C103 -> 1.0540742e+08 | J103: =IF(I103>0,1,0) -> 1
A104: 44936 | B104: 4.2692718e+10 | C104: 4.4012648e+10 | D104: =(B104-B103)/B103 -> -0.0005640936 | E104: =C104*(1+ReservesUSDT!$H$8) -> 4.4151364e+10 | F104: =E104*(D104+1) -> 4.4126458e+10 | G104: =(F104-F103)/F103 -> 0.0010683916 | I104: =F104-C104 -> 1.1381024e+08 | J104: =IF(I104>0,1,0) -> 1
A105: 44937 | B105: 4.2235232e+10 | C105: 4.3685112e+10 | D105: =(B105-B104)/B104 -> -0.010715785 | E105: =C105*(1+ReservesUSDT!$H$8) -> 4.3822796e+10 | F105: =E105*(D105+1) -> 4.33532e+10 | G105: =(F105-F104)/F104 -> -0.017523691 | I105: =F105-C105 -> -3.3191221e+08 | J105: =IF(I105>0,1,0) -> 0
A106: 44938 | B106: 4.2860256e+10 | C106: 4.3929682e+10 | D106: =(B106-B105)/B105 -> 0.014798644 | E106: =C106*(1+ReservesUSDT!$H$8) -> 4.4068137e+10 | F106: =E106*(D106+1) -> 4.4720285e+10 | G106: =(F106-F105)/F105 -> 0.031533665 | I106: =F106-C106 -> 7.9060292e+08 | J106: =IF(I106>0,1,0) -> 1
... A183: 45015 | B183: 4.0818312e+10 | C183: 3.3299623e+10 | D183: =(B183-B182)/B182 -> -0.014141018 | E183: =C183*(1+ReservesUSDT!$H$8) -> 3.3404574e+10 | F183: =E183*(D183+1) -> 3.2932199e+10 | G183: =(F183-F182)/F182 -> -0.0058221247 | I183: =F183-C183 -> -3.6742345e+08 | J183: =IF(I183>0,1,0) -> 0
A184: 45016 | B184: 32571701308 | C184: 3.2875147e+10 | D184: 0 | E184: =C184*(1+ReservesUSDT!$H$9) -> 3.2875147e+10 | F184: =E184*(D184+1) -> 3.2875147e+10 | G184: =(F184-F183)/F183 -> -0.0017324113 | I184: =F184-C184 -> 0 | J184: =IF(I184>0,1,0) -> 0
A185: 45017 | B185: 32571701308 | C185: 3.2545003e+10 | D185: =(B185-B184)/B184 -> 0 | E185: =C185*(1+ReservesUSDT!$H$9) -> 3.2545003e+10 | F185: =E185*(D185+1) -> 3.2545003e+10 | G185: =(F185-F184)/F184 -> -0.010042368 | I185: =F185-C185 -> 0 | J185: =IF(I185>0,1,0) -> 0
A186: 45018 | B186: 32571701308 | C186: 3.2545587e+10 | D186: =(B186-B185)/B185 -> 0 | E186: =C186*(1+ReservesUSDT!$H$9) -> 3.2545587e+10 | F186: =E186*(D186+1) -> 3.2545587e+10 | G186: =(F186-F185)/F185 -> 1.7931375e-05 | I186: =F186-C186 -> 0 | J186: =IF(I186>0,1,0) -> 0
A187: 45019 | B187: 3.2521808e+10 | C187: 3.2564611e+10 | D187: =(B187-B186)/B186 -> -0.0015318032 | E187: =C187*(1+ReservesUSDT!$H$9) -> 3.2564611e+10 | F187: =E187*(D187+1) -> 3.2514729e+10 | G187: =(F187-F186)/F186 -> -0.00094814246 | I187: =F187-C187 -> -49882576 | J187: =IF(I187>0,1,0) -> 0
A188: 45020 | B188: 3.2208741e+10 | C188: 3.2678368e+10 | D188: =(B188-B187)/B187 -> -0.0096263731 | E188: =C188*(1+ReservesUSDT!$H$9) -> 3.2678368e+10 | F188: =E188*(D188+1) -> 3.2363794e+10 | G188: =(F188-F187)/F187 -> -0.0046420421 | I188: =F188-C188 -> -3.1457416e+08 | J188: =IF(I188>0,1,0) -> 0
A189: 45021 | B189: 3.2032818e+10 | C189: 3.2706456e+10 | D189: =(B189-B188)/B188 -> -0.0054619441 | E189: =C189*(1+ReservesUSDT!$H$9) -> 3.2706456e+10 | F189: =E189*(D189+1) -> 3.2527815e+10 | G189: =(F189-F188)/F188 -> 0.0050680351 | I189: =F189-C189 -> -1.7864083e+08 | J189: =IF(I189>0,1,0) -> 0
A190: 45022 | B190: 3.1941911e+10 | C190: 3.2640958e+10 | D190: =(B190-B189)/B189 -> -0.0028379604 | E190: =C190*(1+ReservesUSDT!$H$9) -> 3.2640958e+10 | F190: =E190*(D190+1) -> 3.2548324e+10 | G190: =(F190-F189)/F189 -> 0.00063051908 | I190: =F190-C190 -> -92633745 | J190: =IF(I190>0,1,0) -> 0
A191: 45023 | B191: 3.1809477e+10 | C191: 3.2758617e+10 | D191: =(B191-B190)/B190 -> -0.0041460743 | E191: =C191*(1+ReservesUSDT!$H$9) -> 3.2758617e+10 | F191: =E191*(D191+1) -> 3.2622797e+10 | G191: =(F191-F190)/F190 -> 0.0022880645 | I191: =F191-C191 -> -1.3581966e+08 | J191: =IF(I191>0,1,0) -> 0
A192: 45024 | B192: 3.1809477e+10 | C192: 3.2617421e+10 | D192: =(B192-B191)/B191 -> 0 | E192: =C192*(1+ReservesUSDT!$H$9) -> 3.2617421e+10 | F192: =E192*(D192+1) -> 3.2617421e+10 | G192: =(F192-F191)/F191 -> -0.00016478602 | I192: =F192-C192 -> 0 | J192: =IF(I192>0,1,0) -> 0
A193: 45025 | B193: 3.1809477e+10 | C193: 3.2622414e+10 | D193: =(B193-B192)/B192 -> 0 | E193: =C193*(1+ReservesUSDT!$H$9) -> 3.2622414e+10 | F193: =E193*(D193+1) -> 3.2622414e+10 | G193: =(F193-F192)/F192 -> 0.00015308069 | I193: =F193-C193 -> 0 | J193: =IF(I193>0,1,0) -> 0
A194: 45026 | B194: 3.0872972e+10 | C194: 3.2618005e+10 | D194: =(B194-B193)/B193 -> -0.029441084 | E194: =C194*(1+ReservesUSDT!$H$9) -> 3.2618005e+10 | F194: =E194*(D194+1) -> 3.1657696e+10 | G194: =(F194-F193)/F193 -> -0.029572256 | I194: =F194-C194 -> -9.6030943e+08 | J194: =IF(I194>0,1,0) -> 0
A195: 45027 | B195: 3.0899783e+10 | C195: 3.236991e+10 | D195: =(B195-B194)/B194 -> 0.0008684556 | E195: =C195*(1+ReservesUSDT!$H$9) -> 3.236991e+10 | F195: =E195*(D195+1) -> 3.2398022e+10 | G195: =(F195-F194)/F194 -> 0.023385342 | I195: =F195-C195 -> 28111830 | J195: =IF(I195>0,1,0) -> 1
A196: 45028 | B196: 3.07723e+10 | C196: 3.2413088e+10 | D196: =(B196-B195)/B195 -> -0.0041257063 | E196: =C196*(1+ReservesUSDT!$H$9) -> 3.2413088e+10 | F196: =E196*(D196+1) -> 3.2279361e+10 | G196: =(F196-F195)/F195 -> -0.0036625847 | I196: =F196-C196 -> -1.3372688e+08 | J196: =IF(I196>0,1,0) -> 0
... A274: 45106 | B274: 2.8560176e+10 | C274: 2.8123529e+10 | D274: =(B274-B273)/B273 -> 0.00021444317 | E274: =C274*(1+ReservesUSDT!$H$9) -> 2.8123529e+10 | F274: =E274*(D274+1) -> 2.812956e+10 | G274: =(F274-F273)/F273 -> 0.0058877436 | I274: =F274-C274 -> 6030898.7 | J274: =IF(I274>0,1,0) -> 1
A275: 45107 | B275: 27439541303 | C275: 2.7953686e+10 | D275: 0 | E275: =C275*(1+ReservesUSDT!$H$10) -> 2.8010023e+10 | F275: =E275*(D275+1) -> 2.8010023e+10 | G275: =(F275-F274)/F274 -> -0.0042495083 | I275: =F275-C275 -> 56336832 | J275: =IF(I275>0,1,0) -> 1
A276: 45108 | B276: 27439541303 | C276: 2.7367222e+10 | D276: =(B276-B275)/B275 -> 0 | E276: =C276*(1+ReservesUSDT!$H$10) -> 2.7422377e+10 | F276: =E276*(D276+1) -> 2.7422377e+10 | G276: =(F276-F275)/F275 -> -0.020979857 | I276: =F276-C276 -> 55154893 | J276: =IF(I276>0,1,0) -> 1
A277: 45109 | B277: 27439541303 | C277: 2.7391541e+10 | D277: =(B277-B276)/B276 -> 0 | E277: =C277*(1+ReservesUSDT!$H$10) -> 2.7446745e+10 | F277: =E277*(D277+1) -> 2.7446745e+10 | G277: =(F277-F276)/F276 -> 0.00088863356 | I277: =F277-C277 -> 55203905 | J277: =IF(I277>0,1,0) -> 1
A278: 45110 | B278: 2.7435647e+10 | C278: 2.738945e+10 | D278: =(B278-B277)/B277 -> -0.00014193755 | E278: =C278*(1+ReservesUSDT!$H$10) -> 2.744465e+10 | F278: =E278*(D278+1) -> 2.7440755e+10 | G278: =(F278-F277)/F277 -> -0.00021826298 | I278: =F278-C278 -> 51304265 | J278: =IF(I278>0,1,0) -> 1
A279: 45111 | B279: 2.7380017e+10 | C279: 2.7689207e+10 | D279: =(B279-B278)/B278 -> -0.002027636 | E279: =C279*(1+ReservesUSDT!$H$10) -> 2.7745011e+10 | F279: =E279*(D279+1) -> 2.7688754e+10 | G279: =(F279-F278)/F278 -> 0.0090376304 | I279: =F279-C279 -> -452972.37 | J279: =IF(I279>0,1,0) -> 0
A280: 45112 | B280: 2.7373303e+10 | C280: 2.7754724e+10 | D280: =(B280-B279)/B279 -> -0.00024523538 | E280: =C280*(1+ReservesUSDT!$H$10) -> 2.781066e+10 | F280: =E280*(D280+1) -> 2.780384e+10 | G280: =(F280-F279)/F279 -> 0.0041564157 | I280: =F280-C280 -> 49115693 | J280: =IF(I280>0,1,0) -> 1
A281: 45113 | B281: 2.7357208e+10 | C281: 2.7662666e+10 | D281: =(B281-B280)/B280 -> -0.00058797341 | E281: =C281*(1+ReservesUSDT!$H$10) -> 2.7718416e+10 | F281: =E281*(D281+1) -> 2.7702118e+10 | G281: =(F281-F280)/F280 -> -0.0036585499 | I281: =F281-C281 -> 39452628 | J281: =IF(I281>0,1,0) -> 1
A282: 45114 | B282: 2.7351859e+10 | C282: 2.757756e+10 | D282: =(B282-B281)/B281 -> -0.00019551812 | E282: =C282*(1+ReservesUSDT!$H$10) -> 2.7633139e+10 | F282: =E282*(D282+1) -> 2.7627736e+10 | G282: =(F282-F281)/F281 -> -0.002685069 | I282: =F282-C282 -> 50176021 | J282: =IF(I282>0,1,0) -> 1
A283: 45115 | B283: 2.7351859e+10 | C283: 2.7490882e+10 | D283: =(B283-B282)/B282 -> 0 | E283: =C283*(1+ReservesUSDT!$H$10) -> 2.7546286e+10 | F283: =E283*(D283+1) -> 2.7546286e+10 | G283: =(F283-F282)/F282 -> -0.0029481139 | I283: =F283-C283 -> 55404114 | J283: =IF(I283>0,1,0) -> 1
A284: 45116 | B284: 2.7351859e+10 | C284: 2.7520618e+10 | D284: =(B284-B283)/B283 -> 0 | E284: =C284*(1+ReservesUSDT!$H$10) -> 2.7576082e+10 | F284: =E284*(D284+1) -> 2.7576082e+10 | G284: =(F284-F283)/F283 -> 0.0010816711 | I284: =F284-C284 -> 55464043 | J284: =IF(I284>0,1,0) -> 1
A285: 45117 | B285: 2.7350523e+10 | C285: 2.7497914e+10 | D285: =(B285-B284)/B284 -> -4.88402e-05 | E285: =C285*(1+ReservesUSDT!$H$10) -> 2.7553333e+10 | F285: =E285*(D285+1) -> 2.7551987e+10 | G285: =(F285-F284)/F284 -> -0.00087378831 | I285: =F285-C285 -> 54072575 | J285: =IF(I285>0,1,0) -> 1
A286: 45118 | B286: 2.7302444e+10 | C286: 2.7383208e+10 | D286: =(B286-B285)/B285 -> -0.0017578935 | E286: =C286*(1+ReservesUSDT!$H$10) -> 2.7438395e+10 | F286: =E286*(D286+1) -> 2.7390161e+10 | G286: =(F286-F285)/F285 -> -0.0058734639 | I286: =F286-C286 -> 6953334.4 | J286: =IF(I286>0,1,0) -> 1
A287: 45119 | B287: 2.7322809e+10 | C287: 2.7372802e+10 | D287: =(B287-B286)/B286 -> 0.00074592064 | E287: =C287*(1+ReservesUSDT!$H$10) -> 2.7427968e+10 | F287: =E287*(D287+1) -> 2.7448427e+10 | G287: =(F287-F286)/F286 -> 0.0021272438 | I287: =F287-C287 -> 75625225 | J287: =IF(I287>0,1,0) -> 1
... A366: 45198 | B366: 2.7222006e+10 | C366: 2.557907e+10 | D366: =(B366-B365)/B365 -> 0.00067008193 | E366: =C366*(1+ReservesUSDT!$H$10) -> 2.5630621e+10 | F366: =E366*(D366+1) -> 2.5647796e+10 | G366: =(F366-F365)/F365 -> 0.0034269948 | I366: =F366-C366 -> 68725733 | J366: =IF(I366>0,1,0) -> 1
A367: 45199 | B367: 25025027673 | C367: 2.5054613e+10 | D367: 0 | E367: =C367*(1+ReservesUSDT!$H$11) -> 2.510665e+10 | F367: =E367*(D367+1) -> 2.510665e+10 | G367: =(F367-F366)/F366 -> -0.0210991 | I367: =F367-C367 -> 52037823 | J367: =IF(I367>0,1,0) -> 1
A368: 45200 | B368: 25025027673 | C368: 2.5109327e+10 | D368: =(B368-B367)/B367 -> 0 | E368: =C368*(1+ReservesUSDT!$H$11) -> 2.5161478e+10 | F368: =E368*(D368+1) -> 2.5161478e+10 | G368: =(F368-F367)/F367 -> 0.0021838065 | I368: =F368-C368 -> 52151463 | J368: =IF(I368>0,1,0) -> 1
A369: 45201 | B369: 2.4990907e+10 | C369: 2.5169346e+10 | D369: =(B369-B368)/B368 -> -0.0013634453 | E369: =C369*(1+ReservesUSDT!$H$11) -> 2.5221622e+10 | F369: =E369*(D369+1) -> 2.5187234e+10 | G369: =(F369-F368)/F368 -> 0.0010236066 | I369: =F369-C369 -> 17887820 | J369: =IF(I369>0,1,0) -> 1
A370: 45202 | B370: 2.4923306e+10 | C370: 2.5337546e+10 | D370: =(B370-B369)/B369 -> -0.002705048 | E370: =C370*(1+ReservesUSDT!$H$11) -> 2.5390172e+10 | F370: =E370*(D370+1) -> 2.532149e+10 | G370: =(F370-F369)/F369 -> 0.0053303343 | I370: =F370-C370 -> -16056164 | J370: =IF(I370>0,1,0) -> 0
A371: 45203 | B371: 2.4912573e+10 | C371: 2.5301297e+10 | D371: =(B371-B370)/B370 -> -0.00043063043 | E371: =C371*(1+ReservesUSDT!$H$11) -> 2.5353847e+10 | F371: =E371*(D371+1) -> 2.5342929e+10 | G371: =(F371-F370)/F370 -> 0.00084666728 | I371: =F371-C371 -> 41632043 | J371: =IF(I371>0,1,0) -> 1
A372: 45204 | B372: 2.4912573e+10 | C372: 2.5223334e+10 | D372: =(B372-B371)/B371 -> 0 | E372: =C372*(1+ReservesUSDT!$H$11) -> 2.5275722e+10 | F372: =E372*(D372+1) -> 2.5275722e+10 | G372: =(F372-F371)/F371 -> -0.0026518908 | I372: =F372-C372 -> 52388254 | J372: =IF(I372>0,1,0) -> 1
A373: 45205 | B373: 2.489075e+10 | C373: 2.5212208e+10 | D373: =(B373-B372)/B372 -> -0.00087600458 | E373: =C373*(1+ReservesUSDT!$H$11) -> 2.5264573e+10 | F373: =E373*(D373+1) -> 2.5242441e+10 | G373: =(F373-F372)/F372 -> -0.0013167434 | I373: =F373-C373 -> 30233263 | J373: =IF(I373>0,1,0) -> 1
A374: 45206 | B374: 2.489075e+10 | C374: 2.5496505e+10 | D374: =(B374-B373)/B373 -> 0 | E374: =C374*(1+ReservesUSDT!$H$11) -> 2.5549461e+10 | F374: =E374*(D374+1) -> 2.5549461e+10 | G374: =(F374-F373)/F373 -> 0.012162852 | I374: =F374-C374 -> 52955623 | J374: =IF(I374>0,1,0) -> 1
A375: 45207 | B375: 2.489075e+10 | C375: 2.5538082e+10 | D375: =(B375-B374)/B374 -> 0 | E375: =C375*(1+ReservesUSDT!$H$11) -> 2.5591124e+10 | F375: =E375*(D375+1) -> 2.5591124e+10 | G375: =(F375-F374)/F374 -> 0.0016306925 | I375: =F375-C375 -> 53041978 | J375: =IF(I375>0,1,0) -> 1
A376: 45208 | B376: 2.489075e+10 | C376: 2.5568023e+10 | D376: =(B376-B375)/B375 -> 0 | E376: =C376*(1+ReservesUSDT!$H$11) -> 2.5621127e+10 | F376: =E376*(D376+1) -> 2.5621127e+10 | G376: =(F376-F375)/F375 -> 0.0011724085 | I376: =F376-C376 -> 53104165 | J376: =IF(I376>0,1,0) -> 1
A377: 45209 | B377: 2.4939488e+10 | C377: 2.5508088e+10 | D377: =(B377-B376)/B376 -> 0.0019580986 | E377: =C377*(1+ReservesUSDT!$H$11) -> 2.5561067e+10 | F377: =E377*(D377+1) -> 2.5611118e+10 | G377: =(F377-F376)/F376 -> -0.00039065666 | I377: =F377-C377 -> 1.0303077e+08 | J377: =IF(I377>0,1,0) -> 1
A378: 45210 | B378: 2.4912757e+10 | C378: 2.5378591e+10 | D378: =(B378-B377)/B377 -> -0.0010718293 | E378: =C378*(1+ReservesUSDT!$H$11) -> 2.5431302e+10 | F378: =E378*(D378+1) -> 2.5404044e+10 | G378: =(F378-F377)/F377 -> -0.0080853244 | I378: =F378-C378 -> 25452704 | J378: =IF(I378>0,1,0) -> 1
A379: 45211 | B379: 2.4903874e+10 | C379: 2.5240293e+10 | D379: =(B379-B378)/B378 -> -0.00035658682 | E379: =C379*(1+ReservesUSDT!$H$11) -> 2.5292717e+10 | F379: =E379*(D379+1) -> 2.5283698e+10 | G379: =(F379-F378)/F378 -> -0.0047372865 | I379: =F379-C379 -> 43404428 | J379: =IF(I379>0,1,0) -> 1
... A458: 45290 | B458: 2.5261569e+10 | C458: 2.4770043e+10 | D458: =(B458-B457)/B457 -> 0 | E458: =C458*(1+ReservesUSDT!$H$11) -> 2.482149e+10 | F458: =E458*(D458+1) -> 2.482149e+10 | G458: =(F458-F457)/F457 -> -0.0065665691 | I458: =F458-C458 -> 51446779 | J458: =IF(I458>0,1,0) -> 1
A459: 45291 | B459: 24693288222 | C459: 2.4659691e+10 | D459: 0 | E459: =C459*(1+ReservesUSDT!$H$12) -> 2.4711627e+10 | F459: =E459*(D459+1) -> 2.4711627e+10 | G459: =(F459-F458)/F458 -> -0.0044261208 | I459: =F459-C459 -> 51936022 | J459: =IF(I459>0,1,0) -> 1
A460: 45292 | B460: 24693288222 | C460: 2.4493496e+10 | D460: =(B460-B459)/B459 -> 0 | E460: =C460*(1+ReservesUSDT!$H$12) -> 2.4545082e+10 | F460: =E460*(D460+1) -> 2.4545082e+10 | G460: =(F460-F459)/F459 -> -0.006739554 | I460: =F460-C460 -> 51585997 | J460: =IF(I460>0,1,0) -> 1
A461: 45293 | B461: 2.4652739e+10 | C461: 2.4564299e+10 | D461: =(B461-B460)/B460 -> -0.0016421135 | E461: =C461*(1+ReservesUSDT!$H$12) -> 2.4616034e+10 | F461: =E461*(D461+1) -> 2.4575612e+10 | G461: =(F461-F460)/F460 -> 0.0012438472 | I461: =F461-C461 -> 11312794 | J461: =IF(I461>0,1,0) -> 1
A462: 45294 | B462: 2.4613654e+10 | C462: 2.4792052e+10 | D462: =(B462-B461)/B461 -> -0.0015854315 | E462: =C462*(1+ReservesUSDT!$H$12) -> 2.4844267e+10 | F462: =E462*(D462+1) -> 2.4804878e+10 | G462: =(F462-F461)/F461 -> 0.0093290118 | I462: =F462-C462 -> 12825906 | J462: =IF(I462>0,1,0) -> 1
A463: 45295 | B463: 2.4616513e+10 | C463: 2.4996243e+10 | D463: =(B463-B462)/B462 -> 0.00011618003 | E463: =C463*(1+ReservesUSDT!$H$12) -> 2.5048888e+10 | F463: =E463*(D463+1) -> 2.5051798e+10 | G463: =(F463-F462)/F462 -> 0.009954488 | I463: =F463-C463 -> 55555018 | J463: =IF(I463>0,1,0) -> 1
A464: 45296 | B464: 2.4638186e+10 | C464: 2.5128588e+10 | D464: =(B464-B463)/B463 -> 0.00088041227 | E464: =C464*(1+ReservesUSDT!$H$12) -> 2.5181511e+10 | F464: =E464*(D464+1) -> 2.5203681e+10 | G464: =(F464-F463)/F463 -> 0.0060627772 | I464: =F464-C464 -> 75093682 | J464: =IF(I464>0,1,0) -> 1
A465: 45297 | B465: 2.4638186e+10 | C465: 2.5398487e+10 | D465: =(B465-B464)/B464 -> 0 | E465: =C465*(1+ReservesUSDT!$H$12) -> 2.5451979e+10 | F465: =E465*(D465+1) -> 2.5451979e+10 | G465: =(F465-F464)/F464 -> 0.0098516207 | I465: =F465-C465 -> 53492007 | J465: =IF(I465>0,1,0) -> 1
A466: 45298 | B466: 2.4638186e+10 | C466: 2.5419112e+10 | D466: =(B466-B465)/B465 -> 0 | E466: =C466*(1+ReservesUSDT!$H$12) -> 2.5472647e+10 | F466: =E466*(D466+1) -> 2.5472647e+10 | G466: =(F466-F465)/F465 -> 0.00081206494 | I466: =F466-C466 -> 53535446 | J466: =IF(I466>0,1,0) -> 1
A467: 45299 | B467: 2.4625058e+10 | C467: 2.5416438e+10 | D467: =(B467-B466)/B466 -> -0.00053283625 | E467: =C467*(1+ReservesUSDT!$H$12) -> 2.5469967e+10 | F467: =E467*(D467+1) -> 2.5456396e+10 | G467: =(F467-F466)/F466 -> -0.00063798408 | I467: =F467-C467 -> 39958492 | J467: =IF(I467>0,1,0) -> 1
A468: 45300 | B468: 2.4631609e+10 | C468: 2.535943e+10 | D468: =(B468-B467)/B467 -> 0.00026602704 | E468: =C468*(1+ReservesUSDT!$H$12) -> 2.541284e+10 | F468: =E468*(D468+1) -> 2.5419601e+10 | G468: =(F468-F467)/F467 -> -0.0014454323 | I468: =F468-C468 -> 60170253 | J468: =IF(I468>0,1,0) -> 1
A469: 45301 | B469: 2.4631609e+10 | C469: 2.5215667e+10 | D469: =(B469-B468)/B468 -> 0 | E469: =C469*(1+ReservesUSDT!$H$12) -> 2.5268774e+10 | F469: =E469*(D469+1) -> 2.5268774e+10 | G469: =(F469-F468)/F468 -> -0.0059334814 | I469: =F469-C469 -> 53106969 | J469: =IF(I469>0,1,0) -> 1
A470: 45302 | B470: 2.4641445e+10 | C470: 2.5291407e+10 | D470: =(B470-B469)/B469 -> 0.00039933336 | E470: =C470*(1+ReservesUSDT!$H$12) -> 2.5344673e+10 | F470: =E470*(D470+1) -> 2.5354794e+10 | G470: =(F470-F469)/F469 -> 0.0034042235 | I470: =F470-C470 -> 63387459 | J470: =IF(I470>0,1,0) -> 1
A471: 45303 | B471: 2.4659505e+10 | C471: 2.5286029e+10 | D471: =(B471-B470)/B470 -> 0.00073291665 | E471: =C471*(1+ReservesUSDT!$H$12) -> 2.5339284e+10 | F471: =E471*(D471+1) -> 2.5357855e+10 | G471: =(F471-F470)/F470 -> 0.00012072683 | I471: =F471-C471 -> 71826742 | J471: =IF(I471>0,1,0) -> 1
... A549: 45381 | B549: 2.464895e+10 | C549: 3.2433889e+10 | D549: =(B549-B548)/B548 -> 0 | E549: =C549*(1+ReservesUSDT!$H$12) -> 3.2502198e+10 | F549: =E549*(D549+1) -> 3.2502198e+10 | G549: =(F549-F548)/F548 -> 0.00020558535 | I549: =F549-C549 -> 68309339 | J549: =IF(I549>0,1,0) -> 1
A550: 45382 | B550: 32425876781 | C550: 3.2460742e+10 | D550: 0 | E550: =C550*(1+ReservesUSDT!$H$13) -> 3.2512208e+10 | F550: =E550*(D550+1) -> 3.2512208e+10 | G550: =(F550-F549)/F549 -> 0.00030795499 | I550: =F550-C550 -> 51465832 | J550: =IF(I550>0,1,0) -> 1
A551: 45383 | B551: 3.2414016e+10 | C551: 3.2388207e+10 | D551: =(B551-B550)/B550 -> -0.00036577484 | E551: =C551*(1+ReservesUSDT!$H$13) -> 3.2439557e+10 | F551: =E551*(D551+1) -> 3.2427692e+10 | G551: =(F551-F550)/F550 -> -0.0025995108 | I551: =F551-C551 -> 39485255 | J551: =IF(I551>0,1,0) -> 1
A552: 45384 | B552: 3.2442975e+10 | C552: 3.262767e+10 | D552: =(B552-B551)/B551 -> 0.00089341726 | E552: =C552*(1+ReservesUSDT!$H$13) -> 3.26794e+10 | F552: =E552*(D552+1) -> 3.2708597e+10 | G552: =(F552-F551)/F551 -> 0.0086625029 | I552: =F552-C552 -> 80926834 | J552: =IF(I552>0,1,0) -> 1
A553: 45385 | B553: 3.2441001e+10 | C553: 3.2751475e+10 | D553: =(B553-B552)/B552 -> -6.0844592e-05 | E553: =C553*(1+ReservesUSDT!$H$13) -> 3.2803402e+10 | F553: =E553*(D553+1) -> 3.2801406e+10 | G553: =(F553-F552)/F552 -> 0.002837458 | I553: =F553-C553 -> 49930874 | J553: =IF(I553>0,1,0) -> 1
A554: 45386 | B554: 3.2455292e+10 | C554: 3.2876498e+10 | D554: =(B554-B553)/B553 -> 0.00044050709 | E554: =C554*(1+ReservesUSDT!$H$13) -> 3.2928623e+10 | F554: =E554*(D554+1) -> 3.2943128e+10 | G554: =(F554-F553)/F553 -> 0.0043206078 | I554: =F554-C554 -> 66630296 | J554: =IF(I554>0,1,0) -> 1
A555: 45387 | B555: 3.2420952e+10 | C555: 3.3042631e+10 | D555: =(B555-B554)/B554 -> -0.0010580725 | E555: =C555*(1+ReservesUSDT!$H$13) -> 3.3095019e+10 | F555: =E555*(D555+1) -> 3.3060002e+10 | G555: =(F555-F554)/F554 -> 0.003547755 | I555: =F555-C555 -> 17371477 | J555: =IF(I555>0,1,0) -> 1
A556: 45388 | B556: 3.2420952e+10 | C556: 3.2959702e+10 | D556: =(B556-B555)/B555 -> 0 | E556: =C556*(1+ReservesUSDT!$H$13) -> 3.3011959e+10 | F556: =E556*(D556+1) -> 3.3011959e+10 | G556: =(F556-F555)/F555 -> -0.0014532079 | I556: =F556-C556 -> 52256923 | J556: =IF(I556>0,1,0) -> 1
A557: 45389 | B557: 3.2420952e+10 | C557: 3.2938115e+10 | D557: =(B557-B556)/B556 -> 0 | E557: =C557*(1+ReservesUSDT!$H$13) -> 3.2990338e+10 | F557: =E557*(D557+1) -> 3.2990338e+10 | G557: =(F557-F556)/F556 -> -0.00065496175 | I557: =F557-C557 -> 52222697 | J557: =IF(I557>0,1,0) -> 1
A558: 45390 | B558: 3.2412835e+10 | C558: 3.2969897e+10 | D558: =(B558-B557)/B557 -> -0.00025035712 | E558: =C558*(1+ReservesUSDT!$H$13) -> 3.302217e+10 | F558: =E558*(D558+1) -> 3.3013903e+10 | G558: =(F558-F557)/F557 -> 0.00071430045 | I558: =F558-C558 -> 44005751 | J558: =IF(I558>0,1,0) -> 1
A559: 45391 | B559: 3.2449897e+10 | C559: 3.2588939e+10 | D559: =(B559-B558)/B558 -> 0.0011434451 | E559: =C559*(1+ReservesUSDT!$H$13) -> 3.2640608e+10 | F559: =E559*(D559+1) -> 3.2677931e+10 | G559: =(F559-F558)/F558 -> -0.010176672 | I559: =F559-C559 -> 88991831 | J559: =IF(I559>0,1,0) -> 1
A560: 45392 | B560: 3.2321188e+10 | C560: 3.2324467e+10 | D560: =(B560-B559)/B559 -> -0.0039664077 | E560: =C560*(1+ReservesUSDT!$H$13) -> 3.2375717e+10 | F560: =E560*(D560+1) -> 3.2247301e+10 | G560: =(F560-F559)/F559 -> -0.013177993 | I560: =F560-C560 -> -77165520 | J560: =IF(I560>0,1,0) -> 0
A561: 45393 | B561: 3.2338156e+10 | C561: 3.2181972e+10 | D561: =(B561-B560)/B560 -> 0.00052498706 | E561: =C561*(1+ReservesUSDT!$H$13) -> 3.2232996e+10 | F561: =E561*(D561+1) -> 3.2249917e+10 | G561: =(F561-F560)/F560 -> 8.1126688e-05 | I561: =F561-C561 -> 67945753 | J561: =IF(I561>0,1,0) -> 1
A562: 45394 | B562: 3.2372143e+10 | C562: 3.2222451e+10 | D562: =(B562-B561)/B561 -> 0.0010509973 | E562: =C562*(1+ReservesUSDT!$H$13) -> 3.2273539e+10 | F562: =E562*(D562+1) -> 3.2307459e+10 | G562: =(F562-F561)/F561 -> 0.0017842331 | I562: =F562-C562 -> 85007431 | J562: =IF(I562>0,1,0) -> 1
... A640: 45472 | B640: 3.2459665e+10 | C640: 3.2332465e+10 | D640: =(B640-B639)/B639 -> 0 | E640: =C640*(1+ReservesUSDT!$H$13) -> 3.2383728e+10 | F640: =E640*(D640+1) -> 3.2383728e+10 | G640: =(F640-F639)/F639 -> -0.010767244 | I640: =F640-C640 -> 51262453 | J640: =IF(I640>0,1,0) -> 1
A641: 45473 | B641: 32274321543 | C641: 3.2264498e+10 | D641: =(B641-B640)/B640 -> -0.0057099715 | E641: =C641*(1+ReservesUSDT!$H$14) -> 3.2316213e+10 | F641: =E641*(D641+1) -> 3.2131688e+10 | G641: =(F641-F640)/F640 -> -0.0077829178 | I641: =F641-C641 -> -1.3281032e+08 | J641: =IF(I641>0,1,0) -> 0
...

Sheet ReservesCompositionDetailed
A1: Date | B1: CDs/CPs | C1: Cash&BanksDepo | D1: O/N Repo | E1: Reverse Repo | F1: Money Mkts | G1: Tbills | H1: Non US Tbills | I1: SecuredLoans | J1: Corporate Bonds | K1: Metals and CB | L1: BTC | M1: Other Inv (Digital tokens) | N1: Cash & Equivalents | O1: Other Assets | P1: Avg Duration CPs/CDs | Q1: Avg RatingCPs/CDs | R1: Comments | S1: Tbills Duration | T1: Non US Tbills Duration | U1: Corporate bond maturity | V1: Reverse Repo Duration | W1: BTC Price for valuation (YF price Adj close before 2024) | X1: #BTC Held | Y1: % BTC/Other Inv | Z1: O/N OIS | AA1: 3m OIS | AB1: Gold Price | AC1: FX (maybe consider them hedged and use 3m rate + Spread | AD1: UST 3m | AE1: UST curve | AF1: IG Spread
A2: 44377 | B2: 30807654349 | C2: 6282756692 | D2: 1000662458 | F2: 0 | G2: 15279528705 | H2: 0 | I2: 2517140390 | K2: 4830821277 | M2: 2054626204 | O2: =SUM(I2:M2) -> 9402587871 | P2: 150 days | Q2: A-2 | R2: =SUM(B2:M2)-ReservesUSDT!B2 -> 0
A3: 44469 | B3: 30595197667 | C3: 7237204694 | D3: 0 | F3: 999989000 | G3: 19434280489 | H3: 0 | I3: 3452029190 | K3: 3607629331 | M3: 3830441303 | N3: =SUM(B3:H3)/SUM(B3:M3) -> 0.84253025 | O3: =SUM(I3:M3) -> 10890099824 | P3: 141 days | Q3: A-2 | R3: =SUM(B3:M3)-ReservesUSDT!B3 -> 0
A4: 44561 | B4: 24165815363 | C4: 4187004507 | D4: 0 | F4: 3000083600 | G4: 34527886113 | H4: 0 | I4: 4142957365 | K4: 3628506483 | M4: 5023389246 | N4: =SUM(B4:H4)/SUM(B4:M4) -> 0.83737212 | O4: =SUM(I4:M4) -> 12794853094 | P4: 80 days | Q4: A-2 | R4: =SUM(B4:M4)-ReservesUSDT!B4 -> 0
A5: 44651 | B5: 20096579998 | C5: 4100485805 | D5: 105331269 | F5: 6798150552 | G5: 39199221428 | H5: 286155289 | I5: 3149732368 | K5: 3729529946 | M5: 4959634446 | N5: =SUM(B5:H5)/SUM(B5:M5) -> 0.85636733 | O5: =SUM(I5:M5) -> 11838896760 | P5: 44 days | Q5: A-1 | R5: =SUM(B5:M5)-ReservesUSDT!B5 -> 0
A6: 44742 | B6: 8402426505 | C6: 5418232067 | D6: 2992015954 | F6: 6810253431 | G6: 28856434491 | H6: 397150678 | I6: 4494373260 | K6: 3486896735 | M6: 5551836303 | N6: =SUM(B6:H6)/SUM(B6:M6) -> 0.79621768 | O6: =SUM(I6:M6) -> 13533106298 | P6: 27 days | Q6: A-1 | R6: =SUM(B6:M6)-ReservesUSDT!B6 -> 0
A7: 44834 | B7: 49981855 | C7: 6077722223 | E7: 3023814393 | F7: 7101935591 | G7: 39678465980 | H7: 182114357 | I7: 6135946415 | K7: 3194369894 | L7: 0 | M7: 2617267750 | N7: =SUM(B7:H7)/SUM(B7:M7) -> 0.8244593 | O7: =SUM(I7:M7) -> 11947584059 | P7: 15 days | Q7: A-1+ | R7: 10bps redepemption | S7: 45 | T7: 90 | U7: - | V7: - | W7: 19312 | X7: =L7/W7 -> 0
A8: 44926 | B8: - | C8: 5318311794 | E8: 3046093954 | F8: 7372926391 | G8: 39230259046 | H8: 93849833 | I8: 5852823328 | K8: 3444097599 | L8: 0 | M8: 2685786230 | N8: =SUM(B8:H8)/SUM(B8:M8) -> 0.82127139 | O8: =SUM(I8:M8) -> 11982707157 | P8: - | Q8: - | R8: 10bps redepemption | S8: 60 | T8: 90 | U8: - | V8: - | W8: 16625 | X8: =L8/W8 -> 0
A9: 45016 | B9: - | C9: 481350555 | D9: =7500000000 -> 7500000000 | E9: 786850807 | F9: 7453204896 | G9: 53044762609 | H9: 47680940 | I9: 5349078821 | J9: 140669244 | K9: =3391091658 -> 3391091658 | L9: 1500064140 | M9: =2138395675 -> 2138395675 | N9: =SUM(B9:H9)/SUM(B9:M9) -> 0.84701433 | O9: =SUM(I9:M9) -> 12519299538 | R9: 10bps redepemption | S9: 90 | T9: 180 | U9: 210 | V9: 90 | W9: 28411 | X9: =L9/W9 -> 52798.71 | Y9: =L9/(L9+M9) -> 0.41227998
A10: 45107 | B10: - | C10: 90811797 | D10: =8893000000 -> 8893000000 | E10: 577232281 | F10: 8133865426 | G10: 55809730658 | H10: 62937172 | I10: 5504292639 | J10: 115496758 | K10: =3270216824 -> 3270216824 | L10: 2365438303 | M10: =1676229360 -> 1676229360 | N10: =SUM(B10:H10)/SUM(B10:M10) -> 0.85049959 | O10: =SUM(I10:M10) -> 12931673884 | P10: - | Q10: - | R10: 10bps redepemption | S10: 90 | T10: 450 | U10: 180 | V10: 90 | W10: 30590 | X10: =L10/W10 -> 77327.176 | Y10: =L10/(L10+M10) -> 0.58526294
A11: 45199 | B11: - | C11: 292641978 | D11: =8203000000 -> 8203000000 | E11: 652002048 | F11: 8233687005 | G11: 56611569049 | H11: 65248902 | I11: 5168269890 | J11: 88570555 | K11: =3149722956 -> 3149722956 | L11: 1661948724 | M11: =2257992725 -> 2257992725 | N11: =SUM(B11:H11)/SUM(B11:M11) -> 0.85730677 | O11: =SUM(I11:M11) -> 12326504850 | R11: 10bps redepemption | S11: 90 | T11: 450 | U11: 150 | V11: 90 | W11: 27983 | X11: =L11/W11 -> 59391.371 | Y11: =L11/(L11+M11) -> 0.42397284
A12: 45291 | B12: - | C12: 394746540 | D12: =9359124175 -> 9359124175 | E12: 815301051 | F12: 8339339590 | G12: 63086013400 | H12: 69259151 | I12: 4804666695 | J12: 44412069 | K12: =3514935634 -> 3514935634 | L12: 2820162484 | M12: =3772433767 -> 3772433767 | N12: =SUM(B12:H12)/SUM(B12:M12) -> 0.84584055 | O12: =SUM(I12:M12) -> 14956610649 | R12: 10bps redepemption | S12: 83 | T12: 423 | U12: 137 | V12: 90 | W12: 44167 | X12: =L12/W12 -> 63852.254 | Y12: =L12/(L12+M12) -> 0.42777722
A13: 45382 | B13: - | C13: 100264024 | D13: =11311946813 -> 11311946813 | E13: 838514084 | F13: 6279586483 | G13: 74045290303 | H13: 122452086 | I13: 4735309369 | J13: 25111317 | K13: =3650599989 -> 3650599989 | L13: 5374726904 | M13: =3805605037 -> 3805605037 | N13: =SUM(B13:H13)/SUM(B13:M13) -> 0.84049826 | O13: =SUM(I13:M13) -> 17591352616 | R13: 10bps redepemption | S13: 90 | T13: 250 | U13: 150 | V13: 90 | W13: 71326 | X13: =L13/W13 -> 75354.386 | Y13: =L13/(L13+M13) -> 0.58546106
A14: 45473 | B14: - | C14: 109867228 | D14: =11286972273 -> 11286972273 | E14: 997373133 | F14: 6355402510 | G14: 80948647984 | H14: 72412344 | I14: 6571282257 | J14: 17377107 | K14: =3814334566 -> 3814334566 | L14: 4734040881 | M14: =3528626010 -> 3528626010 | N14: =SUM(B14:H14)/SUM(B14:M14) -> 0.8423992 | O14: =SUM(I14:M14) -> 18665660821 | R14: 10bps redepemption | S14: 90 | T14: 360 | U14: 180 | V14: 90 | W14: 62824 | X14: =L14/W14 -> 75354.019 | Y14: =L14/(L14+M14) -> 0.57294345
A15: 45565 | B15: - | C15: 78413266 | D15: =12542965206 -> 12542965206 | E15: 1566204143 | F15: =6436961021 -> 6436961021 | G15: 84548020412 | H15: 91310586 | I15: 6721817210 | J15: 17547614 | K15: =4962116508 -> 4962116508 | L15: 4782917086 | M15: =3723727227 -> 3723727227 | N15: =SUM(B15:H15)/SUM(B15:M15) -> 0.83894315 | O15: =SUM(I15:M15) -> 20208125645 | R15: 10bps redepemption | S15: 90 | T15: 270 | U15: 180 | V15: 90 | W15: 63473 | X15: =L15/W15 -> 75353.569 | Y15: =L15/(L15+M15) -> 0.56225662
A16: 45657 | B16: - | C16: 108844601 | D16: =14101623321 -> 14101623321 | E16: 3077452467 | F16: 6506444067 | G16: 94471651607 | H16: 69263354 | I16: 8194007406 | J16: 14270773 | K16: =5318875241 -> 5318875241 | L16: 7857529277 | M16: =3984793433 -> 3984793433 | N16: =SUM(B16:H16)/SUM(B16:M16) -> 0.82346112 | O16: =SUM(I16:M16) -> 25369476130 | R16: 10bps redepemption | S16: 90 | T16: 300 | U16: 150 | V16: 90 | W16: 93812 | X16: =L16/W16 -> 83758.253 | Y16: =L16/(L16+M16) -> 0.66351251
A17: 45747 | B17: - | C17: 64302555 | D17: =15093981718 -> 15093981718 | E17: 1613610695 | F17: 6285638008 | G17: 98523657338 | H17: 65886184 | I17: 8825524405 | J17: 14354777 | K17: =6663205657 -> 6663205657 | L17: 7662210442 | M17: =4462144209 -> 4462144209 | N17: =SUM(B17:H17)/SUM(B17:M17) -> 0.81492193 | O17: =SUM(I17:M17) -> 27627439490 | R17: 10bps redepemption | S17: 90 | T17: 270 | U17: 120 | V17: 90 | W17: 82704 | X17: =L17/W17 -> 92646.189 | Y17: =L17/(L17+M17) -> 0.63196852
A18: 45838 | B18: - | C18: 32430726 | D18: =16341965339 -> 16341965339 | E18: 1666870344 | F18: 6345999587 | G18: 105518993610 | H18: 48169774 | I18: 10137145089 | J18: 14605090 | K18: =8725417224 -> 8725417224 | L18: 8928174931 | M18: =4815162084 -> 4815162084 | N18: =SUM(B18:H18)/SUM(B18:M18) -> 0.79935096 | O18: =SUM(I18:M18) -> 32620504418 | R18: 10bps redepemption | S18: 90 | T18: 360 | U18: 120 | V18: 90 | W18: 107240 | X18: =L18/W18 -> 83254.149 | Y18: =L18/(L18+M18) -> 0.64963661
A19: 45930 | B19: - | C19: 30100334 | D19: =17991468781 -> 17991468781 | E19: 3056191686 | F19: 6409774689 | G19: 112417034272 | H19: 47901280 | I19: 14604086904 | J19: 14672361 | K19: =12921449635 -> 12921449635 | L19: 9856011011 | M19: =3874458261 -> 3874458261 | N19: =SUM(B19:H19)/SUM(B19:M19) -> 0.77226597 | O19: =SUM(I19:M19) -> 41270678172 | R19: 10bps redepemption | S19: 90 | T19: 270 | U19: 90 | V19: 90 | W19: 114160 | X19: =L19/W19 -> 86335.065 | Y19: =L19/(L19+M19) -> 0.7178204
A20: 46022 | B20: - | C20: 33952735 | D20: =19279408559 -> 19279408559 | E20: 5548439332 | F20: 0 | G20: 122325714946 | H20: 0 | I20: 17043516665 | J20: 3031239 | K20: =17450435088 -> 17450435088 | L20: 8430374292 | M20: =2762856288 -> 2762856288 | N20: =SUM(B20:H20)/SUM(B20:M20) -> 0.76311307 | O20: =SUM(I20:M20) -> 45690213572 | R20: 10bps redepemption | S20: 90 | T20: - | U20: 360 | V20: 90 | W20: 87647 | X20: =L20/W20 -> 96185.543 | Y20: =L20/(L20+M20) -> 0.75316721
R21: =SUM(B21:M21)-ReservesUSDT!B21 -> 0
R22: =SUM(B22:M22)-ReservesUSDT!B22 -> 0
R23: =SUM(B23:M23)-ReservesUSDT!B23 -> 0
R24: =SUM(B24:M24)-ReservesUSDT!B24 -> 0
R25: =SUM(B25:M25)-ReservesUSDT!B25 -> 0
R26: =SUM(B26:M26)-ReservesUSDT!B26 -> 0
R27: =SUM(B27:M27)-ReservesUSDT!B27 -> 0
R28: =SUM(B28:M28)-ReservesUSDT!B28 -> 0
R29: =SUM(B29:M29)-ReservesUSDT!B29 -> 0
R30: =SUM(B30:M30)-ReservesUSDT!B30 -> 0

Sheet Tether Assets
I1: Duration o/n repo: | J1: =1/360 -> 0.0027777778 | L1: Duration MM | M1: =2/360 -> 0.0055555556
A2: Date | B2: CDs | C2: # BTC | D2: BTC Price | E2: BTC Value | F2: Oz Gold | G2: Gold Price | H2: Gold Value | I2: Cash + Banks Depo | J2: O/n Repo MtM | K2: Reverse Repo MtM | L2: Reverse Repo Duration | M2: Money Makts MtM | N2: Tbills Notional | O2: Tbills Duration | P2: Non US Tbills Notionals | Q2: NonUSTBills Duration | R2: Secured Loans | S2: Corporate Bonds | T2: Corporate Bonds | U2: Other inv | V2: Total Asset Values | W2: L | X2: D | Y2: K | Z2: New Estimate Reserves | AA2: USDT Market Cap
A3: 44834 | B3: 49981855 | C3: 81315.278 | D3: =_xlfn.XLOOKUP(A3,'BBG Data'!A:A,'BBG Data'!B:B) -> 19425.13 | E3: =C3*D3 -> 1.5795598e+09 | F3: 1827431.7 | G3: =_xlfn.XLOOKUP(A3,'BBG Data'!A:A,'BBG Data'!C:C) -> 1660.61 | H3: =G3*F3 -> 3.0346514e+09 | I3: 6077722223 | J3: 2.721433e+09 | K3: 3.0238144e+08 | L3: 90 | M3: 7101935591 | N3: 39678465980 | O3: 45 | P3: 182114357 | Q3: 90 | R3: 6135946415 | S3: 1.5971849e+08 | T3: 180 | U3: 1046907100 | V3: =U3+S3+R3+P3+N3+M3+K3+J3+I3+H3+E3+B3 -> 6.8070818e+10 | W3: =(I3+J3)/V3 -> 0.12926472 | X3: =N3/V3 -> 0.5828998 | Y3: =USDT_FinalReserves!G2/USDT_FinalReserves!$F2 -> 0.0037687243 | Z3: 6.8276251e+10 | AA3: 6.8018937e+10
A4: 44835 | B4: 49981855 | C4: 81315.278 | D4: =_xlfn.XLOOKUP(A4,'BBG Data'!A:A,'BBG Data'!B:B) -> 19252.71 | E4: =C4*D4 -> 1.5655395e+09 | F4: 1827431.7 | G4: =_xlfn.XLOOKUP(A4,'BBG Data'!A:A,'BBG Data'!C:C) -> 1660.61 | H4: =G4*F4 -> 3.0346514e+09 | I4: 6077722223 | J4: =J3-$J$1*J3*_xlfn.XLOOKUP(A4,'BBG Data'!A:A,'BBG Data'!F:F) -> 2.721433e+09 | K4: =K3-K3*L4/360*_xlfn.XLOOKUP(A4,'BBG Data'!A:A,'BBG Data'!J:J) -> 3.0238144e+08 | L4: 90 | M4: =M3-M3*$M$1*_xlfn.XLOOKUP(A4,'BBG Data'!A:A,'BBG Data'!F:F) -> 7101935591 | N4: =N3-N3*O4/360*_xlfn.XLOOKUP('Tether Assets'!A4,'BBG Data'!A:A,'BBG Data'!V:V) -> 39678465980 | O4: 45 | P4: =P3-P3*Q4/360*_xlfn.XLOOKUP(A4,'BBG Data'!A:A,'BBG Data'!V:V) -> 182114357 | Q4: 90 | R4: 6135946415 | S4: =S3-S3*T4/360*_xlfn.XLOOKUP('Tether Assets'!A4,'BBG Data'!A:A,'BBG Data'!AB:AB) -> 1.5971849e+08 | T4: 180 | U4: 1046907100 | V4: =U4+S4+R4+P4+N4+M4+K4+J4+I4+H4+E4+B4 -> 6.8056797e+10 | W4: =(I4+J4)/V4 -> 0.12929135 | X4: =N4/V4 -> 0.58301988 | Y4: =USDT_FinalReserves!G3/USDT_FinalReserves!$F3 -> 0.0035634907 | Z4: 6.8275764e+10 | AA4: 6.8032464e+10
A5: 44836 | B5: 49981855 | C5: 81315.278 | D5: =_xlfn.XLOOKUP(A5,'BBG Data'!A:A,'BBG Data'!B:B) -> 19234.63 | E5: =C5*D5 -> 1.5640693e+09 | F5: 1827431.7 | G5: =_xlfn.XLOOKUP(A5,'BBG Data'!A:A,'BBG Data'!C:C) -> 1660.61 | H5: =G5*F5 -> 3.0346514e+09 | I5: 6077722223 | J5: =J4-$J$1*J4*_xlfn.XLOOKUP(A5,'BBG Data'!A:A,'BBG Data'!F:F) -> 2.721433e+09 | K5: =K4-K4*L5/360*_xlfn.XLOOKUP(A5,'BBG Data'!A:A,'BBG Data'!J:J) -> 3.0238144e+08 | L5: 90 | M5: =M4-M4*$M$1*_xlfn.XLOOKUP(A5,'BBG Data'!A:A,'BBG Data'!F:F) -> 7101935591 | N5: =N4-N4*O5/360*_xlfn.XLOOKUP('Tether Assets'!A5,'BBG Data'!A:A,'BBG Data'!V:V) -> 39678465980 | O5: 45 | P5: =P4-P4*Q5/360*_xlfn.XLOOKUP(A5,'BBG Data'!A:A,'BBG Data'!V:V) -> 182114357 | Q5: 90 | R5: 6135946415 | S5: =S4-S4*T5/360*_xlfn.XLOOKUP('Tether Assets'!A5,'BBG Data'!A:A,'BBG Data'!AB:AB) -> 1.5971849e+08 | T5: 180 | U5: 1046907100 | V5: =U5+S5+R5+P5+N5+M5+K5+J5+I5+H5+E5+B5 -> 6.8055327e+10 | W5: =(I5+J5)/V5 -> 0.12929414 | X5: =N5/V5 -> 0.58303248 | Y5: =USDT_FinalReserves!G4/USDT_FinalReserves!$F4 -> 0.003747203 | Z5: 6.8240924e+10 | AA5: 6.7985211e+10
A6: 44837 | B6: 49981855 | C6: 81315.278 | D6: =_xlfn.XLOOKUP(A6,'BBG Data'!A:A,'BBG Data'!B:B) -> 19597.13 | E6: =C6*D6 -> 1.5935461e+09 | F6: 1827431.7 | G6: =_xlfn.XLOOKUP(A6,'BBG Data'!A:A,'BBG Data'!C:C) -> 1699.89 | H6: =G6*F6 -> 3.1064329e+09 | I6: 6077722223 | J6: =J5-$J$1*J5*_xlfn.XLOOKUP(A6,'BBG Data'!A:A,'BBG Data'!F:F) -> 2.7212818e+09 | K6: =K5-K5*L6/360*_xlfn.XLOOKUP(A6,'BBG Data'!A:A,'BBG Data'!J:J) -> 3.0207377e+08 | L6: 90 | M6: =M5-M5*$M$1*_xlfn.XLOOKUP(A6,'BBG Data'!A:A,'BBG Data'!F:F) -> 7.1011465e+09 | N6: =N5-N5*O6/360*_xlfn.XLOOKUP('Tether Assets'!A6,'BBG Data'!A:A,'BBG Data'!V:V) -> 3.9876858e+10 | O6: 45 | P6: =P5-P5*Q6/360*_xlfn.XLOOKUP(A6,'BBG Data'!A:A,'BBG Data'!V:V) -> 1.839355e+08 | Q6: 90 | R6: 6135946415 | S6: =S5-S5*T6/360*_xlfn.XLOOKUP('Tether Assets'!A6,'BBG Data'!A:A,'BBG Data'!AB:AB) -> 1.6444616e+08 | T6: 180 | U6: 1046907100 | V6: =U6+S6+R6+P6+N6+M6+K6+J6+I6+H6+E6+B6 -> 6.8360279e+10 | W6: =(I6+J6)/V6 -> 0.12871516 | X6: =N6/V6 -> 0.58333376 | Y6: =USDT_FinalReserves!G5/USDT_FinalReserves!$F5 -> 0.0082128578 | Z6: 6.8414751e+10 | AA6: 6.7852871e+10
A7: 44838 | B7: 49981855 | C7: 81315.278 | D7: =_xlfn.XLOOKUP(A7,'BBG Data'!A:A,'BBG Data'!B:B) -> 20340.91 | E7: =C7*D7 -> 1.6540268e+09 | F7: 1827431.7 | G7: =_xlfn.XLOOKUP(A7,'BBG Data'!A:A,'BBG Data'!C:C) -> 1726.13 | H7: =G7*F7 -> 3.1543847e+09 | I7: 6077722223 | J7: =J6-$J$1*J6*_xlfn.XLOOKUP(A7,'BBG Data'!A:A,'BBG Data'!F:F) -> 2.7209794e+09 | K7: =K6-K6*L7/360*_xlfn.XLOOKUP(A7,'BBG Data'!A:A,'BBG Data'!J:J) -> 3.009425e+08 | L7: 90 | M7: =M6-M6*$M$1*_xlfn.XLOOKUP(A7,'BBG Data'!A:A,'BBG Data'!F:F) -> 7.0995685e+09 | N7: =N6-N6*O7/360*_xlfn.XLOOKUP('Tether Assets'!A7,'BBG Data'!A:A,'BBG Data'!V:V) -> 3.9114213e+10 | O7: 45 | P7: =P6-P6*Q7/360*_xlfn.XLOOKUP(A7,'BBG Data'!A:A,'BBG Data'!V:V) -> 1.7689997e+08 | Q7: 90 | R7: 6135946415 | S7: =S6-S6*T7/360*_xlfn.XLOOKUP('Tether Assets'!A7,'BBG Data'!A:A,'BBG Data'!AB:AB) -> 1.681462e+08 | T7: 180 | U7: 1046907100 | V7: =U7+S7+R7+P7+N7+M7+K7+J7+I7+H7+E7+B7 -> 6.7699719e+10 | W7: =(I7+J7)/V7 -> 0.12996659 | X7: =N7/V7 -> 0.57776035 | Y7: =USDT_FinalReserves!G6/USDT_FinalReserves!$F6 -> -0.0059517018 | Z7: 6.755343e+10 | AA7: 6.7955488e+10
A8: 44839 | B8: 49981855 | C8: 81315.278 | D8: =_xlfn.XLOOKUP(A8,'BBG Data'!A:A,'BBG Data'!B:B) -> 19988.42 | E8: =C8*D8 -> 1.6253639e+09 | F8: 1827431.7 | G8: =_xlfn.XLOOKUP(A8,'BBG Data'!A:A,'BBG Data'!C:C) -> 1716.26 | H8: =G8*F8 -> 3.136348e+09 | I8: 6077722223 | J8: =J7-$J$1*J7*_xlfn.XLOOKUP(A8,'BBG Data'!A:A,'BBG Data'!F:F) -> 2.7209794e+09 | K8: =K7-K7*L8/360*_xlfn.XLOOKUP(A8,'BBG Data'!A:A,'BBG Data'!J:J) -> 2.9694448e+08 | L8: 90 | M8: =M7-M7*$M$1*_xlfn.XLOOKUP(A8,'BBG Data'!A:A,'BBG Data'!F:F) -> 7.0995685e+09 | N8: =N7-N7*O8/360*_xlfn.XLOOKUP('Tether Assets'!A8,'BBG Data'!A:A,'BBG Data'!V:V) -> 3.9163106e+10 | O8: 45 | P8: =P7-P7*Q8/360*_xlfn.XLOOKUP(A8,'BBG Data'!A:A,'BBG Data'!V:V) -> 1.7734222e+08 | Q8: 90 | R8: 6135946415 | S8: =S7-S7*T8/360*_xlfn.XLOOKUP('Tether Assets'!A8,'BBG Data'!A:A,'BBG Data'!AB:AB) -> 1.6775106e+08 | T8: 180 | U8: 1046907100 | V8: =U8+S8+R8+P8+N8+M8+K8+J8+I8+H8+E8+B8 -> 6.7697961e+10 | W8: =(I8+J8)/V8 -> 0.12996996 | X8: =N8/V8 -> 0.57849757 | Y8: =USDT_FinalReserves!G7/USDT_FinalReserves!$F7 -> 0.003742858 | Z8: 6.8402494e+10 | AA8: 6.8146473e+10
A9: 44840 | B9: 49981855 | C9: 81315.278 | D9: =_xlfn.XLOOKUP(A9,'BBG Data'!A:A,'BBG Data'!B:B) -> 20051.13 | E9: =C9*D9 -> 1.6304632e+09 | F9: 1827431.7 | G9: =_xlfn.XLOOKUP(A9,'BBG Data'!A:A,'BBG Data'!C:C) -> 1712.53 | H9: =G9*F9 -> 3.1295317e+09 | I9: 6077722223 | J9: =J8-$J$1*J8*_xlfn.XLOOKUP(A9,'BBG Data'!A:A,'BBG Data'!F:F) -> 2.7209038e+09 | K9: =K8-K8*L9/360*_xlfn.XLOOKUP(A9,'BBG Data'!A:A,'BBG Data'!J:J) -> 2.9275533e+08 | L9: 90 | M9: =M8-M8*$M$1*_xlfn.XLOOKUP(A9,'BBG Data'!A:A,'BBG Data'!F:F) -> 7.099174e+09 | N9: =N8-N8*O9/360*_xlfn.XLOOKUP('Tether Assets'!A9,'BBG Data'!A:A,'BBG Data'!V:V) -> 3.9138629e+10 | O9: 45 | P9: =P8-P8*Q9/360*_xlfn.XLOOKUP(A9,'BBG Data'!A:A,'BBG Data'!V:V) -> 1.7712054e+08 | Q9: 90 | R9: 6135946415 | S9: =S8-S8*T9/360*_xlfn.XLOOKUP('Tether Assets'!A9,'BBG Data'!A:A,'BBG Data'!AB:AB) -> 1.652264e+08 | T9: 180 | U9: 1046907100 | V9: =U9+S9+R9+P9+N9+M9+K9+J9+I9+H9+E9+B9 -> 6.7664362e+10 | W9: =(I9+J9)/V9 -> 0.13003339 | X9: =N9/V9 -> 0.57842309 | Y9: =USDT_FinalReserves!G8/USDT_FinalReserves!$F8 -> 0.0032740351 | Z9: 6.8473697e+10 | AA9: 6.8249512e+10
A10: 44841 | B10: 49981855 | C10: 81315.278 | D10: =_xlfn.XLOOKUP(A10,'BBG Data'!A:A,'BBG Data'!B:B) -> 19551.56 | E10: =C10*D10 -> 1.5898405e+09 | F10: 1827431.7 | G10: =_xlfn.XLOOKUP(A10,'BBG Data'!A:A,'BBG Data'!C:C) -> 1694.82 | H10: =G10*F10 -> 3.0971678e+09 | I10: 6077722223 | J10: =J9-$J$1*J9*_xlfn.XLOOKUP(A10,'BBG Data'!A:A,'BBG Data'!F:F) -> 2.7209038e+09 | K10: =K9-K9*L10/360*_xlfn.XLOOKUP(A10,'BBG Data'!A:A,'BBG Data'!J:J) -> 2.915082e+08 | L10: 90 | M10: =M9-M9*$M$1*_xlfn.XLOOKUP(A10,'BBG Data'!A:A,'BBG Data'!F:F) -> 7.099174e+09 | N10: =N9-N9*O10/360*_xlfn.XLOOKUP('Tether Assets'!A10,'BBG Data'!A:A,'BBG Data'!V:V) -> 3.924626e+10 | O10: 45 | P10: =P9-P9*Q10/360*_xlfn.XLOOKUP(A10,'BBG Data'!A:A,'BBG Data'!V:V) -> 1.780947e+08 | Q10: 90 | R10: 6135946415 | S10: =S9-S9*T10/360*_xlfn.XLOOKUP('Tether Assets'!A10,'BBG Data'!A:A,'BBG Data'!AB:AB) -> 1.5603982e+08 | T10: 180 | U10: 1046907100 | V10: =U10+S10+R10+P10+N10+M10+K10+J10+I10+H10+E10+B10 -> 6.7689547e+10 | W10: =(I10+J10)/V10 -> 0.129985 | X10: =N10/V10 -> 0.57979795 | Y10: =USDT_FinalReserves!G9/USDT_FinalReserves!$F9 -> 0.004139391 | Z10: 6.8523834e+10 | AA10: 6.8240187e+10
A11: 44842 | B11: 49981855 | C11: 81315.278 | D11: =_xlfn.XLOOKUP(A11,'BBG Data'!A:A,'BBG Data'!B:B) -> 19456.38 | E11: =C11*D11 -> 1.5821009e+09 | F11: 1827431.7 | G11: =_xlfn.XLOOKUP(A11,'BBG Data'!A:A,'BBG Data'!C:C) -> 1694.82 | H11: =G11*F11 -> 3.0971678e+09 | I11: 6077722223 | J11: =J10-$J$1*J10*_xlfn.XLOOKUP(A11,'BBG Data'!A:A,'BBG Data'!F:F) -> 2.7209038e+09 | K11: =K10-K10*L11/360*_xlfn.XLOOKUP(A11,'BBG Data'!A:A,'BBG Data'!J:J) -> 2.915082e+08 | L11: 90 | M11: =M10-M10*$M$1*_xlfn.XLOOKUP(A11,'BBG Data'!A:A,'BBG Data'!F:F) -> 7.099174e+09 | N11: =N10-N10*O11/360*_xlfn.XLOOKUP('Tether Assets'!A11,'BBG Data'!A:A,'BBG Data'!V:V) -> 3.924626e+10 | O11: 45 | P11: =P10-P10*Q11/360*_xlfn.XLOOKUP(A11,'BBG Data'!A:A,'BBG Data'!V:V) -> 1.780947e+08 | Q11: 90 | R11: 6135946415 | S11: =S10-S10*T11/360*_xlfn.XLOOKUP('Tether Assets'!A11,'BBG Data'!A:A,'BBG Data'!AB:AB) -> 1.5603982e+08 | T11: 180 | U11: 1046907100 | V11: =U11+S11+R11+P11+N11+M11+K11+J11+I11+H11+E11+B11 -> 6.7681807e+10 | W11: =(I11+J11)/V11 -> 0.12999987 | X11: =N11/V11 -> 0.57986425 | Y11: =USDT_FinalReserves!G10/USDT_FinalReserves!$F10 -> 0.0036548027 | Z11: 6.8610782e+10 | AA11: 6.8360023e+10
A12: 44843 | B12: 49981855 | C12: 81315.278 | D12: =_xlfn.XLOOKUP(A12,'BBG Data'!A:A,'BBG Data'!B:B) -> 19485.5 | E12: =C12*D12 -> 1.5844689e+09 | F12: 1827431.7 | G12: =_xlfn.XLOOKUP(A12,'BBG Data'!A:A,'BBG Data'!C:C) -> 1694.82 | H12: =G12*F12 -> 3.0971678e+09 | I12: 6077722223 | J12: =J11-$J$1*J11*_xlfn.XLOOKUP(A12,'BBG Data'!A:A,'BBG Data'!F:F) -> 2.7209038e+09 | K12: =K11-K11*L12/360*_xlfn.XLOOKUP(A12,'BBG Data'!A:A,'BBG Data'!J:J) -> 2.915082e+08 | L12: 90 | M12: =M11-M11*$M$1*_xlfn.XLOOKUP(A12,'BBG Data'!A:A,'BBG Data'!F:F) -> 7.099174e+09 | N12: =N11-N11*O12/360*_xlfn.XLOOKUP('Tether Assets'!A12,'BBG Data'!A:A,'BBG Data'!V:V) -> 3.924626e+10 | O12: 45 | P12: =P11-P11*Q12/360*_xlfn.XLOOKUP(A12,'BBG Data'!A:A,'BBG Data'!V:V) -> 1.780947e+08 | Q12: 90 | R12: 6135946415 | S12: =S11-S11*T12/360*_xlfn.XLOOKUP('Tether Assets'!A12,'BBG Data'!A:A,'BBG Data'!AB:AB) -> 1.5603982e+08 | T12: 180 | U12: 1046907100 | V12: =U12+S12+R12+P12+N12+M12+K12+J12+I12+H12+E12+B12 -> 6.7684175e+10 | W12: =(I12+J12)/V12 -> 0.12999532 | X12: =N12/V12 -> 0.57984396 | Y12: =USDT_FinalReserves!G11/USDT_FinalReserves!$F11 -> 0.003803577 | Z12: 6.8645759e+10 | AA12: 6.838466e+10
A13: 44844 | B13: 49981855 | C13: 81315.278 | D13: =_xlfn.XLOOKUP(A13,'BBG Data'!A:A,'BBG Data'!B:B) -> 19241.2 | E13: =C13*D13 -> 1.5646035e+09 | F13: 1827431.7 | G13: =_xlfn.XLOOKUP(A13,'BBG Data'!A:A,'BBG Data'!C:C) -> 1668.61 | H13: =G13*F13 -> 3.0492709e+09 | I13: 6077722223 | J13: =J12-$J$1*J12*_xlfn.XLOOKUP(A13,'BBG Data'!A:A,'BBG Data'!F:F) -> 2.7209038e+09 | K13: =K12-K12*L13/360*_xlfn.XLOOKUP(A13,'BBG Data'!A:A,'BBG Data'!J:J) -> 2.915082e+08 | L13: 90 | M13: =M12-M12*$M$1*_xlfn.XLOOKUP(A13,'BBG Data'!A:A,'BBG Data'!F:F) -> 7.099174e+09 | N13: =N12-N12*O13/360*_xlfn.XLOOKUP('Tether Assets'!A13,'BBG Data'!A:A,'BBG Data'!V:V) -> 3.924626e+10 | O13: 45 | P13: =P12-P12*Q13/360*_xlfn.XLOOKUP(A13,'BBG Data'!A:A,'BBG Data'!V:V) -> 1.780947e+08 | Q13: 90 | R13: 6135946415 | S13: =S12-S12*T13/360*_xlfn.XLOOKUP('Tether Assets'!A13,'BBG Data'!A:A,'BBG Data'!AB:AB) -> 1.5603982e+08 | T13: 180 | U13: 1046907100 | V13: =U13+S13+R13+P13+N13+M13+K13+J13+I13+H13+E13+B13 -> 6.7616413e+10 | W13: =(I13+J13)/V13 -> 0.1301256 | X13: =N13/V13 -> 0.58042506 | Y13: =USDT_FinalReserves!G12/USDT_FinalReserves!$F12 -> 0.0027703435 | Z13: 6.8498065e+10 | AA13: 6.8308302e+10
A14: 44845 | B14: 49981855 | C14: 81315.278 | D14: =_xlfn.XLOOKUP(A14,'BBG Data'!A:A,'BBG Data'!B:B) -> 19019.1 | E14: =C14*D14 -> 1.5465434e+09 | F14: 1827431.7 | G14: =_xlfn.XLOOKUP(A14,'BBG Data'!A:A,'BBG Data'!C:C) -> 1666.34 | H14: =G14*F14 -> 3.0451226e+09 | I14: 6077722223 | J14: =J13-$J$1*J13*_xlfn.XLOOKUP(A14,'BBG Data'!A:A,'BBG Data'!F:F) -> 2.7209038e+09 | K14: =K13-K13*L14/360*_xlfn.XLOOKUP(A14,'BBG Data'!A:A,'BBG Data'!J:J) -> 2.882076e+08 | L14: 90 | M14: =M13-M13*$M$1*_xlfn.XLOOKUP(A14,'BBG Data'!A:A,'BBG Data'!F:F) -> 7.099174e+09 | N14: =N13-N13*O14/360*_xlfn.XLOOKUP('Tether Assets'!A14,'BBG Data'!A:A,'BBG Data'!V:V) -> 3.8834175e+10 | O14: 45 | P14: =P13-P13*Q14/360*_xlfn.XLOOKUP(A14,'BBG Data'!A:A,'BBG Data'!V:V) -> 1.7435471e+08 | Q14: 90 | R14: 6135946415 | S14: =S13-S13*T14/360*_xlfn.XLOOKUP('Tether Assets'!A14,'BBG Data'!A:A,'BBG Data'!AB:AB) -> 1.5231827e+08 | T14: 180 | U14: 1046907100 | V14: =U14+S14+R14+P14+N14+M14+K14+J14+I14+H14+E14+B14 -> 6.7171357e+10 | W14: =(I14+J14)/V14 -> 0.13098777 | X14: =N14/V14 -> 0.57813593 | Y14: =USDT_FinalReserves!G13/USDT_FinalReserves!$F13 -> -0.0028319906 | Z14: 6.8272184e+10 | AA14: 6.846553e+10
A15: 44846 | B15: 49981855 | C15: 81315.278 | D15: =_xlfn.XLOOKUP(A15,'BBG Data'!A:A,'BBG Data'!B:B) -> 19169.43 | E15: =C15*D15 -> 1.5587675e+09 | F15: 1827431.7 | G15: =_xlfn.XLOOKUP(A15,'BBG Data'!A:A,'BBG Data'!C:C) -> 1673.19 | H15: =G15*F15 -> 3.0576405e+09 | I15: 6077722223 | J15: =J14-$J$1*J14*_xlfn.XLOOKUP(A15,'BBG Data'!A:A,'BBG Data'!F:F) -> 2.7209794e+09 | K15: =K14-K14*L15/360*_xlfn.XLOOKUP(A15,'BBG Data'!A:A,'BBG Data'!J:J) -> 2.8511945e+08 | L15: 90 | M15: =M14-M14*$M$1*_xlfn.XLOOKUP(A15,'BBG Data'!A:A,'BBG Data'!F:F) -> 7.0995684e+09 | N15: =N14-N14*O15/360*_xlfn.XLOOKUP('Tether Assets'!A15,'BBG Data'!A:A,'BBG Data'!V:V) -> 3.7979823e+10 | O15: 45 | P15: =P14-P14*Q15/360*_xlfn.XLOOKUP(A15,'BBG Data'!A:A,'BBG Data'!V:V) -> 1.6668311e+08 | Q15: 90 | R15: 6135946415 | S15: =S14-S14*T15/360*_xlfn.XLOOKUP('Tether Assets'!A15,'BBG Data'!A:A,'BBG Data'!AB:AB) -> 1.5045237e+08 | T15: 180 | U15: 1046907100 | V15: =U15+S15+R15+P15+N15+M15+K15+J15+I15+H15+E15+B15 -> 6.6329591e+10 | W15: =(I15+J15)/V15 -> 0.13265123 | X15: =N15/V15 -> 0.57259245 | Y15: =USDT_FinalReserves!G14/USDT_FinalReserves!$F14 -> -0.0088740959 | Z15: 6.7826661e+10 | AA15: 6.8428562e+10
... A94: 44925 | B94: 49981855 | C94: 81315.278 | D94: =_xlfn.XLOOKUP(A94,'BBG Data'!A:A,'BBG Data'!B:B) -> 16579.06 | E94: =C94*D94 -> 1.3481309e+09 | F94: 1827431.7 | G94: =_xlfn.XLOOKUP(A94,'BBG Data'!A:A,'BBG Data'!C:C) -> 1824.02 | H94: =G94*F94 -> 3.333272e+09 | I94: 6077722223 | J94: =J93-$J$1*J93*_xlfn.XLOOKUP(A94,'BBG Data'!A:A,'BBG Data'!F:F) -> 2.7114639e+09 | K94: =K93-K93*L94/360*_xlfn.XLOOKUP(A94,'BBG Data'!A:A,'BBG Data'!J:J) -> 2.355567e+08 | L94: 90 | M94: =M93-M93*$M$1*_xlfn.XLOOKUP(A94,'BBG Data'!A:A,'BBG Data'!F:F) -> 7.0499539e+09 | N94: =N93-N93*O94/360*_xlfn.XLOOKUP('Tether Assets'!A94,'BBG Data'!A:A,'BBG Data'!V:V) -> 3.4517952e+10 | O94: 45 | P94: =P93-P93*Q94/360*_xlfn.XLOOKUP(A94,'BBG Data'!A:A,'BBG Data'!V:V) -> 1.3745099e+08 | Q94: 90 | R94: 6135946415 | S94: =S93-S93*T94/360*_xlfn.XLOOKUP('Tether Assets'!A94,'BBG Data'!A:A,'BBG Data'!AB:AB) -> 1.1765813e+08 | T94: 180 | U94: 1046907100 | V94: =U94+S94+R94+P94+N94+M94+K94+J94+I94+H94+E94+B94 -> 6.2761996e+10 | W94: =(I94+J94)/V94 -> 0.14003994 | X94: =N94/V94 -> 0.54998174 | Y94: =USDT_FinalReserves!G93/USDT_FinalReserves!$F93 -> 0.0050474825 | Z94: 6.6591937e+10 | AA94: 6.6255816e+10
A95: 44926 | B95: 0 | C95: 96930.631 | D95: =_xlfn.XLOOKUP(A95,'BBG Data'!A:A,'BBG Data'!B:B) -> 16539.5 | E95: =C95*D95 -> 1.6031842e+09 | F95: 1793781.2 | G95: =_xlfn.XLOOKUP(A95,'BBG Data'!A:A,'BBG Data'!C:C) -> 1824.02 | H95: =G95*F95 -> 3.2718927e+09 | I95: 5318311794 | J95: 2.7414846e+09 | K95: 3.046094e+08 | L95: 90 | M95: 7372926391 | N95: 39230259046 | O95: 60 | P95: 93849833 | Q95: 60 | R95: 5852823328 | S95: 1.7220488e+08 | T95: 180 | U95: 1074314492 | V95: =U95+S95+R95+P95+N95+M95+K95+J95+I95+H95+E95+B95 -> 6.7035861e+10 | W95: =(I95+J95)/V95 -> 0.12023112 | X95: =N95/V95 -> 0.58521303 | Y95: =USDT_FinalReserves!G94/USDT_FinalReserves!$F94 -> 0.014719972 | Z95: 6.7269245e+10 | AA95: 6.6279044e+10
A96: 44927 | B96: 0 | C96: 96930.631 | D96: =_xlfn.XLOOKUP(A96,'BBG Data'!A:A,'BBG Data'!B:B) -> 16602.63 | E96: =C96*D96 -> 1.6093034e+09 | F96: 1793781.2 | G96: =_xlfn.XLOOKUP(A96,'BBG Data'!A:A,'BBG Data'!C:C) -> 1824.02 | H96: =G96*F96 -> 3.2718927e+09 | I96: 5318311794 | J96: =J95-$J$1*J95*_xlfn.XLOOKUP(A96,'BBG Data'!A:A,'BBG Data'!F:F) -> 2.7414846e+09 | K96: =K95-K95*L96/360*_xlfn.XLOOKUP(A96,'BBG Data'!A:A,'BBG Data'!J:J) -> 3.046094e+08 | L96: 90 | M96: =M95-M95*$M$1*_xlfn.XLOOKUP(A96,'BBG Data'!A:A,'BBG Data'!F:F) -> 7372926391 | N96: =N95-N95*O96/360*_xlfn.XLOOKUP('Tether Assets'!A96,'BBG Data'!A:A,'BBG Data'!V:V) -> 39230259046 | O96: 60 | P96: =P95-P95*Q96/360*_xlfn.XLOOKUP(A96,'BBG Data'!A:A,'BBG Data'!V:V) -> 93849833 | Q96: 60 | R96: 5852823328 | S96: =S95-S95*T96/360*_xlfn.XLOOKUP('Tether Assets'!A96,'BBG Data'!A:A,'BBG Data'!AB:AB) -> 1.7220488e+08 | T96: 180 | U96: 1074314492 | V96: =U96+S96+R96+P96+N96+M96+K96+J96+I96+H96+E96+B96 -> 6.704198e+10 | W96: =(I96+J96)/V96 -> 0.12022014 | X96: =N96/V96 -> 0.58515961 | Y96: =USDT_FinalReserves!G95/USDT_FinalReserves!$F95 -> 0.014809903 | Z96: 6.7222003e+10 | AA96: 6.6226452e+10
A97: 44928 | B97: 0 | C97: 96930.631 | D97: =_xlfn.XLOOKUP(A97,'BBG Data'!A:A,'BBG Data'!B:B) -> 16750.94 | E97: =C97*D97 -> 1.6236792e+09 | F97: 1793781.2 | G97: =_xlfn.XLOOKUP(A97,'BBG Data'!A:A,'BBG Data'!C:C) -> 1824.02 | H97: =G97*F97 -> 3.2718927e+09 | I97: 5318311794 | J97: =J96-$J$1*J96*_xlfn.XLOOKUP(A97,'BBG Data'!A:A,'BBG Data'!F:F) -> 2.7414846e+09 | K97: =K96-K96*L97/360*_xlfn.XLOOKUP(A97,'BBG Data'!A:A,'BBG Data'!J:J) -> 3.046094e+08 | L97: 90 | M97: =M96-M96*$M$1*_xlfn.XLOOKUP(A97,'BBG Data'!A:A,'BBG Data'!F:F) -> 7372926391 | N97: =N96-N96*O97/360*_xlfn.XLOOKUP('Tether Assets'!A97,'BBG Data'!A:A,'BBG Data'!V:V) -> 39230259046 | O97: 60 | P97: =P96-P96*Q97/360*_xlfn.XLOOKUP(A97,'BBG Data'!A:A,'BBG Data'!V:V) -> 93849833 | Q97: 60 | R97: 5852823328 | S97: =S96-S96*T97/360*_xlfn.XLOOKUP('Tether Assets'!A97,'BBG Data'!A:A,'BBG Data'!AB:AB) -> 1.7220488e+08 | T97: 180 | U97: 1074314492 | V97: =U97+S97+R97+P97+N97+M97+K97+J97+I97+H97+E97+B97 -> 6.7056356e+10 | W97: =(I97+J97)/V97 -> 0.12019437 | X97: =N97/V97 -> 0.58503417 | Y97: =USDT_FinalReserves!G96/USDT_FinalReserves!$F96 -> 0.0149312 | Z97: 6.730683e+10 | AA97: 6.6301858e+10
A98: 44929 | B98: 0 | C98: 96930.631 | D98: =_xlfn.XLOOKUP(A98,'BBG Data'!A:A,'BBG Data'!B:B) -> 16661.86 | E98: =C98*D98 -> 1.6150446e+09 | F98: 1793781.2 | G98: =_xlfn.XLOOKUP(A98,'BBG Data'!A:A,'BBG Data'!C:C) -> 1839.48 | H98: =G98*F98 -> 3.2996246e+09 | I98: 5318311794 | J98: =J97-$J$1*J97*_xlfn.XLOOKUP(A98,'BBG Data'!A:A,'BBG Data'!F:F) -> 2.7414084e+09 | K98: =K97-K97*L98/360*_xlfn.XLOOKUP(A98,'BBG Data'!A:A,'BBG Data'!J:J) -> 3.0343741e+08 | L98: 90 | M98: =M97-M97*$M$1*_xlfn.XLOOKUP(A98,'BBG Data'!A:A,'BBG Data'!F:F) -> 7.3725168e+09 | N98: =N97-N97*O98/360*_xlfn.XLOOKUP('Tether Assets'!A98,'BBG Data'!A:A,'BBG Data'!V:V) -> 3.9269489e+10 | O98: 60 | P98: =P97-P97*Q98/360*_xlfn.XLOOKUP(A98,'BBG Data'!A:A,'BBG Data'!V:V) -> 93943683 | Q98: 60 | R98: 5852823328 | S98: =S97-S97*T98/360*_xlfn.XLOOKUP('Tether Assets'!A98,'BBG Data'!A:A,'BBG Data'!AB:AB) -> 1.7668221e+08 | T98: 180 | U98: 1074314492 | V98: =U98+S98+R98+P98+N98+M98+K98+J98+I98+H98+E98+B98 -> 6.7117597e+10 | W98: =(I98+J98)/V98 -> 0.12008356 | X98: =N98/V98 -> 0.58508486 | Y98: =USDT_FinalReserves!G97/USDT_FinalReserves!$F97 -> 0.015618984 | Z98: 6.7274003e+10 | AA98: 6.6223252e+10
A99: 44930 | B99: 0 | C99: 96930.631 | D99: =_xlfn.XLOOKUP(A99,'BBG Data'!A:A,'BBG Data'!B:B) -> 16821.82 | E99: =C99*D99 -> 1.6305496e+09 | F99: 1793781.2 | G99: =_xlfn.XLOOKUP(A99,'BBG Data'!A:A,'BBG Data'!C:C) -> 1854.56 | H99: =G99*F99 -> 3.3266748e+09 | I99: 5318311794 | J99: =J98-$J$1*J98*_xlfn.XLOOKUP(A99,'BBG Data'!A:A,'BBG Data'!F:F) -> 2.7414846e+09 | K99: =K98-K98*L99/360*_xlfn.XLOOKUP(A99,'BBG Data'!A:A,'BBG Data'!J:J) -> 3.03335e+08 | L99: 90 | M99: =M98-M98*$M$1*_xlfn.XLOOKUP(A99,'BBG Data'!A:A,'BBG Data'!F:F) -> 7.3729264e+09 | N99: =N98-N98*O99/360*_xlfn.XLOOKUP('Tether Assets'!A99,'BBG Data'!A:A,'BBG Data'!V:V) -> 3.8346656e+10 | O99: 60 | P99: =P98-P98*Q99/360*_xlfn.XLOOKUP(A99,'BBG Data'!A:A,'BBG Data'!V:V) -> 91736006 | Q99: 60 | R99: 5852823328 | S99: =S98-S98*T99/360*_xlfn.XLOOKUP('Tether Assets'!A99,'BBG Data'!A:A,'BBG Data'!AB:AB) -> 1.7647902e+08 | T99: 180 | U99: 1074314492 | V99: =U99+S99+R99+P99+N99+M99+K99+J99+I99+H99+E99+B99 -> 6.6235291e+10 | W99: =(I99+J99)/V99 -> 0.12168432 | X99: =N99/V99 -> 0.57894599 | Y99: =USDT_FinalReserves!G98/USDT_FinalReserves!$F98 -> 0.0015952806 | Z99: 6.6379954e+10 | AA99: 6.6274059e+10
A100: 44931 | B100: 0 | C100: 96930.631 | D100: =_xlfn.XLOOKUP(A100,'BBG Data'!A:A,'BBG Data'!B:B) -> 16844.62 | E100: =C100*D100 -> 1.6327596e+09 | F100: 1793781.2 | G100: =_xlfn.XLOOKUP(A100,'BBG Data'!A:A,'BBG Data'!C:C) -> 1832.89 | H100: =G100*F100 -> 3.2878036e+09 | I100: 5318311794 | J100: =J99-$J$1*J99*_xlfn.XLOOKUP(A100,'BBG Data'!A:A,'BBG Data'!F:F) -> 2.7414084e+09 | K100: =K99-K99*L100/360*_xlfn.XLOOKUP(A100,'BBG Data'!A:A,'BBG Data'!J:J) -> 3.0171974e+08 | L100: 90 | M100: =M99-M99*$M$1*_xlfn.XLOOKUP(A100,'BBG Data'!A:A,'BBG Data'!F:F) -> 7.3725168e+09 | N100: =N99-N99*O100/360*_xlfn.XLOOKUP('Tether Assets'!A100,'BBG Data'!A:A,'BBG Data'!V:V) -> 3.7694763e+10 | O100: 60 | P100: =P99-P99*Q100/360*_xlfn.XLOOKUP(A100,'BBG Data'!A:A,'BBG Data'!V:V) -> 90176494 | Q100: 60 | R100: 5852823328 | S100: =S99-S99*T100/360*_xlfn.XLOOKUP('Tether Assets'!A100,'BBG Data'!A:A,'BBG Data'!AB:AB) -> 1.7237589e+08 | T100: 180 | U100: 1074314492 | V100: =U100+S100+R100+P100+N100+M100+K100+J100+I100+H100+E100+B100 -> 6.5538973e+10 | W100: =(I100+J100)/V100 -> 0.12297599 | X100: =N100/V100 -> 0.57515035 | Y100: =USDT_FinalReserves!G99/USDT_FinalReserves!$F99 -> 0.0042518764 | Z100: 6.6528416e+10 | AA100: 6.6245546e+10
A101: 44932 | B101: 0 | C101: 96930.631 | D101: =_xlfn.XLOOKUP(A101,'BBG Data'!A:A,'BBG Data'!B:B) -> 16927.86 | E101: =C101*D101 -> 1.6408281e+09 | F101: 1793781.2 | G101: =_xlfn.XLOOKUP(A101,'BBG Data'!A:A,'BBG Data'!C:C) -> 1865.69 | H101: =G101*F101 -> 3.3466396e+09 | I101: 5318311794 | J101: =J100-$J$1*J100*_xlfn.XLOOKUP(A101,'BBG Data'!A:A,'BBG Data'!F:F) -> 2.7414084e+09 | K101: =K100-K100*L101/360*_xlfn.XLOOKUP(A101,'BBG Data'!A:A,'BBG Data'!J:J) -> 2.9945307e+08 | L101: 90 | M101: =M100-M100*$M$1*_xlfn.XLOOKUP(A101,'BBG Data'!A:A,'BBG Data'!F:F) -> 7.3725168e+09 | N101: =N100-N100*O101/360*_xlfn.XLOOKUP('Tether Assets'!A101,'BBG Data'!A:A,'BBG Data'!V:V) -> 3.7732458e+10 | O101: 60 | P101: =P100-P100*Q101/360*_xlfn.XLOOKUP(A101,'BBG Data'!A:A,'BBG Data'!V:V) -> 90266671 | Q101: 60 | R101: 5852823328 | S101: =S100-S100*T101/360*_xlfn.XLOOKUP('Tether Assets'!A101,'BBG Data'!A:A,'BBG Data'!AB:AB) -> 1.7900374e+08 | T101: 180 | U101: 1074314492 | V101: =U101+S101+R101+P101+N101+M101+K101+J101+I101+H101+E101+B101 -> 6.5648024e+10 | W101: =(I101+J101)/V101 -> 0.12277171 | X101: =N101/V101 -> 0.57476914 | Y101: =USDT_FinalReserves!G100/USDT_FinalReserves!$F100 -> 0.016356662 | Z101: 6.7380773e+10 | AA101: 6.6278649e+10
A102: 44933 | B102: 0 | C102: 96930.631 | D102: =_xlfn.XLOOKUP(A102,'BBG Data'!A:A,'BBG Data'!B:B) -> 16938.55 | E102: =C102*D102 -> 1.6418643e+09 | F102: 1793781.2 | G102: =_xlfn.XLOOKUP(A102,'BBG Data'!A:A,'BBG Data'!C:C) -> 1865.69 | H102: =G102*F102 -> 3.3466396e+09 | I102: 5318311794 | J102: =J101-$J$1*J101*_xlfn.XLOOKUP(A102,'BBG Data'!A:A,'BBG Data'!F:F) -> 2.7414084e+09 | K102: =K101-K101*L102/360*_xlfn.XLOOKUP(A102,'BBG Data'!A:A,'BBG Data'!J:J) -> 2.9945307e+08 | L102: 90 | M102: =M101-M101*$M$1*_xlfn.XLOOKUP(A102,'BBG Data'!A:A,'BBG Data'!F:F) -> 7.3725168e+09 | N102: =N101-N101*O102/360*_xlfn.XLOOKUP('Tether Assets'!A102,'BBG Data'!A:A,'BBG Data'!V:V) -> 3.7732458e+10 | O102: 60 | P102: =P101-P101*Q102/360*_xlfn.XLOOKUP(A102,'BBG Data'!A:A,'BBG Data'!V:V) -> 90266671 | Q102: 60 | R102: 5852823328 | S102: =S101-S101*T102/360*_xlfn.XLOOKUP('Tether Assets'!A102,'BBG Data'!A:A,'BBG Data'!AB:AB) -> 1.7900374e+08 | T102: 180 | U102: 1074314492 | V102: =U102+S102+R102+P102+N102+M102+K102+J102+I102+H102+E102+B102 -> 6.564906e+10 | W102: =(I102+J102)/V102 -> 0.12276977 | X102: =N102/V102 -> 0.57476006 | Y102: =USDT_FinalReserves!G101/USDT_FinalReserves!$F101 -> 0.014735524 | Z102: 6.7254363e+10 | AA102: 6.6263334e+10
A103: 44934 | B103: 0 | C103: 96930.631 | D103: =_xlfn.XLOOKUP(A103,'BBG Data'!A:A,'BBG Data'!B:B) -> 16956.66 | E103: =C103*D103 -> 1.6436198e+09 | F103: 1793781.2 | G103: =_xlfn.XLOOKUP(A103,'BBG Data'!A:A,'BBG Data'!C:C) -> 1865.69 | H103: =G103*F103 -> 3.3466396e+09 | I103: 5318311794 | J103: =J102-$J$1*J102*_xlfn.XLOOKUP(A103,'BBG Data'!A:A,'BBG Data'!F:F) -> 2.7414084e+09 | K103: =K102-K102*L103/360*_xlfn.XLOOKUP(A103,'BBG Data'!A:A,'BBG Data'!J:J) -> 2.9945307e+08 | L103: 90 | M103: =M102-M102*$M$1*_xlfn.XLOOKUP(A103,'BBG Data'!A:A,'BBG Data'!F:F) -> 7.3725168e+09 | N103: =N102-N102*O103/360*_xlfn.XLOOKUP('Tether Assets'!A103,'BBG Data'!A:A,'BBG Data'!V:V) -> 3.7732458e+10 | O103: 60 | P103: =P102-P102*Q103/360*_xlfn.XLOOKUP(A103,'BBG Data'!A:A,'BBG Data'!V:V) -> 90266671 | Q103: 60 | R103: 5852823328 | S103: =S102-S102*T103/360*_xlfn.XLOOKUP('Tether Assets'!A103,'BBG Data'!A:A,'BBG Data'!AB:AB) -> 1.7900374e+08 | T103: 180 | U103: 1074314492 | V103: =U103+S103+R103+P103+N103+M103+K103+J103+I103+H103+E103+B103 -> 6.5650816e+10 | W103: =(I103+J103)/V103 -> 0.12276649 | X103: =N103/V103 -> 0.57474469 | Y103: =USDT_FinalReserves!G102/USDT_FinalReserves!$F102 -> 0.014746317 | Z103: 6.7264353e+10 | AA103: 6.6272452e+10
A104: 44935 | B104: 0 | C104: 96930.631 | D104: =_xlfn.XLOOKUP(A104,'BBG Data'!A:A,'BBG Data'!B:B) -> 17181.34 | E104: =C104*D104 -> 1.6653981e+09 | F104: 1793781.2 | G104: =_xlfn.XLOOKUP(A104,'BBG Data'!A:A,'BBG Data'!C:C) -> 1871.81 | H104: =G104*F104 -> 3.3576175e+09 | I104: 5318311794 | J104: =J103-$J$1*J103*_xlfn.XLOOKUP(A104,'BBG Data'!A:A,'BBG Data'!F:F) -> 2.7414084e+09 | K104: =K103-K103*L104/360*_xlfn.XLOOKUP(A104,'BBG Data'!A:A,'BBG Data'!J:J) -> 3.0098852e+08 | L104: 90 | M104: =M103-M103*$M$1*_xlfn.XLOOKUP(A104,'BBG Data'!A:A,'BBG Data'!F:F) -> 7.3725168e+09 | N104: =N103-N103*O104/360*_xlfn.XLOOKUP('Tether Assets'!A104,'BBG Data'!A:A,'BBG Data'!V:V) -> 3.7707303e+10 | O104: 60 | P104: =P103-P103*Q104/360*_xlfn.XLOOKUP(A104,'BBG Data'!A:A,'BBG Data'!V:V) -> 90206493 | Q104: 60 | R104: 5852823328 | S104: =S103-S103*T104/360*_xlfn.XLOOKUP('Tether Assets'!A104,'BBG Data'!A:A,'BBG Data'!AB:AB) -> 1.8468711e+08 | T104: 180 | U104: 1074314492 | V104: =U104+S104+R104+P104+N104+M104+K104+J104+I104+H104+E104+B104 -> 6.5665575e+10 | W104: =(I104+J104)/V104 -> 0.1227389 | X104: =N104/V104 -> 0.57423243 | Y104: =USDT_FinalReserves!G103/USDT_FinalReserves!$F103 -> 0.014941439 | Z104: 6.7300933e+10 | AA104: 6.629536e+10
A105: 44936 | B105: 0 | C105: 96930.631 | D105: =_xlfn.XLOOKUP(A105,'BBG Data'!A:A,'BBG Data'!B:B) -> 17466.71 | E105: =C105*D105 -> 1.6930592e+09 | F105: 1793781.2 | G105: =_xlfn.XLOOKUP(A105,'BBG Data'!A:A,'BBG Data'!C:C) -> 1877.03 | H105: =G105*F105 -> 3.3669811e+09 | I105: 5318311794 | J105: =J104-$J$1*J104*_xlfn.XLOOKUP(A105,'BBG Data'!A:A,'BBG Data'!F:F) -> 2.7414084e+09 | K105: =K104-K104*L105/360*_xlfn.XLOOKUP(A105,'BBG Data'!A:A,'BBG Data'!J:J) -> 3.017139e+08 | L105: 90 | M105: =M104-M104*$M$1*_xlfn.XLOOKUP(A105,'BBG Data'!A:A,'BBG Data'!F:F) -> 7.3725168e+09 | N105: =N104-N104*O105/360*_xlfn.XLOOKUP('Tether Assets'!A105,'BBG Data'!A:A,'BBG Data'!V:V) -> 3.7688449e+10 | O105: 60 | P105: =P104-P104*Q105/360*_xlfn.XLOOKUP(A105,'BBG Data'!A:A,'BBG Data'!V:V) -> 90161390 | Q105: 60 | R105: 5852823328 | S105: =S104-S104*T105/360*_xlfn.XLOOKUP('Tether Assets'!A105,'BBG Data'!A:A,'BBG Data'!AB:AB) -> 1.8176905e+08 | T105: 180 | U105: 1074314492 | V105: =U105+S105+R105+P105+N105+M105+K105+J105+I105+H105+E105+B105 -> 6.5681509e+10 | W105: =(I105+J105)/V105 -> 0.12270912 | X105: =N105/V105 -> 0.57380608 | Y105: =USDT_FinalReserves!G104/USDT_FinalReserves!$F104 -> 0.014958984 | Z105: 6.7322118e+10 | AA105: 6.6315047e+10
A106: 44937 | B106: 0 | C106: 96930.631 | D106: =_xlfn.XLOOKUP(A106,'BBG Data'!A:A,'BBG Data'!B:B) -> 17560.6 | E106: =C106*D106 -> 1.70216e+09 | F106: 1793781.2 | G106: =_xlfn.XLOOKUP(A106,'BBG Data'!A:A,'BBG Data'!C:C) -> 1875.69 | H106: =G106*F106 -> 3.3645774e+09 | I106: 5318311794 | J106: =J105-$J$1*J105*_xlfn.XLOOKUP(A106,'BBG Data'!A:A,'BBG Data'!F:F) -> 2.7414846e+09 | K106: =K105-K105*L106/360*_xlfn.XLOOKUP(A106,'BBG Data'!A:A,'BBG Data'!J:J) -> 3.0106295e+08 | L106: 90 | M106: =M105-M105*$M$1*_xlfn.XLOOKUP(A106,'BBG Data'!A:A,'BBG Data'!F:F) -> 7.3729263e+09 | N106: =N105-N105*O106/360*_xlfn.XLOOKUP('Tether Assets'!A106,'BBG Data'!A:A,'BBG Data'!V:V) -> 3.7330409e+10 | O106: 60 | P106: =P105-P105*Q106/360*_xlfn.XLOOKUP(A106,'BBG Data'!A:A,'BBG Data'!V:V) -> 89304856 | Q106: 60 | R106: 5852823328 | S106: =S105-S105*T106/360*_xlfn.XLOOKUP('Tether Assets'!A106,'BBG Data'!A:A,'BBG Data'!AB:AB) -> 1.8435017e+08 | T106: 180 | U106: 1074314492 | V106: =U106+S106+R106+P106+N106+M106+K106+J106+I106+H106+E106+B106 -> 6.5331725e+10 | W106: =(I106+J106)/V106 -> 0.12336727 | X106: =N106/V106 -> 0.57139788 | Y106: =USDT_FinalReserves!G105/USDT_FinalReserves!$F105 -> 0.0094448179 | Z106: 6.6940066e+10 | AA106: 6.6307829e+10
A107: 44938 | B107: 0 | C107: 96930.631 | D107: =_xlfn.XLOOKUP(A107,'BBG Data'!A:A,'BBG Data'!B:B) -> 18830.98 | E107: =C107*D107 -> 1.8252988e+09 | F107: 1793781.2 | G107: =_xlfn.XLOOKUP(A107,'BBG Data'!A:A,'BBG Data'!C:C) -> 1897.09 | H107: =G107*F107 -> 3.4029643e+09 | I107: 5318311794 | J107: =J106-$J$1*J106*_xlfn.XLOOKUP(A107,'BBG Data'!A:A,'BBG Data'!F:F) -> 2.7414846e+09 | K107: =K106-K106*L107/360*_xlfn.XLOOKUP(A107,'BBG Data'!A:A,'BBG Data'!J:J) -> 2.9929195e+08 | L107: 90 | M107: =M106-M106*$M$1*_xlfn.XLOOKUP(A107,'BBG Data'!A:A,'BBG Data'!F:F) -> 7.3729263e+09 | N107: =N106-N106*O107/360*_xlfn.XLOOKUP('Tether Assets'!A107,'BBG Data'!A:A,'BBG Data'!V:V) -> 3.7821926e+10 | O107: 60 | P107: =P106-P106*Q107/360*_xlfn.XLOOKUP(A107,'BBG Data'!A:A,'BBG Data'!V:V) -> 90480704 | Q107: 60 | R107: 5852823328 | S107: =S106-S106*T107/360*_xlfn.XLOOKUP('Tether Assets'!A107,'BBG Data'!A:A,'BBG Data'!AB:AB) -> 1.8324407e+08 | T107: 180 | U107: 1074314492 | V107: =U107+S107+R107+P107+N107+M107+K107+J107+I107+H107+E107+B107 -> 6.5983066e+10 | W107: =(I107+J107)/V107 -> 0.12214947 | X107: =N107/V107 -> 0.57320655 | Y107: =USDT_FinalReserves!G106/USDT_FinalReserves!$F106 -> 0.024446009 | Z107: 6.7111021e+10 | AA107: 6.5470424e+10
... A184: 45015 | B184: 0 | C184: 96930.631 | D184: =_xlfn.XLOOKUP(A184,'BBG Data'!A:A,'BBG Data'!B:B) -> 28152.28 | E184: =C184*D184 -> 2.7288183e+09 | F184: 1793781.2 | G184: =_xlfn.XLOOKUP(A184,'BBG Data'!A:A,'BBG Data'!C:C) -> 1980.37 | H184: =G184*F184 -> 3.5523504e+09 | I184: 5318311794 | J184: =J183-$J$1*J183*_xlfn.XLOOKUP(A184,'BBG Data'!A:A,'BBG Data'!F:F) -> 2.7375261e+09 | K184: =K183-K183*L184/360*_xlfn.XLOOKUP(A184,'BBG Data'!A:A,'BBG Data'!J:J) -> 2.8081419e+08 | L184: 90 | M184: =M183-M183*$M$1*_xlfn.XLOOKUP(A184,'BBG Data'!A:A,'BBG Data'!F:F) -> 7.3516429e+09 | N184: =N183-N183*O184/360*_xlfn.XLOOKUP('Tether Assets'!A184,'BBG Data'!A:A,'BBG Data'!V:V) -> 3.6258085e+10 | O184: 60 | P184: =P183-P183*Q184/360*_xlfn.XLOOKUP(A184,'BBG Data'!A:A,'BBG Data'!V:V) -> 86739555 | Q184: 60 | R184: 5852823328 | S184: =S183-S183*T184/360*_xlfn.XLOOKUP('Tether Assets'!A184,'BBG Data'!A:A,'BBG Data'!AB:AB) -> 1.5995495e+08 | T184: 180 | U184: 1074314492 | V184: =U184+S184+R184+P184+N184+M184+K184+J184+I184+H184+E184+B184 -> 6.5401381e+10 | W184: =(I184+J184)/V184 -> 0.12317535 | X184: =N184/V184 -> 0.55439326 | Y184: =USDT_FinalReserves!G183/USDT_FinalReserves!$F183 -> 0.0078048971 | Z184: 8.0262813e+10 | AA184: 7.963637e+10
A185: 45016 | B185: 0 | C185: 52798.71 | D185: =_xlfn.XLOOKUP(A185,'BBG Data'!A:A,'BBG Data'!B:B) -> 28395.3 | E185: =C185*D185 -> 1.4992352e+09 | F185: 1721995.7 | G185: =_xlfn.XLOOKUP(A185,'BBG Data'!A:A,'BBG Data'!C:C) -> 1969.28 | H185: =G185*F185 -> 3391091658 | I185: 481350555 | J185: 7500000000 | K185: 786850807 | L185: 90 | M185: 7453204896 | N185: 53044762609 | O185: 90 | P185: 47680940 | Q185: 180 | R185: 5349078821 | S185: 140669244 | T185: 210 | U185: =2138395675 -> 2138395675 | V185: =U185+S185+R185+P185+N185+M185+K185+J185+I185+H185+E185+B185 -> 8.183232e+10 | W185: =(I185+J185)/V185 -> 0.097532986 | X185: =N185/V185 -> 0.64821286 | Y185: =USDT_FinalReserves!G184/USDT_FinalReserves!$F184 -> 0.030070305 | Z185: 8.2179353e+10 | AA185: 7.9708195e+10
A186: 45017 | B186: 0 | C186: 52798.71 | D186: =_xlfn.XLOOKUP(A186,'BBG Data'!A:A,'BBG Data'!B:B) -> 28463.77 | E186: =C186*D186 -> 1.5028503e+09 | F186: 1721995.7 | G186: =_xlfn.XLOOKUP(A186,'BBG Data'!A:A,'BBG Data'!C:C) -> 1969.28 | H186: =G186*F186 -> 3391091658 | I186: 481350555 | J186: =J185-$J$1*J185*_xlfn.XLOOKUP(A186,'BBG Data'!A:A,'BBG Data'!F:F) -> 7500000000 | K186: =K185-K185*L186/360*_xlfn.XLOOKUP(A186,'BBG Data'!A:A,'BBG Data'!J:J) -> 786850807 | L186: 90 | M186: =M185-M185*$M$1*_xlfn.XLOOKUP(A186,'BBG Data'!A:A,'BBG Data'!F:F) -> 7453204896 | N186: =N185-N185*O186/360*_xlfn.XLOOKUP('Tether Assets'!A186,'BBG Data'!A:A,'BBG Data'!V:V) -> 53044762609 | O186: 90 | P186: =P185-P185*Q186/360*_xlfn.XLOOKUP(A186,'BBG Data'!A:A,'BBG Data'!AC:AC) -> 47680940 | Q186: 180 | R186: 5349078821 | S186: =S185-S185*T186/360*_xlfn.XLOOKUP('Tether Assets'!A186,'BBG Data'!A:A,'BBG Data'!AB:AB) -> 140669244 | T186: 210 | U186: =2138395675 -> 2138395675 | V186: =U186+S186+R186+P186+N186+M186+K186+J186+I186+H186+E186+B186 -> 8.1835936e+10 | W186: =(I186+J186)/V186 -> 0.097528677 | X186: =N186/V186 -> 0.64818423 | Y186: =USDT_FinalReserves!G185/USDT_FinalReserves!$F185 -> 0.030113151 | Z186: 8.2286494e+10 | AA186: 7.9808588e+10
A187: 45018 | B187: 0 | C187: 52798.71 | D187: =_xlfn.XLOOKUP(A187,'BBG Data'!A:A,'BBG Data'!B:B) -> 28076.92 | E187: =C187*D187 -> 1.4824251e+09 | F187: 1721995.7 | G187: =_xlfn.XLOOKUP(A187,'BBG Data'!A:A,'BBG Data'!C:C) -> 1969.28 | H187: =G187*F187 -> 3391091658 | I187: 481350555 | J187: =J186-$J$1*J186*_xlfn.XLOOKUP(A187,'BBG Data'!A:A,'BBG Data'!F:F) -> 7500000000 | K187: =K186-K186*L187/360*_xlfn.XLOOKUP(A187,'BBG Data'!A:A,'BBG Data'!J:J) -> 786850807 | L187: 90 | M187: =M186-M186*$M$1*_xlfn.XLOOKUP(A187,'BBG Data'!A:A,'BBG Data'!F:F) -> 7453204896 | N187: =N186-N186*O187/360*_xlfn.XLOOKUP('Tether Assets'!A187,'BBG Data'!A:A,'BBG Data'!V:V) -> 53044762609 | O187: 90 | P187: =P186-P186*Q187/360*_xlfn.XLOOKUP(A187,'BBG Data'!A:A,'BBG Data'!AC:AC) -> 47680940 | Q187: 180 | R187: 5349078821 | S187: =S186-S186*T187/360*_xlfn.XLOOKUP('Tether Assets'!A187,'BBG Data'!A:A,'BBG Data'!AB:AB) -> 140669244 | T187: 210 | U187: =2138395675 -> 2138395675 | V187: =U187+S187+R187+P187+N187+M187+K187+J187+I187+H187+E187+B187 -> 8.181551e+10 | W187: =(I187+J187)/V187 -> 0.097553025 | X187: =N187/V187 -> 0.64834605 | Y187: =USDT_FinalReserves!G186/USDT_FinalReserves!$F186 -> 0.029828162 | Z187: 8.2224667e+10 | AA187: 7.9772057e+10
A188: 45019 | B188: 0 | C188: 52798.71 | D188: =_xlfn.XLOOKUP(A188,'BBG Data'!A:A,'BBG Data'!B:B) -> 27588.08 | E188: =C188*D188 -> 1.456615e+09 | F188: 1721995.7 | G188: =_xlfn.XLOOKUP(A188,'BBG Data'!A:A,'BBG Data'!C:C) -> 1984.65 | H188: =G188*F188 -> 3.4175587e+09 | I188: 481350555 | J188: =J187-$J$1*J187*_xlfn.XLOOKUP(A188,'BBG Data'!A:A,'BBG Data'!F:F) -> 7500625000 | K188: =K187-K187*L188/360*_xlfn.XLOOKUP(A188,'BBG Data'!A:A,'BBG Data'!J:J) -> 7.8447452e+08 | L188: 90 | M188: =M187-M187*$M$1*_xlfn.XLOOKUP(A188,'BBG Data'!A:A,'BBG Data'!F:F) -> 7.4544471e+09 | N188: =N187-N187*O188/360*_xlfn.XLOOKUP('Tether Assets'!A188,'BBG Data'!A:A,'BBG Data'!V:V) -> 5.2951934e+10 | O188: 90 | P188: =P187-P187*Q188/360*_xlfn.XLOOKUP(A188,'BBG Data'!A:A,'BBG Data'!AC:AC) -> 48086228 | Q188: 180 | R188: 5349078821 | S188: =S187-S187*T188/360*_xlfn.XLOOKUP('Tether Assets'!A188,'BBG Data'!A:A,'BBG Data'!AB:AB) -> 1.4356586e+08 | T188: 210 | U188: =2138395675 -> 2138395675 | V188: =U188+S188+R188+P188+N188+M188+K188+J188+I188+H188+E188+B188 -> 8.1726132e+10 | W188: =(I188+J188)/V188 -> 0.09766736 | X188: =N188/V188 -> 0.64791925 | Y188: =USDT_FinalReserves!G187/USDT_FinalReserves!$F187 -> 0.029009555 | Z188: 8.2176566e+10 | AA188: 7.9792661e+10
A189: 45020 | B189: 0 | C189: 52798.71 | D189: =_xlfn.XLOOKUP(A189,'BBG Data'!A:A,'BBG Data'!B:B) -> 28257.1 | E189: =C189*D189 -> 1.4919384e+09 | F189: 1721995.7 | G189: =_xlfn.XLOOKUP(A189,'BBG Data'!A:A,'BBG Data'!C:C) -> 2020.42 | H189: =G189*F189 -> 3.4791545e+09 | I189: 481350555 | J189: =J188-$J$1*J188*_xlfn.XLOOKUP(A189,'BBG Data'!A:A,'BBG Data'!F:F) -> 7.5008334e+09 | K189: =K188-K188*L189/360*_xlfn.XLOOKUP(A189,'BBG Data'!A:A,'BBG Data'!J:J) -> 7.8119345e+08 | L189: 90 | M189: =M188-M188*$M$1*_xlfn.XLOOKUP(A189,'BBG Data'!A:A,'BBG Data'!F:F) -> 7.4548612e+09 | N189: =N188-N188*O189/360*_xlfn.XLOOKUP('Tether Assets'!A189,'BBG Data'!A:A,'BBG Data'!V:V) -> 5.2369463e+10 | O189: 90 | P189: =P188-P188*Q189/360*_xlfn.XLOOKUP(A189,'BBG Data'!A:A,'BBG Data'!AC:AC) -> 51259919 | Q189: 180 | R189: 5349078821 | S189: =S188-S188*T189/360*_xlfn.XLOOKUP('Tether Assets'!A189,'BBG Data'!A:A,'BBG Data'!AB:AB) -> 1.4666449e+08 | T189: 210 | U189: =2138395675 -> 2138395675 | V189: =U189+S189+R189+P189+N189+M189+K189+J189+I189+H189+E189+B189 -> 8.1244193e+10 | W189: =(I189+J189)/V189 -> 0.098249285 | X189: =N189/V189 -> 0.6445933 | Y189: =USDT_FinalReserves!G188/USDT_FinalReserves!$F188 -> 0.024316708 | Z189: 8.1865499e+10 | AA189: 7.9874799e+10
A190: 45021 | B190: 0 | C190: 52798.71 | D190: =_xlfn.XLOOKUP(A190,'BBG Data'!A:A,'BBG Data'!B:B) -> 28157.09 | E190: =C190*D190 -> 1.486658e+09 | F190: 1721995.7 | G190: =_xlfn.XLOOKUP(A190,'BBG Data'!A:A,'BBG Data'!C:C) -> 2020.73 | H190: =G190*F190 -> 3.4796883e+09 | I190: 481350555 | J190: =J189-$J$1*J189*_xlfn.XLOOKUP(A190,'BBG Data'!A:A,'BBG Data'!F:F) -> 7.5012501e+09 | K190: =K189-K189*L190/360*_xlfn.XLOOKUP(A190,'BBG Data'!A:A,'BBG Data'!J:J) -> 7.8522832e+08 | L190: 90 | M190: =M189-M189*$M$1*_xlfn.XLOOKUP(A190,'BBG Data'!A:A,'BBG Data'!F:F) -> 7.4556896e+09 | N190: =N189-N189*O190/360*_xlfn.XLOOKUP('Tether Assets'!A190,'BBG Data'!A:A,'BBG Data'!V:V) -> 5.2042154e+10 | O190: 90 | P190: =P189-P189*Q190/360*_xlfn.XLOOKUP(A190,'BBG Data'!A:A,'BBG Data'!AC:AC) -> 49978421 | Q190: 180 | R190: 5349078821 | S190: =S189-S189*T190/360*_xlfn.XLOOKUP('Tether Assets'!A190,'BBG Data'!A:A,'BBG Data'!AB:AB) -> 1.4792214e+08 | T190: 210 | U190: =2138395675 -> 2138395675 | V190: =U190+S190+R190+P190+N190+M190+K190+J190+I190+H190+E190+B190 -> 8.0917394e+10 | W190: =(I190+J190)/V190 -> 0.098651232 | X190: =N190/V190 -> 0.64315163 | Y190: =USDT_FinalReserves!G189/USDT_FinalReserves!$F189 -> 0.026153066 | Z190: 8.2231678e+10 | AA190: 8.0081067e+10
A191: 45022 | B191: 0 | C191: 52798.71 | D191: =_xlfn.XLOOKUP(A191,'BBG Data'!A:A,'BBG Data'!B:B) -> 27992.29 | E191: =C191*D191 -> 1.4779568e+09 | F191: 1721995.7 | G191: =_xlfn.XLOOKUP(A191,'BBG Data'!A:A,'BBG Data'!C:C) -> 2007.91 | H191: =G191*F191 -> 3.4576124e+09 | I191: 481350555 | J191: =J190-$J$1*J190*_xlfn.XLOOKUP(A191,'BBG Data'!A:A,'BBG Data'!F:F) -> 7.5012501e+09 | K191: =K190-K190*L191/360*_xlfn.XLOOKUP(A191,'BBG Data'!A:A,'BBG Data'!J:J) -> 7.8951566e+08 | L191: 90 | M191: =M190-M190*$M$1*_xlfn.XLOOKUP(A191,'BBG Data'!A:A,'BBG Data'!F:F) -> 7.4556896e+09 | N191: =N190-N190*O191/360*_xlfn.XLOOKUP('Tether Assets'!A191,'BBG Data'!A:A,'BBG Data'!V:V) -> 5.1873017e+10 | O191: 90 | P191: =P190-P190*Q191/360*_xlfn.XLOOKUP(A191,'BBG Data'!A:A,'BBG Data'!AC:AC) -> 49003842 | Q191: 180 | R191: 5349078821 | S191: =S190-S190*T191/360*_xlfn.XLOOKUP('Tether Assets'!A191,'BBG Data'!A:A,'BBG Data'!AB:AB) -> 1.4851752e+08 | T191: 210 | U191: =2138395675 -> 2138395675 | V191: =U191+S191+R191+P191+N191+M191+K191+J191+I191+H191+E191+B191 -> 8.0721388e+10 | W191: =(I191+J191)/V191 -> 0.098890775 | X191: =N191/V191 -> 0.642618 | Y191: =USDT_FinalReserves!G190/USDT_FinalReserves!$F190 -> 0.027715141 | Z191: 8.2424678e+10 | AA191: 8.0140267e+10
A192: 45023 | B192: 0 | C192: 52798.71 | D192: =_xlfn.XLOOKUP(A192,'BBG Data'!A:A,'BBG Data'!B:B) -> 27890.37 | E192: =C192*D192 -> 1.4725755e+09 | F192: 1721995.7 | G192: =_xlfn.XLOOKUP(A192,'BBG Data'!A:A,'BBG Data'!C:C) -> 2007.91 | H192: =G192*F192 -> 3.4576124e+09 | I192: 481350555 | J192: =J191-$J$1*J191*_xlfn.XLOOKUP(A192,'BBG Data'!A:A,'BBG Data'!F:F) -> 7.5012501e+09 | K192: =K191-K191*L192/360*_xlfn.XLOOKUP(A192,'BBG Data'!A:A,'BBG Data'!J:J) -> 7.8763464e+08 | L192: 90 | M192: =M191-M191*$M$1*_xlfn.XLOOKUP(A192,'BBG Data'!A:A,'BBG Data'!F:F) -> 7.4556896e+09 | N192: =N191-N191*O192/360*_xlfn.XLOOKUP('Tether Assets'!A192,'BBG Data'!A:A,'BBG Data'!V:V) -> 5.162662e+10 | O192: 90 | P192: =P191-P191*Q192/360*_xlfn.XLOOKUP(A192,'BBG Data'!A:A,'BBG Data'!AC:AC) -> 46651657 | Q192: 180 | R192: 5349078821 | S192: =S191-S191*T192/360*_xlfn.XLOOKUP('Tether Assets'!A192,'BBG Data'!A:A,'BBG Data'!AB:AB) -> 1.3927354e+08 | T192: 210 | U192: =2138395675 -> 2138395675 | V192: =U192+S192+R192+P192+N192+M192+K192+J192+I192+H192+E192+B192 -> 8.0456132e+10 | W192: =(I192+J192)/V192 -> 0.099216808 | X192: =N192/V192 -> 0.64167415 | Y192: =USDT_FinalReserves!G191/USDT_FinalReserves!$F191 -> 0.02687255 | Z192: 8.2403056e+10 | AA192: 8.0188675e+10
A193: 45024 | B193: 0 | C193: 52798.71 | D193: =_xlfn.XLOOKUP(A193,'BBG Data'!A:A,'BBG Data'!B:B) -> 27932.43 | E193: =C193*D193 -> 1.4747963e+09 | F193: 1721995.7 | G193: =_xlfn.XLOOKUP(A193,'BBG Data'!A:A,'BBG Data'!C:C) -> 2007.91 | H193: =G193*F193 -> 3.4576124e+09 | I193: 481350555 | J193: =J192-$J$1*J192*_xlfn.XLOOKUP(A193,'BBG Data'!A:A,'BBG Data'!F:F) -> 7.5012501e+09 | K193: =K192-K192*L193/360*_xlfn.XLOOKUP(A193,'BBG Data'!A:A,'BBG Data'!J:J) -> 7.8763464e+08 | L193: 90 | M193: =M192-M192*$M$1*_xlfn.XLOOKUP(A193,'BBG Data'!A:A,'BBG Data'!F:F) -> 7.4556896e+09 | N193: =N192-N192*O193/360*_xlfn.XLOOKUP('Tether Assets'!A193,'BBG Data'!A:A,'BBG Data'!V:V) -> 5.162662e+10 | O193: 90 | P193: =P192-P192*Q193/360*_xlfn.XLOOKUP(A193,'BBG Data'!A:A,'BBG Data'!AC:AC) -> 46651657 | Q193: 180 | R193: 5349078821 | S193: =S192-S192*T193/360*_xlfn.XLOOKUP('Tether Assets'!A193,'BBG Data'!A:A,'BBG Data'!AB:AB) -> 1.3927354e+08 | T193: 210 | U193: =2138395675 -> 2138395675 | V193: =U193+S193+R193+P193+N193+M193+K193+J193+I193+H193+E193+B193 -> 8.0458353e+10 | W193: =(I193+J193)/V193 -> 0.099214069 | X193: =N193/V193 -> 0.64165643 | Y193: =USDT_FinalReserves!G192/USDT_FinalReserves!$F192 -> 0.030097075 | Z193: 8.2759105e+10 | AA193: 8.0268298e+10
A194: 45025 | B194: 0 | C194: 52798.71 | D194: =_xlfn.XLOOKUP(A194,'BBG Data'!A:A,'BBG Data'!B:B) -> 28136.46 | E194: =C194*D194 -> 1.4855688e+09 | F194: 1721995.7 | G194: =_xlfn.XLOOKUP(A194,'BBG Data'!A:A,'BBG Data'!C:C) -> 2007.91 | H194: =G194*F194 -> 3.4576124e+09 | I194: 481350555 | J194: =J193-$J$1*J193*_xlfn.XLOOKUP(A194,'BBG Data'!A:A,'BBG Data'!F:F) -> 7.5012501e+09 | K194: =K193-K193*L194/360*_xlfn.XLOOKUP(A194,'BBG Data'!A:A,'BBG Data'!J:J) -> 7.8763464e+08 | L194: 90 | M194: =M193-M193*$M$1*_xlfn.XLOOKUP(A194,'BBG Data'!A:A,'BBG Data'!F:F) -> 7.4556896e+09 | N194: =N193-N193*O194/360*_xlfn.XLOOKUP('Tether Assets'!A194,'BBG Data'!A:A,'BBG Data'!V:V) -> 5.162662e+10 | O194: 90 | P194: =P193-P193*Q194/360*_xlfn.XLOOKUP(A194,'BBG Data'!A:A,'BBG Data'!AC:AC) -> 46651657 | Q194: 180 | R194: 5349078821 | S194: =S193-S193*T194/360*_xlfn.XLOOKUP('Tether Assets'!A194,'BBG Data'!A:A,'BBG Data'!AB:AB) -> 1.3927354e+08 | T194: 210 | U194: =2138395675 -> 2138395675 | V194: =U194+S194+R194+P194+N194+M194+K194+J194+I194+H194+E194+B194 -> 8.0469126e+10 | W194: =(I194+J194)/V194 -> 0.099200787 | X194: =N194/V194 -> 0.64157054 | Y194: =USDT_FinalReserves!G193/USDT_FinalReserves!$F193 -> 0.03020015 | Z194: 8.2807662e+10 | AA194: 8.0306858e+10
A195: 45026 | B195: 0 | C195: 52798.71 | D195: =_xlfn.XLOOKUP(A195,'BBG Data'!A:A,'BBG Data'!B:B) -> 29142.36 | E195: =C195*D195 -> 1.538679e+09 | F195: 1721995.7 | G195: =_xlfn.XLOOKUP(A195,'BBG Data'!A:A,'BBG Data'!C:C) -> 1991.48 | H195: =G195*F195 -> 3.42932e+09 | I195: 481350555 | J195: =J194-$J$1*J194*_xlfn.XLOOKUP(A195,'BBG Data'!A:A,'BBG Data'!F:F) -> 7.5012501e+09 | K195: =K194-K194*L195/360*_xlfn.XLOOKUP(A195,'BBG Data'!A:A,'BBG Data'!J:J) -> 7.7694841e+08 | L195: 90 | M195: =M194-M194*$M$1*_xlfn.XLOOKUP(A195,'BBG Data'!A:A,'BBG Data'!F:F) -> 7.4556896e+09 | N195: =N194-N194*O195/360*_xlfn.XLOOKUP('Tether Assets'!A195,'BBG Data'!A:A,'BBG Data'!V:V) -> 4.9884222e+10 | O195: 90 | P195: =P194-P194*Q195/360*_xlfn.XLOOKUP(A195,'BBG Data'!A:A,'BBG Data'!AC:AC) -> 46371747 | Q195: 180 | R195: 5349078821 | S195: =S194-S194*T195/360*_xlfn.XLOOKUP('Tether Assets'!A195,'BBG Data'!A:A,'BBG Data'!AB:AB) -> 1.3761619e+08 | T195: 210 | U195: =2138395675 -> 2138395675 | V195: =U195+S195+R195+P195+N195+M195+K195+J195+I195+H195+E195+B195 -> 7.8738922e+10 | W195: =(I195+J195)/V195 -> 0.10138062 | X195: =N195/V195 -> 0.63353956 | Y195: =USDT_FinalReserves!G194/USDT_FinalReserves!$F194 -> 0.0087571306 | Z195: 8.102032e+10 | AA195: 8.0310814e+10
A196: 45027 | B196: 0 | C196: 52798.71 | D196: =_xlfn.XLOOKUP(A196,'BBG Data'!A:A,'BBG Data'!B:B) -> 30192.1 | E196: =C196*D196 -> 1.5941039e+09 | F196: 1721995.7 | G196: =_xlfn.XLOOKUP(A196,'BBG Data'!A:A,'BBG Data'!C:C) -> 2003.62 | H196: =G196*F196 -> 3.450225e+09 | I196: 481350555 | J196: =J195-$J$1*J195*_xlfn.XLOOKUP(A196,'BBG Data'!A:A,'BBG Data'!F:F) -> 7.5014584e+09 | K196: =K195-K195*L196/360*_xlfn.XLOOKUP(A196,'BBG Data'!A:A,'BBG Data'!J:J) -> 7.7346185e+08 | L196: 90 | M196: =M195-M195*$M$1*_xlfn.XLOOKUP(A196,'BBG Data'!A:A,'BBG Data'!F:F) -> 7.4561038e+09 | N196: =N195-N195*O196/360*_xlfn.XLOOKUP('Tether Assets'!A196,'BBG Data'!A:A,'BBG Data'!V:V) -> 4.9934106e+10 | O196: 90 | P196: =P195-P195*Q196/360*_xlfn.XLOOKUP(A196,'BBG Data'!A:A,'BBG Data'!AC:AC) -> 45792101 | Q196: 180 | R196: 5349078821 | S196: =S195-S195*T196/360*_xlfn.XLOOKUP('Tether Assets'!A196,'BBG Data'!A:A,'BBG Data'!AB:AB) -> 1.3877217e+08 | T196: 210 | U196: =2138395675 -> 2138395675 | V196: =U196+S196+R196+P196+N196+M196+K196+J196+I196+H196+E196+B196 -> 7.8862848e+10 | W196: =(I196+J196)/V196 -> 0.10122395 | X196: =N196/V196 -> 0.63317655 | Y196: =USDT_FinalReserves!G195/USDT_FinalReserves!$F195 -> 0.03159447 | Z196: 8.3013575e+10 | AA196: 8.0390805e+10
A197: 45028 | B197: 0 | C197: 52798.71 | D197: =_xlfn.XLOOKUP(A197,'BBG Data'!A:A,'BBG Data'!B:B) -> 29968.01 | E197: =C197*D197 -> 1.5822723e+09 | F197: 1721995.7 | G197: =_xlfn.XLOOKUP(A197,'BBG Data'!A:A,'BBG Data'!C:C) -> 2014.93 | H197: =G197*F197 -> 3.4697008e+09 | I197: 481350555 | J197: =J196-$J$1*J196*_xlfn.XLOOKUP(A197,'BBG Data'!A:A,'BBG Data'!F:F) -> 7.5014584e+09 | K197: =K196-K196*L197/360*_xlfn.XLOOKUP(A197,'BBG Data'!A:A,'BBG Data'!J:J) -> 7.7089783e+08 | L197: 90 | M197: =M196-M196*$M$1*_xlfn.XLOOKUP(A197,'BBG Data'!A:A,'BBG Data'!F:F) -> 7.4561038e+09 | N197: =N196-N196*O197/360*_xlfn.XLOOKUP('Tether Assets'!A197,'BBG Data'!A:A,'BBG Data'!V:V) -> 4.9696919e+10 | O197: 90 | P197: =P196-P196*Q197/360*_xlfn.XLOOKUP(A197,'BBG Data'!A:A,'BBG Data'!AC:AC) -> 46089749 | Q197: 180 | R197: 5349078821 | S197: =S196-S196*T197/360*_xlfn.XLOOKUP('Tether Assets'!A197,'BBG Data'!A:A,'BBG Data'!AB:AB) -> 1.4043165e+08 | T197: 210 | U197: =2138395675 -> 2138395675 | V197: =U197+S197+R197+P197+N197+M197+K197+J197+I197+H197+E197+B197 -> 7.8632698e+10 | W197: =(I197+J197)/V197 -> 0.10152022 | X197: =N197/V197 -> 0.6320134 | Y197: =USDT_FinalReserves!G196/USDT_FinalReserves!$F196 -> 0.02723142 | Z197: 8.2780486e+10 | AA197: 8.0526255e+10
... A275: 45106 | B275: 0 | C275: 52798.71 | D275: =_xlfn.XLOOKUP(A275,'BBG Data'!A:A,'BBG Data'!B:B) -> 30400.46 | E275: =C275*D275 -> 1.6051051e+09 | F275: 1721995.7 | G275: =_xlfn.XLOOKUP(A275,'BBG Data'!A:A,'BBG Data'!C:C) -> 1908.2 | H275: =G275*F275 -> 3.2859122e+09 | I275: 481350555 | J275: =J274-$J$1*J274*_xlfn.XLOOKUP(A275,'BBG Data'!A:A,'BBG Data'!F:F) -> 7.4960408e+09 | K275: =K274-K274*L275/360*_xlfn.XLOOKUP(A275,'BBG Data'!A:A,'BBG Data'!J:J) -> 7.2242421e+08 | L275: 90 | M275: =M274-M274*$M$1*_xlfn.XLOOKUP(A275,'BBG Data'!A:A,'BBG Data'!F:F) -> 7.4453342e+09 | N275: =N274-N274*O275/360*_xlfn.XLOOKUP('Tether Assets'!A275,'BBG Data'!A:A,'BBG Data'!V:V) -> 4.5581191e+10 | O275: 90 | P275: =P274-P274*Q275/360*_xlfn.XLOOKUP(A275,'BBG Data'!A:A,'BBG Data'!AC:AC) -> 35225600 | Q275: 180 | R275: 5349078821 | S275: =S274-S274*T275/360*_xlfn.XLOOKUP('Tether Assets'!A275,'BBG Data'!A:A,'BBG Data'!AB:AB) -> 83986912 | T275: 210 | U275: =2138395675 -> 2138395675 | V275: =U275+S275+R275+P275+N275+M275+K275+J275+I275+H275+E275+B275 -> 7.4224045e+10 | W275: =(I275+J275)/V275 -> 0.10747718 | X275: =N275/V275 -> 0.61410276 | Y275: =USDT_FinalReserves!G274/USDT_FinalReserves!$F274 -> 0.030358759 | Z275: 8.5926346e+10 | AA275: 8.3317728e+10
A276: 45107 | B276: 0 | C276: 77327.176 | D276: =_xlfn.XLOOKUP(A276,'BBG Data'!A:A,'BBG Data'!B:B) -> 30390.91 | E276: =C276*D276 -> 2.3500432e+09 | F276: 1703814.7 | G276: =_xlfn.XLOOKUP(A276,'BBG Data'!A:A,'BBG Data'!C:C) -> 1919.35 | H276: =G276*F276 -> 3270216824 | I276: 90811797 | J276: 8893000000 | K276: 577232281 | L276: 90 | M276: 8133865426 | N276: 55809730658 | O276: 90 | P276: 62937172 | Q276: 450 | R276: 5504292639 | S276: 115496758 | T276: 180 | U276: =1676229360 -> 1676229360 | V276: =U276+S276+R276+P276+N276+M276+K276+J276+I276+H276+E276+B276 -> 8.6483856e+10 | W276: =(I276+J276)/V276 -> 0.10387848 | X276: =N276/V276 -> 0.64531964 | Y276: =USDT_FinalReserves!G275/USDT_FinalReserves!$F275 -> 0.038396064 | Z276: 8.6725889e+10 | AA276: 8.3395956e+10
A277: 45108 | B277: 0 | C277: 77327.176 | D277: =_xlfn.XLOOKUP(A277,'BBG Data'!A:A,'BBG Data'!B:B) -> 30592.81 | E277: =C277*D277 -> 2.3656556e+09 | F277: 1703814.7 | G277: =_xlfn.XLOOKUP(A277,'BBG Data'!A:A,'BBG Data'!C:C) -> 1919.35 | H277: =G277*F277 -> 3270216824 | I277: 90811797 | J277: =J276-$J$1*J276*_xlfn.XLOOKUP(A277,'BBG Data'!A:A,'BBG Data'!F:F) -> 8893000000 | K277: =K276-K276*L277/360*_xlfn.XLOOKUP(A277,'BBG Data'!A:A,'BBG Data'!J:J) -> 577232281 | L277: 90 | M277: =M276-M276*$M$1*_xlfn.XLOOKUP(A277,'BBG Data'!A:A,'BBG Data'!F:F) -> 8133865426 | N277: =N276-N276*O277/360*_xlfn.XLOOKUP('Tether Assets'!A277,'BBG Data'!A:A,'BBG Data'!V:V) -> 55809730658 | O277: 90 | P277: =P276-P276*Q277/360*_xlfn.XLOOKUP(A277,'BBG Data'!A:A,'BBG Data'!AF:AF) -> 62937172 | Q277: 450 | R277: 5504292639 | S277: =S276-S276*T277/360*_xlfn.XLOOKUP('Tether Assets'!A277,'BBG Data'!A:A,'BBG Data'!AB:AB) -> 115496758 | T277: 180 | U277: =1676229360 -> 1676229360 | V277: =U277+S277+R277+P277+N277+M277+K277+J277+I277+H277+E277+B277 -> 8.6499469e+10 | W277: =(I277+J277)/V277 -> 0.10385973 | X277: =N277/V277 -> 0.64520316 | Y277: =USDT_FinalReserves!G276/USDT_FinalReserves!$F276 -> 0.038569625 | Z277: 8.6625744e+10 | AA277: 8.3284622e+10
A278: 45109 | B278: 0 | C278: 77327.176 | D278: =_xlfn.XLOOKUP(A278,'BBG Data'!A:A,'BBG Data'!B:B) -> 30592.26 | E278: =C278*D278 -> 2.3656131e+09 | F278: 1703814.7 | G278: =_xlfn.XLOOKUP(A278,'BBG Data'!A:A,'BBG Data'!C:C) -> 1919.35 | H278: =G278*F278 -> 3270216824 | I278: 90811797 | J278: =J277-$J$1*J277*_xlfn.XLOOKUP(A278,'BBG Data'!A:A,'BBG Data'!F:F) -> 8893000000 | K278: =K277-K277*L278/360*_xlfn.XLOOKUP(A278,'BBG Data'!A:A,'BBG Data'!J:J) -> 577232281 | L278: 90 | M278: =M277-M277*$M$1*_xlfn.XLOOKUP(A278,'BBG Data'!A:A,'BBG Data'!F:F) -> 8133865426 | N278: =N277-N277*O278/360*_xlfn.XLOOKUP('Tether Assets'!A278,'BBG Data'!A:A,'BBG Data'!V:V) -> 55809730658 | O278: 90 | P278: =P277-P277*Q278/360*_xlfn.XLOOKUP(A278,'BBG Data'!A:A,'BBG Data'!AF:AF) -> 62937172 | Q278: 450 | R278: 5504292639 | S278: =S277-S277*T278/360*_xlfn.XLOOKUP('Tether Assets'!A278,'BBG Data'!A:A,'BBG Data'!AB:AB) -> 115496758 | T278: 180 | U278: =1676229360 -> 1676229360 | V278: =U278+S278+R278+P278+N278+M278+K278+J278+I278+H278+E278+B278 -> 8.6499426e+10 | W278: =(I278+J278)/V278 -> 0.10385979 | X278: =N278/V278 -> 0.64520348 | Y278: =USDT_FinalReserves!G277/USDT_FinalReserves!$F277 -> 0.038395591 | Z278: 8.6663094e+10 | AA278: 8.3335613e+10
A279: 45110 | B279: 0 | C279: 77327.176 | D279: =_xlfn.XLOOKUP(A279,'BBG Data'!A:A,'BBG Data'!B:B) -> 31128.76 | E279: =C279*D279 -> 2.4070991e+09 | F279: 1703814.7 | G279: =_xlfn.XLOOKUP(A279,'BBG Data'!A:A,'BBG Data'!C:C) -> 1921.64 | H279: =G279*F279 -> 3.2741186e+09 | I279: 90811797 | J279: =J278-$J$1*J278*_xlfn.XLOOKUP(A279,'BBG Data'!A:A,'BBG Data'!F:F) -> 8.8937411e+09 | K279: =K278-K278*L279/360*_xlfn.XLOOKUP(A279,'BBG Data'!A:A,'BBG Data'!J:J) -> 5.7717744e+08 | L279: 90 | M279: =M278-M278*$M$1*_xlfn.XLOOKUP(A279,'BBG Data'!A:A,'BBG Data'!F:F) -> 8.1352211e+09 | N279: =N278-N278*O279/360*_xlfn.XLOOKUP('Tether Assets'!A279,'BBG Data'!A:A,'BBG Data'!V:V) -> 5.5753921e+10 | O279: 90 | P279: =P278-P278*Q279/360*_xlfn.XLOOKUP(A279,'BBG Data'!A:A,'BBG Data'!AF:AF) -> 62622486 | Q279: 450 | R279: 5504292639 | S279: =S278-S278*T279/360*_xlfn.XLOOKUP('Tether Assets'!A279,'BBG Data'!A:A,'BBG Data'!AB:AB) -> 1.1647271e+08 | T279: 180 | U279: =1676229360 -> 1676229360 | V279: =U279+S279+R279+P279+N279+M279+K279+J279+I279+H279+E279+B279 -> 8.6491707e+10 | W279: =(I279+J279)/V279 -> 0.10387762 | X279: =N279/V279 -> 0.6446158 | Y279: =USDT_FinalReserves!G278/USDT_FinalReserves!$F278 -> 0.038310247 | Z279: 8.6592805e+10 | AA279: 8.3275413e+10
A280: 45111 | B280: 0 | C280: 77327.176 | D280: =_xlfn.XLOOKUP(A280,'BBG Data'!A:A,'BBG Data'!B:B) -> 30807.48 | E280: =C280*D280 -> 2.3822554e+09 | F280: 1703814.7 | G280: =_xlfn.XLOOKUP(A280,'BBG Data'!A:A,'BBG Data'!C:C) -> 1925.48 | H280: =G280*F280 -> 3.2806612e+09 | I280: 90811797 | J280: =J279-$J$1*J279*_xlfn.XLOOKUP(A280,'BBG Data'!A:A,'BBG Data'!F:F) -> 8.8937411e+09 | K280: =K279-K279*L280/360*_xlfn.XLOOKUP(A280,'BBG Data'!A:A,'BBG Data'!J:J) -> 5.7717744e+08 | L280: 90 | M280: =M279-M279*$M$1*_xlfn.XLOOKUP(A280,'BBG Data'!A:A,'BBG Data'!F:F) -> 8.1352211e+09 | N280: =N279-N279*O280/360*_xlfn.XLOOKUP('Tether Assets'!A280,'BBG Data'!A:A,'BBG Data'!V:V) -> 5.5182443e+10 | O280: 90 | P280: =P279-P279*Q280/360*_xlfn.XLOOKUP(A280,'BBG Data'!A:A,'BBG Data'!AF:AF) -> 62622486 | Q280: 450 | R280: 5504292639 | S280: =S279-S279*T280/360*_xlfn.XLOOKUP('Tether Assets'!A280,'BBG Data'!A:A,'BBG Data'!AB:AB) -> 1.1647271e+08 | T280: 180 | U280: =1676229360 -> 1676229360 | V280: =U280+S280+R280+P280+N280+M280+K280+J280+I280+H280+E280+B280 -> 8.5901928e+10 | W280: =(I280+J280)/V280 -> 0.10459082 | X280: =N280/V280 -> 0.64238888 | Y280: =USDT_FinalReserves!G279/USDT_FinalReserves!$F279 -> 0.031793959 | Z280: 8.6077298e+10 | AA280: 8.334056e+10
A281: 45112 | B281: 0 | C281: 77327.176 | D281: =_xlfn.XLOOKUP(A281,'BBG Data'!A:A,'BBG Data'!B:B) -> 30470.54 | E281: =C281*D281 -> 2.3562008e+09 | F281: 1703814.7 | G281: =_xlfn.XLOOKUP(A281,'BBG Data'!A:A,'BBG Data'!C:C) -> 1915.3 | H281: =G281*F281 -> 3.2633164e+09 | I281: 90811797 | J281: =J280-$J$1*J280*_xlfn.XLOOKUP(A281,'BBG Data'!A:A,'BBG Data'!F:F) -> 8.8937411e+09 | K281: =K280-K280*L281/360*_xlfn.XLOOKUP(A281,'BBG Data'!A:A,'BBG Data'!J:J) -> 5.760202e+08 | L281: 90 | M281: =M280-M280*$M$1*_xlfn.XLOOKUP(A281,'BBG Data'!A:A,'BBG Data'!F:F) -> 8.1352211e+09 | N281: =N280-N280*O281/360*_xlfn.XLOOKUP('Tether Assets'!A281,'BBG Data'!A:A,'BBG Data'!V:V) -> 5.5113465e+10 | O281: 90 | P281: =P280-P280*Q281/360*_xlfn.XLOOKUP(A281,'BBG Data'!A:A,'BBG Data'!AF:AF) -> 64109770 | Q281: 450 | R281: 5504292639 | S281: =S280-S280*T281/360*_xlfn.XLOOKUP('Tether Assets'!A281,'BBG Data'!A:A,'BBG Data'!AB:AB) -> 1.1455091e+08 | T281: 180 | U281: =1676229360 -> 1676229360 | V281: =U281+S281+R281+P281+N281+M281+K281+J281+I281+H281+E281+B281 -> 8.5787959e+10 | W281: =(I281+J281)/V281 -> 0.10472977 | X281: =N281/V281 -> 0.64243824 | Y281: =USDT_FinalReserves!G280/USDT_FinalReserves!$F280 -> 0.037118574 | Z281: 8.6594237e+10 | AA281: 8.3379982e+10
A282: 45113 | B282: 0 | C282: 77327.176 | D282: =_xlfn.XLOOKUP(A282,'BBG Data'!A:A,'BBG Data'!B:B) -> 30315.91 | E282: =C282*D282 -> 2.3442437e+09 | F282: 1703814.7 | G282: =_xlfn.XLOOKUP(A282,'BBG Data'!A:A,'BBG Data'!C:C) -> 1910.9 | H282: =G282*F282 -> 3.2558196e+09 | I282: 90811797 | J282: =J281-$J$1*J281*_xlfn.XLOOKUP(A282,'BBG Data'!A:A,'BBG Data'!F:F) -> 8.8937411e+09 | K282: =K281-K281*L282/360*_xlfn.XLOOKUP(A282,'BBG Data'!A:A,'BBG Data'!J:J) -> 5.7542402e+08 | L282: 90 | M282: =M281-M281*$M$1*_xlfn.XLOOKUP(A282,'BBG Data'!A:A,'BBG Data'!F:F) -> 8.1352211e+09 | N282: =N281-N281*O282/360*_xlfn.XLOOKUP('Tether Assets'!A282,'BBG Data'!A:A,'BBG Data'!V:V) -> 5.4948125e+10 | O282: 90 | P282: =P281-P281*Q282/360*_xlfn.XLOOKUP(A282,'BBG Data'!A:A,'BBG Data'!AF:AF) -> 62026203 | Q282: 450 | R282: 5504292639 | S282: =S281-S281*T282/360*_xlfn.XLOOKUP('Tether Assets'!A282,'BBG Data'!A:A,'BBG Data'!AB:AB) -> 1.1163559e+08 | T282: 180 | U282: =1676229360 -> 1676229360 | V282: =U282+S282+R282+P282+N282+M282+K282+J282+I282+H282+E282+B282 -> 8.559757e+10 | W282: =(I282+J282)/V282 -> 0.10496271 | X282: =N282/V282 -> 0.64193557 | Y282: =USDT_FinalReserves!G281/USDT_FinalReserves!$F281 -> 0.036257228 | Z282: 8.645286e+10 | AA282: 8.3318318e+10
A283: 45114 | B283: 0 | C283: 77327.176 | D283: =_xlfn.XLOOKUP(A283,'BBG Data'!A:A,'BBG Data'!B:B) -> 30272.41 | E283: =C283*D283 -> 2.34088e+09 | F283: 1703814.7 | G283: =_xlfn.XLOOKUP(A283,'BBG Data'!A:A,'BBG Data'!C:C) -> 1925.05 | H283: =G283*F283 -> 3.2799286e+09 | I283: 90811797 | J283: =J282-$J$1*J282*_xlfn.XLOOKUP(A283,'BBG Data'!A:A,'BBG Data'!F:F) -> 8.8937411e+09 | K283: =K282-K282*L283/360*_xlfn.XLOOKUP(A283,'BBG Data'!A:A,'BBG Data'!J:J) -> 5.7289647e+08 | L283: 90 | M283: =M282-M282*$M$1*_xlfn.XLOOKUP(A283,'BBG Data'!A:A,'BBG Data'!F:F) -> 8.1352211e+09 | N283: =N282-N282*O283/360*_xlfn.XLOOKUP('Tether Assets'!A283,'BBG Data'!A:A,'BBG Data'!V:V) -> 5.4893177e+10 | O283: 90 | P283: =P282-P282*Q283/360*_xlfn.XLOOKUP(A283,'BBG Data'!A:A,'BBG Data'!AF:AF) -> 63421792 | Q283: 450 | R283: 5504292639 | S283: =S282-S282*T283/360*_xlfn.XLOOKUP('Tether Assets'!A283,'BBG Data'!A:A,'BBG Data'!AB:AB) -> 1.1114997e+08 | T283: 180 | U283: =1676229360 -> 1676229360 | V283: =U283+S283+R283+P283+N283+M283+K283+J283+I283+H283+E283+B283 -> 8.5561749e+10 | W283: =(I283+J283)/V283 -> 0.10500665 | X283: =N283/V283 -> 0.64156211 | Y283: =USDT_FinalReserves!G282/USDT_FinalReserves!$F282 -> 0.037993488 | Z283: 8.6782491e+10 | AA283: 8.3485321e+10
A284: 45115 | B284: 0 | C284: 77327.176 | D284: =_xlfn.XLOOKUP(A284,'BBG Data'!A:A,'BBG Data'!B:B) -> 30163.19 | E284: =C284*D284 -> 2.3324343e+09 | F284: 1703814.7 | G284: =_xlfn.XLOOKUP(A284,'BBG Data'!A:A,'BBG Data'!C:C) -> 1925.05 | H284: =G284*F284 -> 3.2799286e+09 | I284: 90811797 | J284: =J283-$J$1*J283*_xlfn.XLOOKUP(A284,'BBG Data'!A:A,'BBG Data'!F:F) -> 8.8937411e+09 | K284: =K283-K283*L284/360*_xlfn.XLOOKUP(A284,'BBG Data'!A:A,'BBG Data'!J:J) -> 5.7289647e+08 | L284: 90 | M284: =M283-M283*$M$1*_xlfn.XLOOKUP(A284,'BBG Data'!A:A,'BBG Data'!F:F) -> 8.1352211e+09 | N284: =N283-N283*O284/360*_xlfn.XLOOKUP('Tether Assets'!A284,'BBG Data'!A:A,'BBG Data'!V:V) -> 5.4893177e+10 | O284: 90 | P284: =P283-P283*Q284/360*_xlfn.XLOOKUP(A284,'BBG Data'!A:A,'BBG Data'!AF:AF) -> 63421792 | Q284: 450 | R284: 5504292639 | S284: =S283-S283*T284/360*_xlfn.XLOOKUP('Tether Assets'!A284,'BBG Data'!A:A,'BBG Data'!AB:AB) -> 1.1114997e+08 | T284: 180 | U284: =1676229360 -> 1676229360 | V284: =U284+S284+R284+P284+N284+M284+K284+J284+I284+H284+E284+B284 -> 8.5553304e+10 | W284: =(I284+J284)/V284 -> 0.10501702 | X284: =N284/V284 -> 0.64162545 | Y284: =USDT_FinalReserves!G283/USDT_FinalReserves!$F283 -> 0.038301136 | Z284: 8.6681584e+10 | AA284: 8.3361581e+10
A285: 45116 | B285: 0 | C285: 77327.176 | D285: =_xlfn.XLOOKUP(A285,'BBG Data'!A:A,'BBG Data'!B:B) -> 30201.16 | E285: =C285*D285 -> 2.3353704e+09 | F285: 1703814.7 | G285: =_xlfn.XLOOKUP(A285,'BBG Data'!A:A,'BBG Data'!C:C) -> 1925.05 | H285: =G285*F285 -> 3.2799286e+09 | I285: 90811797 | J285: =J284-$J$1*J284*_xlfn.XLOOKUP(A285,'BBG Data'!A:A,'BBG Data'!F:F) -> 8.8937411e+09 | K285: =K284-K284*L285/360*_xlfn.XLOOKUP(A285,'BBG Data'!A:A,'BBG Data'!J:J) -> 5.7289647e+08 | L285: 90 | M285: =M284-M284*$M$1*_xlfn.XLOOKUP(A285,'BBG Data'!A:A,'BBG Data'!F:F) -> 8.1352211e+09 | N285: =N284-N284*O285/360*_xlfn.XLOOKUP('Tether Assets'!A285,'BBG Data'!A:A,'BBG Data'!V:V) -> 5.4893177e+10 | O285: 90 | P285: =P284-P284*Q285/360*_xlfn.XLOOKUP(A285,'BBG Data'!A:A,'BBG Data'!AF:AF) -> 63421792 | Q285: 450 | R285: 5504292639 | S285: =S284-S284*T285/360*_xlfn.XLOOKUP('Tether Assets'!A285,'BBG Data'!A:A,'BBG Data'!AB:AB) -> 1.1114997e+08 | T285: 180 | U285: =1676229360 -> 1676229360 | V285: =U285+S285+R285+P285+N285+M285+K285+J285+I285+H285+E285+B285 -> 8.555624e+10 | W285: =(I285+J285)/V285 -> 0.10501341 | X285: =N285/V285 -> 0.64160343 | Y285: =USDT_FinalReserves!G284/USDT_FinalReserves!$F284 -> 0.038429065 | Z285: 8.673317e+10 | AA285: 8.3400095e+10
A286: 45117 | B286: 0 | C286: 77327.176 | D286: =_xlfn.XLOOKUP(A286,'BBG Data'!A:A,'BBG Data'!B:B) -> 30785.96 | E286: =C286*D286 -> 2.3805913e+09 | F286: 1703814.7 | G286: =_xlfn.XLOOKUP(A286,'BBG Data'!A:A,'BBG Data'!C:C) -> 1925.35 | H286: =G286*F286 -> 3.2804397e+09 | I286: 90811797 | J286: =J285-$J$1*J285*_xlfn.XLOOKUP(A286,'BBG Data'!A:A,'BBG Data'!F:F) -> 8.8937411e+09 | K286: =K285-K285*L286/360*_xlfn.XLOOKUP(A286,'BBG Data'!A:A,'BBG Data'!J:J) -> 5.7274895e+08 | L286: 90 | M286: =M285-M285*$M$1*_xlfn.XLOOKUP(A286,'BBG Data'!A:A,'BBG Data'!F:F) -> 8.1352211e+09 | N286: =N285-N285*O286/360*_xlfn.XLOOKUP('Tether Assets'!A286,'BBG Data'!A:A,'BBG Data'!V:V) -> 5.4879453e+10 | O286: 90 | P286: =P285-P285*Q286/360*_xlfn.XLOOKUP(A286,'BBG Data'!A:A,'BBG Data'!AF:AF) -> 65086614 | Q286: 450 | R286: 5504292639 | S286: =S285-S285*T286/360*_xlfn.XLOOKUP('Tether Assets'!A286,'BBG Data'!A:A,'BBG Data'!AB:AB) -> 1.1237262e+08 | T286: 180 | U286: =1676229360 -> 1676229360 | V286: =U286+S286+R286+P286+N286+M286+K286+J286+I286+H286+E286+B286 -> 8.5590989e+10 | W286: =(I286+J286)/V286 -> 0.10497078 | X286: =N286/V286 -> 0.64118261 | Y286: =USDT_FinalReserves!G285/USDT_FinalReserves!$F285 -> 0.038786462 | Z286: 8.676734e+10 | AA286: 8.3401942e+10
A287: 45118 | B287: 0 | C287: 77327.176 | D287: =_xlfn.XLOOKUP(A287,'BBG Data'!A:A,'BBG Data'!B:B) -> 30578.75 | E287: =C287*D287 -> 2.3645684e+09 | F287: 1703814.7 | G287: =_xlfn.XLOOKUP(A287,'BBG Data'!A:A,'BBG Data'!C:C) -> 1932.23 | H287: =G287*F287 -> 3.292162e+09 | I287: 90811797 | J287: =J286-$J$1*J286*_xlfn.XLOOKUP(A287,'BBG Data'!A:A,'BBG Data'!F:F) -> 8.8937411e+09 | K287: =K286-K286*L287/360*_xlfn.XLOOKUP(A287,'BBG Data'!A:A,'BBG Data'!J:J) -> 5.7252128e+08 | L287: 90 | M287: =M286-M286*$M$1*_xlfn.XLOOKUP(A287,'BBG Data'!A:A,'BBG Data'!F:F) -> 8.1352211e+09 | N287: =N286-N286*O287/360*_xlfn.XLOOKUP('Tether Assets'!A287,'BBG Data'!A:A,'BBG Data'!V:V) -> 5.4385538e+10 | O287: 90 | P287: =P286-P286*Q287/360*_xlfn.XLOOKUP(A287,'BBG Data'!A:A,'BBG Data'!AF:AF) -> 64273032 | Q287: 450 | R287: 5504292639 | S287: =S286-S286*T287/360*_xlfn.XLOOKUP('Tether Assets'!A287,'BBG Data'!A:A,'BBG Data'!AB:AB) -> 1.1249623e+08 | T287: 180 | U287: =1676229360 -> 1676229360 | V287: =U287+S287+R287+P287+N287+M287+K287+J287+I287+H287+E287+B287 -> 8.5091855e+10 | W287: =(I287+J287)/V287 -> 0.10558652 | X287: =N287/V287 -> 0.63913918 | Y287: =USDT_FinalReserves!G286/USDT_FinalReserves!$F286 -> 0.032755469 | Z287: 8.617994e+10 | AA287: 8.3357075e+10
A288: 45119 | B288: 0 | C288: 77327.176 | D288: =_xlfn.XLOOKUP(A288,'BBG Data'!A:A,'BBG Data'!B:B) -> 30351.84 | E288: =C288*D288 -> 2.3470221e+09 | F288: 1703814.7 | G288: =_xlfn.XLOOKUP(A288,'BBG Data'!A:A,'BBG Data'!C:C) -> 1957.35 | H288: =G288*F288 -> 3.3349618e+09 | I288: 90811797 | J288: =J287-$J$1*J287*_xlfn.XLOOKUP(A288,'BBG Data'!A:A,'BBG Data'!F:F) -> 8.8939881e+09 | K288: =K287-K287*L288/360*_xlfn.XLOOKUP(A288,'BBG Data'!A:A,'BBG Data'!J:J) -> 5.7109571e+08 | L288: 90 | M288: =M287-M287*$M$1*_xlfn.XLOOKUP(A288,'BBG Data'!A:A,'BBG Data'!F:F) -> 8.135673e+09 | N288: =N287-N287*O288/360*_xlfn.XLOOKUP('Tether Assets'!A288,'BBG Data'!A:A,'BBG Data'!V:V) -> 5.4589484e+10 | O288: 90 | P288: =P287-P287*Q288/360*_xlfn.XLOOKUP(A288,'BBG Data'!A:A,'BBG Data'!AF:AF) -> 69173850 | Q288: 450 | R288: 5504292639 | S288: =S287-S287*T288/360*_xlfn.XLOOKUP('Tether Assets'!A288,'BBG Data'!A:A,'BBG Data'!AB:AB) -> 1.1759231e+08 | T288: 180 | U288: =1676229360 -> 1676229360 | V288: =U288+S288+R288+P288+N288+M288+K288+J288+I288+H288+E288+B288 -> 8.5330325e+10 | W288: =(I288+J288)/V288 -> 0.10529434 | X288: =N288/V288 -> 0.63974307 | Y288: =USDT_FinalReserves!G287/USDT_FinalReserves!$F287 -> 0.041083424 | Z288: 8.697449e+10 | AA288: 8.3401281e+10
... A367: 45198 | B367: 0 | C367: 77327.176 | D367: =_xlfn.XLOOKUP(A367,'BBG Data'!A:A,'BBG Data'!B:B) -> 26903.18 | E367: =C367*D367 -> 2.0803469e+09 | F367: 1703814.7 | G367: =_xlfn.XLOOKUP(A367,'BBG Data'!A:A,'BBG Data'!C:C) -> 1848.63 | H367: =G367*F367 -> 3.149723e+09 | I367: 90811797 | J367: =J366-$J$1*J366*_xlfn.XLOOKUP(A367,'BBG Data'!A:A,'BBG Data'!F:F) -> 8.8875648e+09 | K367: =K366-K366*L367/360*_xlfn.XLOOKUP(A367,'BBG Data'!A:A,'BBG Data'!J:J) -> 5.5912657e+08 | L367: 90 | M367: =M366-M366*$M$1*_xlfn.XLOOKUP(A367,'BBG Data'!A:A,'BBG Data'!F:F) -> 8.1239219e+09 | N367: =N366-N366*O367/360*_xlfn.XLOOKUP('Tether Assets'!A367,'BBG Data'!A:A,'BBG Data'!V:V) -> 5.3690882e+10 | O367: 90 | P367: =P366-P366*Q367/360*_xlfn.XLOOKUP(A367,'BBG Data'!A:A,'BBG Data'!AF:AF) -> 57520305 | Q367: 450 | R367: 5504292639 | S367: =S366-S366*T367/360*_xlfn.XLOOKUP('Tether Assets'!A367,'BBG Data'!A:A,'BBG Data'!AB:AB) -> 1.0199833e+08 | T367: 180 | U367: =1676229360 -> 1676229360 | V367: =U367+S367+R367+P367+N367+M367+K367+J367+I367+H367+E367+B367 -> 8.3922418e+10 | W367: =(I367+J367)/V367 -> 0.10698425 | X367: =N367/V367 -> 0.63976806 | Y367: =USDT_FinalReserves!G366/USDT_FinalReserves!$F366 -> 0.040044509 | Z367: 8.6740921e+10 | AA367: 8.3267423e+10
A368: 45199 | B368: 0 | C368: 59391.371 | D368: =_xlfn.XLOOKUP(A368,'BBG Data'!A:A,'BBG Data'!B:B) -> 27072.54 | E368: =C368*D368 -> 1.6078753e+09 | F368: 1703814.7 | G368: =_xlfn.XLOOKUP(A368,'BBG Data'!A:A,'BBG Data'!C:C) -> 1848.63 | H368: =G368*F368 -> 3149722956 | I368: 292641978 | J368: =8203000000 -> 8203000000 | K368: 652002048 | L368: 90 | M368: 8233687005 | N368: 56611569049 | O368: 90 | P368: 65248902 | Q368: 450 | R368: 5168269890 | S368: 88570555 | T368: 150 | U368: =2257992725 -> 2257992725 | V368: =U368+S368+R368+P368+N368+M368+K368+J368+I368+H368+E368+B368 -> 8.633058e+10 | W368: =(I368+J368)/V368 -> 0.098408257 | X368: =N368/V368 -> 0.65575337 | Y368: =USDT_FinalReserves!G367/USDT_FinalReserves!$F367 -> 0.037405836 | Z368: 8.6503715e+10 | AA368: 8.3267971e+10
A369: 45200 | B369: 0 | C369: 59391.371 | D369: =_xlfn.XLOOKUP(A369,'BBG Data'!A:A,'BBG Data'!B:B) -> 27114.69 | E369: =C369*D369 -> 1.6103786e+09 | F369: 1703814.7 | G369: =_xlfn.XLOOKUP(A369,'BBG Data'!A:A,'BBG Data'!C:C) -> 1848.63 | H369: =G369*F369 -> 3149722956 | I369: 292641978 | J369: =J368-$J$1*J368*_xlfn.XLOOKUP(A369,'BBG Data'!A:A,'BBG Data'!F:F) -> 8203000000 | K369: =K368-K368*L369/360*_xlfn.XLOOKUP(A369,'BBG Data'!A:A,'BBG Data'!J:J) -> 652002048 | L369: 90 | M369: =M368-M368*$M$1*_xlfn.XLOOKUP(A369,'BBG Data'!A:A,'BBG Data'!F:F) -> 8233687005 | N369: =N368-N368*O369/360*_xlfn.XLOOKUP('Tether Assets'!A369,'BBG Data'!A:A,'BBG Data'!V:V) -> 56611569049 | O369: 90 | P369: =P368-P368*Q369/360*_xlfn.XLOOKUP(A369,'BBG Data'!A:A,'BBG Data'!AF:AF) -> 65248902 | Q369: 450 | R369: 5168269890 | S369: =S368-S368*T369/360*_xlfn.XLOOKUP('Tether Assets'!A369,'BBG Data'!A:A,'BBG Data'!AB:AB) -> 88570555 | T369: 150 | U369: =2257992725 -> 2257992725 | V369: =U369+S369+R369+P369+N369+M369+K369+J369+I369+H369+E369+B369 -> 8.6333084e+10 | W369: =(I369+J369)/V369 -> 0.098405404 | X369: =N369/V369 -> 0.65573436 | Y369: =USDT_FinalReserves!G368/USDT_FinalReserves!$F368 -> 0.037433747 | Z369: 8.6495866e+10 | AA369: 8.3258002e+10
A370: 45201 | B370: 0 | C370: 59391.371 | D370: =_xlfn.XLOOKUP(A370,'BBG Data'!A:A,'BBG Data'!B:B) -> 27842.16 | E370: =C370*D370 -> 1.653584e+09 | F370: 1703814.7 | G370: =_xlfn.XLOOKUP(A370,'BBG Data'!A:A,'BBG Data'!C:C) -> 1828.03 | H370: =G370*F370 -> 3.1146244e+09 | I370: 292641978 | J370: =J369-$J$1*J369*_xlfn.XLOOKUP(A370,'BBG Data'!A:A,'BBG Data'!F:F) -> 8.2027721e+09 | K370: =K369-K369*L370/360*_xlfn.XLOOKUP(A370,'BBG Data'!A:A,'BBG Data'!J:J) -> 6.532001e+08 | L370: 90 | M370: =M369-M369*$M$1*_xlfn.XLOOKUP(A370,'BBG Data'!A:A,'BBG Data'!F:F) -> 8.2332296e+09 | N370: =N369-N369*O370/360*_xlfn.XLOOKUP('Tether Assets'!A370,'BBG Data'!A:A,'BBG Data'!V:V) -> 5.6399276e+10 | O370: 90 | P370: =P369-P369*Q370/360*_xlfn.XLOOKUP(A370,'BBG Data'!A:A,'BBG Data'!AF:AF) -> 62068018 | Q370: 450 | R370: 5168269890 | S370: =S369-S369*T370/360*_xlfn.XLOOKUP('Tether Assets'!A370,'BBG Data'!A:A,'BBG Data'!AB:AB) -> 88448770 | T370: 150 | U370: =2257992725 -> 2257992725 | V370: =U370+S370+R370+P370+N370+M370+K370+J370+I370+H370+E370+B370 -> 8.6126107e+10 | W370: =(I370+J370)/V370 -> 0.098639244 | X370: =N370/V370 -> 0.65484529 | Y370: =USDT_FinalReserves!G369/USDT_FinalReserves!$F369 -> 0.03509255 | Z370: 8.6279234e+10 | AA370: 8.3251476e+10
A371: 45202 | B371: 0 | C371: 59391.371 | D371: =_xlfn.XLOOKUP(A371,'BBG Data'!A:A,'BBG Data'!B:B) -> 27396.6 | E371: =C371*D371 -> 1.6271216e+09 | F371: 1703814.7 | G371: =_xlfn.XLOOKUP(A371,'BBG Data'!A:A,'BBG Data'!C:C) -> 1823.02 | H371: =G371*F371 -> 3.1060883e+09 | I371: 292641978 | J371: =J370-$J$1*J370*_xlfn.XLOOKUP(A371,'BBG Data'!A:A,'BBG Data'!F:F) -> 8.2025443e+09 | K371: =K370-K370*L371/360*_xlfn.XLOOKUP(A371,'BBG Data'!A:A,'BBG Data'!J:J) -> 6.4893144e+08 | L371: 90 | M371: =M370-M370*$M$1*_xlfn.XLOOKUP(A371,'BBG Data'!A:A,'BBG Data'!F:F) -> 8.2327722e+09 | N371: =N370-N370*O371/360*_xlfn.XLOOKUP('Tether Assets'!A371,'BBG Data'!A:A,'BBG Data'!V:V) -> 5.5976281e+10 | O371: 90 | P371: =P370-P370*Q371/360*_xlfn.XLOOKUP(A371,'BBG Data'!A:A,'BBG Data'!AF:AF) -> 62921453 | Q371: 450 | R371: 5168269890 | S371: =S370-S370*T371/360*_xlfn.XLOOKUP('Tether Assets'!A371,'BBG Data'!A:A,'BBG Data'!AB:AB) -> 86322315 | T371: 150 | U371: =2257992725 -> 2257992725 | V371: =U371+S371+R371+P371+N371+M371+K371+J371+I371+H371+E371+B371 -> 8.5661887e+10 | W371: =(I371+J371)/V371 -> 0.099171131 | X371: =N371/V371 -> 0.65345608 | Y371: =USDT_FinalReserves!G370/USDT_FinalReserves!$F370 -> 0.032189333 | Z371: 8.6043004e+10 | AA371: 8.3273337e+10
A372: 45203 | B372: 0 | C372: 59391.371 | D372: =_xlfn.XLOOKUP(A372,'BBG Data'!A:A,'BBG Data'!B:B) -> 27659.68 | E372: =C372*D372 -> 1.6427463e+09 | F372: 1703814.7 | G372: =_xlfn.XLOOKUP(A372,'BBG Data'!A:A,'BBG Data'!C:C) -> 1821.36 | H372: =G372*F372 -> 3.1032599e+09 | I372: 292641978 | J372: =J371-$J$1*J371*_xlfn.XLOOKUP(A372,'BBG Data'!A:A,'BBG Data'!F:F) -> 8.2027721e+09 | K372: =K371-K371*L372/360*_xlfn.XLOOKUP(A372,'BBG Data'!A:A,'BBG Data'!J:J) -> 6.4761573e+08 | L372: 90 | M372: =M371-M371*$M$1*_xlfn.XLOOKUP(A372,'BBG Data'!A:A,'BBG Data'!F:F) -> 8.2332296e+09 | N372: =N371-N371*O372/360*_xlfn.XLOOKUP('Tether Assets'!A372,'BBG Data'!A:A,'BBG Data'!V:V) -> 5.5906311e+10 | O372: 90 | P372: =P371-P371*Q372/360*_xlfn.XLOOKUP(A372,'BBG Data'!A:A,'BBG Data'!AF:AF) -> 68269777 | Q372: 450 | R372: 5168269890 | S372: =S371-S371*T372/360*_xlfn.XLOOKUP('Tether Assets'!A372,'BBG Data'!A:A,'BBG Data'!AB:AB) -> 88710565 | T372: 150 | U372: =2257992725 -> 2257992725 | V372: =U372+S372+R372+P372+N372+M372+K372+J372+I372+H372+E372+B372 -> 8.5611819e+10 | W372: =(I372+J372)/V372 -> 0.09923179 | X372: =N372/V372 -> 0.65302094 | Y372: =USDT_FinalReserves!G371/USDT_FinalReserves!$F371 -> 0.036842887 | Z372: 8.6540782e+10 | AA372: 8.335237e+10
A373: 45204 | B373: 0 | C373: 59391.371 | D373: =_xlfn.XLOOKUP(A373,'BBG Data'!A:A,'BBG Data'!B:B) -> 27479 | E373: =C373*D373 -> 1.6320155e+09 | F373: 1703814.7 | G373: =_xlfn.XLOOKUP(A373,'BBG Data'!A:A,'BBG Data'!C:C) -> 1820.3 | H373: =G373*F373 -> 3.1014539e+09 | I373: 292641978 | J373: =J372-$J$1*J372*_xlfn.XLOOKUP(A373,'BBG Data'!A:A,'BBG Data'!F:F) -> 8.2027721e+09 | K373: =K372-K372*L373/360*_xlfn.XLOOKUP(A373,'BBG Data'!A:A,'BBG Data'!J:J) -> 6.5023857e+08 | L373: 90 | M373: =M372-M372*$M$1*_xlfn.XLOOKUP(A373,'BBG Data'!A:A,'BBG Data'!F:F) -> 8.2332296e+09 | N373: =N372-N372*O373/360*_xlfn.XLOOKUP('Tether Assets'!A373,'BBG Data'!A:A,'BBG Data'!V:V) -> 5.5906311e+10 | O373: 90 | P373: =P372-P372*Q373/360*_xlfn.XLOOKUP(A373,'BBG Data'!A:A,'BBG Data'!AF:AF) -> 71853940 | Q373: 450 | R373: 5168269890 | S373: =S372-S372*T373/360*_xlfn.XLOOKUP('Tether Assets'!A373,'BBG Data'!A:A,'BBG Data'!AB:AB) -> 88337242 | T373: 150 | U373: =2257992725 -> 2257992725 | V373: =U373+S373+R373+P373+N373+M373+K373+J373+I373+H373+E373+B373 -> 8.5605116e+10 | W373: =(I373+J373)/V373 -> 0.099239561 | X373: =N373/V373 -> 0.65307207 | Y373: =USDT_FinalReserves!G372/USDT_FinalReserves!$F372 -> 0.037330461 | Z373: 8.6588515e+10 | AA373: 8.3356125e+10
A374: 45205 | B374: 0 | C374: 59391.371 | D374: =_xlfn.XLOOKUP(A374,'BBG Data'!A:A,'BBG Data'!B:B) -> 27995.25 | E374: =C374*D374 -> 1.6626763e+09 | F374: 1703814.7 | G374: =_xlfn.XLOOKUP(A374,'BBG Data'!A:A,'BBG Data'!C:C) -> 1833.01 | H374: =G374*F374 -> 3.1231094e+09 | I374: 292641978 | J374: =J373-$J$1*J373*_xlfn.XLOOKUP(A374,'BBG Data'!A:A,'BBG Data'!F:F) -> 8.203e+09 | K374: =K373-K373*L374/360*_xlfn.XLOOKUP(A374,'BBG Data'!A:A,'BBG Data'!J:J) -> 6.5015079e+08 | L374: 90 | M374: =M373-M373*$M$1*_xlfn.XLOOKUP(A374,'BBG Data'!A:A,'BBG Data'!F:F) -> 8.233687e+09 | N374: =N373-N373*O374/360*_xlfn.XLOOKUP('Tether Assets'!A374,'BBG Data'!A:A,'BBG Data'!V:V) -> 5.5766545e+10 | O374: 90 | P374: =P373-P373*Q374/360*_xlfn.XLOOKUP(A374,'BBG Data'!A:A,'BBG Data'!AF:AF) -> 67632521 | Q374: 450 | R374: 5168269890 | S374: =S373-S373*T374/360*_xlfn.XLOOKUP('Tether Assets'!A374,'BBG Data'!A:A,'BBG Data'!AB:AB) -> 88694271 | T374: 150 | U374: =2257992725 -> 2257992725 | V374: =U374+S374+R374+P374+N374+M374+K374+J374+I374+H374+E374+B374 -> 8.55144e+10 | W374: =(I374+J374)/V374 -> 0.099347502 | X374: =N374/V374 -> 0.65213046 | Y374: =USDT_FinalReserves!G373/USDT_FinalReserves!$F373 -> 0.036384685 | Z374: 8.6506607e+10 | AA374: 8.3359091e+10
A375: 45206 | B375: 0 | C375: 59391.371 | D375: =_xlfn.XLOOKUP(A375,'BBG Data'!A:A,'BBG Data'!B:B) -> 27937.45 | E375: =C375*D375 -> 1.6592434e+09 | F375: 1703814.7 | G375: =_xlfn.XLOOKUP(A375,'BBG Data'!A:A,'BBG Data'!C:C) -> 1833.01 | H375: =G375*F375 -> 3.1231094e+09 | I375: 292641978 | J375: =J374-$J$1*J374*_xlfn.XLOOKUP(A375,'BBG Data'!A:A,'BBG Data'!F:F) -> 8.203e+09 | K375: =K374-K374*L375/360*_xlfn.XLOOKUP(A375,'BBG Data'!A:A,'BBG Data'!J:J) -> 6.5015079e+08 | L375: 90 | M375: =M374-M374*$M$1*_xlfn.XLOOKUP(A375,'BBG Data'!A:A,'BBG Data'!F:F) -> 8.233687e+09 | N375: =N374-N374*O375/360*_xlfn.XLOOKUP('Tether Assets'!A375,'BBG Data'!A:A,'BBG Data'!V:V) -> 5.5766545e+10 | O375: 90 | P375: =P374-P374*Q375/360*_xlfn.XLOOKUP(A375,'BBG Data'!A:A,'BBG Data'!AF:AF) -> 67632521 | Q375: 450 | R375: 5168269890 | S375: =S374-S374*T375/360*_xlfn.XLOOKUP('Tether Assets'!A375,'BBG Data'!A:A,'BBG Data'!AB:AB) -> 88694271 | T375: 150 | U375: =2257992725 -> 2257992725 | V375: =U375+S375+R375+P375+N375+M375+K375+J375+I375+H375+E375+B375 -> 8.5510967e+10 | W375: =(I375+J375)/V375 -> 0.09935149 | X375: =N375/V375 -> 0.65215664 | Y375: =USDT_FinalReserves!G374/USDT_FinalReserves!$F374 -> 0.037367193 | Z375: 8.6651488e+10 | AA375: 8.3413565e+10
A376: 45207 | B376: 0 | C376: 59391.371 | D376: =_xlfn.XLOOKUP(A376,'BBG Data'!A:A,'BBG Data'!B:B) -> 27923.41 | E376: =C376*D376 -> 1.6584096e+09 | F376: 1703814.7 | G376: =_xlfn.XLOOKUP(A376,'BBG Data'!A:A,'BBG Data'!C:C) -> 1833.01 | H376: =G376*F376 -> 3.1231094e+09 | I376: 292641978 | J376: =J375-$J$1*J375*_xlfn.XLOOKUP(A376,'BBG Data'!A:A,'BBG Data'!F:F) -> 8.203e+09 | K376: =K375-K375*L376/360*_xlfn.XLOOKUP(A376,'BBG Data'!A:A,'BBG Data'!J:J) -> 6.5015079e+08 | L376: 90 | M376: =M375-M375*$M$1*_xlfn.XLOOKUP(A376,'BBG Data'!A:A,'BBG Data'!F:F) -> 8.233687e+09 | N376: =N375-N375*O376/360*_xlfn.XLOOKUP('Tether Assets'!A376,'BBG Data'!A:A,'BBG Data'!V:V) -> 5.5766545e+10 | O376: 90 | P376: =P375-P375*Q376/360*_xlfn.XLOOKUP(A376,'BBG Data'!A:A,'BBG Data'!AF:AF) -> 67632521 | Q376: 450 | R376: 5168269890 | S376: =S375-S375*T376/360*_xlfn.XLOOKUP('Tether Assets'!A376,'BBG Data'!A:A,'BBG Data'!AB:AB) -> 88694271 | T376: 150 | U376: =2257992725 -> 2257992725 | V376: =U376+S376+R376+P376+N376+M376+K376+J376+I376+H376+E376+B376 -> 8.5510133e+10 | W376: =(I376+J376)/V376 -> 0.099352459 | X376: =N376/V376 -> 0.652163 | Y376: =USDT_FinalReserves!G375/USDT_FinalReserves!$F375 -> 0.037396449 | Z376: 8.6770364e+10 | AA376: 8.3525461e+10
A377: 45208 | B377: 0 | C377: 59391.371 | D377: =_xlfn.XLOOKUP(A377,'BBG Data'!A:A,'BBG Data'!B:B) -> 27576.46 | E377: =C377*D377 -> 1.6378038e+09 | F377: 1703814.7 | G377: =_xlfn.XLOOKUP(A377,'BBG Data'!A:A,'BBG Data'!C:C) -> 1861.41 | H377: =G377*F377 -> 3.1714977e+09 | I377: 292641978 | J377: =J376-$J$1*J376*_xlfn.XLOOKUP(A377,'BBG Data'!A:A,'BBG Data'!F:F) -> 8.203e+09 | K377: =K376-K376*L377/360*_xlfn.XLOOKUP(A377,'BBG Data'!A:A,'BBG Data'!J:J) -> 6.5015079e+08 | L377: 90 | M377: =M376-M376*$M$1*_xlfn.XLOOKUP(A377,'BBG Data'!A:A,'BBG Data'!F:F) -> 8.233687e+09 | N377: =N376-N376*O377/360*_xlfn.XLOOKUP('Tether Assets'!A377,'BBG Data'!A:A,'BBG Data'!V:V) -> 5.5766545e+10 | O377: 90 | P377: =P376-P376*Q377/360*_xlfn.XLOOKUP(A377,'BBG Data'!A:A,'BBG Data'!AF:AF) -> 67632521 | Q377: 450 | R377: 5168269890 | S377: =S376-S376*T377/360*_xlfn.XLOOKUP('Tether Assets'!A377,'BBG Data'!A:A,'BBG Data'!AB:AB) -> 88694271 | T377: 150 | U377: =2257992725 -> 2257992725 | V377: =U377+S377+R377+P377+N377+M377+K377+J377+I377+H377+E377+B377 -> 8.5537916e+10 | W377: =(I377+J377)/V377 -> 0.099320189 | X377: =N377/V377 -> 0.65195118 | Y377: =USDT_FinalReserves!G376/USDT_FinalReserves!$F376 -> 0.037718484 | Z377: 8.6789572e+10 | AA377: 8.3516001e+10
A378: 45209 | B378: 0 | C378: 59391.371 | D378: =_xlfn.XLOOKUP(A378,'BBG Data'!A:A,'BBG Data'!B:B) -> 27405.48 | E378: =C378*D378 -> 1.627649e+09 | F378: 1703814.7 | G378: =_xlfn.XLOOKUP(A378,'BBG Data'!A:A,'BBG Data'!C:C) -> 1860.4 | H378: =G378*F378 -> 3.1697769e+09 | I378: 292641978 | J378: =J377-$J$1*J377*_xlfn.XLOOKUP(A378,'BBG Data'!A:A,'BBG Data'!F:F) -> 8.203e+09 | K378: =K377-K377*L378/360*_xlfn.XLOOKUP(A378,'BBG Data'!A:A,'BBG Data'!J:J) -> 6.470577e+08 | L378: 90 | M378: =M377-M377*$M$1*_xlfn.XLOOKUP(A378,'BBG Data'!A:A,'BBG Data'!F:F) -> 8.233687e+09 | N378: =N377-N377*O378/360*_xlfn.XLOOKUP('Tether Assets'!A378,'BBG Data'!A:A,'BBG Data'!V:V) -> 5.6073261e+10 | O378: 90 | P378: =P377-P377*Q378/360*_xlfn.XLOOKUP(A378,'BBG Data'!A:A,'BBG Data'!AF:AF) -> 73465826 | Q378: 450 | R378: 5168269890 | S378: =S377-S377*T378/360*_xlfn.XLOOKUP('Tether Assets'!A378,'BBG Data'!A:A,'BBG Data'!AB:AB) -> 91776397 | T378: 150 | U378: =2257992725 -> 2257992725 | V378: =U378+S378+R378+P378+N378+M378+K378+J378+I378+H378+E378+B378 -> 8.5838578e+10 | W378: =(I378+J378)/V378 -> 0.098972305 | X378: =N378/V378 -> 0.65324079 | Y378: =USDT_FinalReserves!G377/USDT_FinalReserves!$F377 -> 0.040777469 | Z378: 8.7074755e+10 | AA378: 8.3524067e+10
A379: 45210 | B379: 0 | C379: 59391.371 | D379: =_xlfn.XLOOKUP(A379,'BBG Data'!A:A,'BBG Data'!B:B) -> 26717.11 | E379: =C379*D379 -> 1.5867658e+09 | F379: 1703814.7 | G379: =_xlfn.XLOOKUP(A379,'BBG Data'!A:A,'BBG Data'!C:C) -> 1874.36 | H379: =G379*F379 -> 3.1935621e+09 | I379: 292641978 | J379: =J378-$J$1*J378*_xlfn.XLOOKUP(A379,'BBG Data'!A:A,'BBG Data'!F:F) -> 8.203e+09 | K379: =K378-K378*L379/360*_xlfn.XLOOKUP(A379,'BBG Data'!A:A,'BBG Data'!J:J) -> 6.5223416e+08 | L379: 90 | M379: =M378-M378*$M$1*_xlfn.XLOOKUP(A379,'BBG Data'!A:A,'BBG Data'!F:F) -> 8.233687e+09 | N379: =N378-N378*O379/360*_xlfn.XLOOKUP('Tether Assets'!A379,'BBG Data'!A:A,'BBG Data'!V:V) -> 5.5905041e+10 | O379: 90 | P379: =P378-P378*Q379/360*_xlfn.XLOOKUP(A379,'BBG Data'!A:A,'BBG Data'!AF:AF) -> 72363839 | Q379: 450 | R379: 5168269890 | S379: =S378-S378*T379/360*_xlfn.XLOOKUP('Tether Assets'!A379,'BBG Data'!A:A,'BBG Data'!AB:AB) -> 90369159 | T379: 150 | U379: =2257992725 -> 2257992725 | V379: =U379+S379+R379+P379+N379+M379+K379+J379+I379+H379+E379+B379 -> 8.5655928e+10 | W379: =(I379+J379)/V379 -> 0.099183351 | X379: =N379/V379 -> 0.65266985 | Y379: =USDT_FinalReserves!G378/USDT_FinalReserves!$F378 -> 0.035353224 | Z379: 8.6543492e+10 | AA379: 8.3483901e+10
A380: 45211 | B380: 0 | C380: 59391.371 | D380: =_xlfn.XLOOKUP(A380,'BBG Data'!A:A,'BBG Data'!B:B) -> 26737.69 | E380: =C380*D380 -> 1.5879881e+09 | F380: 1703814.7 | G380: =_xlfn.XLOOKUP(A380,'BBG Data'!A:A,'BBG Data'!C:C) -> 1868.9 | H380: =G380*F380 -> 3.1842593e+09 | I380: 292641978 | J380: =J379-$J$1*J379*_xlfn.XLOOKUP(A380,'BBG Data'!A:A,'BBG Data'!F:F) -> 8.203e+09 | K380: =K379-K379*L380/360*_xlfn.XLOOKUP(A380,'BBG Data'!A:A,'BBG Data'!J:J) -> 6.5221786e+08 | L380: 90 | M380: =M379-M379*$M$1*_xlfn.XLOOKUP(A380,'BBG Data'!A:A,'BBG Data'!F:F) -> 8.233687e+09 | N380: =N379-N379*O380/360*_xlfn.XLOOKUP('Tether Assets'!A380,'BBG Data'!A:A,'BBG Data'!V:V) -> 5.5849136e+10 | O380: 90 | P380: =P379-P379*Q380/360*_xlfn.XLOOKUP(A380,'BBG Data'!A:A,'BBG Data'!AF:AF) -> 68564737 | Q380: 450 | R380: 5168269890 | S380: =S379-S379*T380/360*_xlfn.XLOOKUP('Tether Assets'!A380,'BBG Data'!A:A,'BBG Data'!AB:AB) -> 89130349 | T380: 150 | U380: =2257992725 -> 2257992725 | V380: =U380+S380+R380+P380+N380+M380+K380+J380+I380+H380+E380+B380 -> 8.5586888e+10 | W380: =(I380+J380)/V380 -> 0.099263359 | X380: =N380/V380 -> 0.65254313 | Y380: =USDT_FinalReserves!G379/USDT_FinalReserves!$F379 -> 0.036629346 | Z380: 8.6674503e+10 | AA380: 8.3499673e+10
... A459: 45290 | B459: 0 | C459: 59391.371 | D459: =_xlfn.XLOOKUP(A459,'BBG Data'!A:A,'BBG Data'!B:B) -> 42303.24 | E459: =C459*D459 -> 2.5124474e+09 | F459: 1703814.7 | G459: =_xlfn.XLOOKUP(A459,'BBG Data'!A:A,'BBG Data'!C:C) -> 2062.98 | H459: =G459*F459 -> 3.5149356e+09 | I459: 292641978 | J459: =J458-$J$1*J458*_xlfn.XLOOKUP(A459,'BBG Data'!A:A,'BBG Data'!F:F) -> 8.2014047e+09 | K459: =K458-K458*L459/360*_xlfn.XLOOKUP(A459,'BBG Data'!A:A,'BBG Data'!J:J) -> 6.6239668e+08 | L459: 90 | M459: =M458-M458*$M$1*_xlfn.XLOOKUP(A459,'BBG Data'!A:A,'BBG Data'!F:F) -> 8.230484e+09 | N459: =N458-N458*O459/360*_xlfn.XLOOKUP('Tether Assets'!A459,'BBG Data'!A:A,'BBG Data'!V:V) -> 5.8117149e+10 | O459: 90 | P459: =P458-P458*Q459/360*_xlfn.XLOOKUP(A459,'BBG Data'!A:A,'BBG Data'!AF:AF) -> 1.3714004e+08 | Q459: 450 | R459: 5168269890 | S459: =S458-S458*T459/360*_xlfn.XLOOKUP('Tether Assets'!A459,'BBG Data'!A:A,'BBG Data'!AB:AB) -> 1.0683393e+08 | T459: 150 | U459: =2257992725 -> 2257992725 | V459: =U459+S459+R459+P459+N459+M459+K459+J459+I459+H459+E459+B459 -> 8.9201696e+10 | W459: =(I459+J459)/V459 -> 0.095222929 | X459: =N459/V459 -> 0.65152516 | Y459: =USDT_FinalReserves!G458/USDT_FinalReserves!$F458 -> 0.037641625 | Z459: 9.5157202e+10 | AA459: 91575330091
A460: 45291 | B460: 0 | C460: 63852.254 | D460: =_xlfn.XLOOKUP(A460,'BBG Data'!A:A,'BBG Data'!B:B) -> 42507.9 | E460: =C460*D460 -> 2.7142252e+09 | F460: 1703814.7 | G460: =_xlfn.XLOOKUP(A460,'BBG Data'!A:A,'BBG Data'!C:C) -> 2062.98 | H460: =G460*F460 -> 3514935634 | I460: 394746540 | J460: =9359124175 -> 9359124175 | K460: 815301051 | L460: 90 | M460: 8339339590 | N460: 63086013400 | O460: 83 | P460: 69259151 | Q460: 423 | R460: 4804666695 | S460: 44412069 | T460: 137 | U460: =3772433767 -> 3772433767 | V460: =U460+S460+R460+P460+N460+M460+K460+J460+I460+H460+E460+B460 -> 9.6914457e+10 | W460: =(I460+J460)/V460 -> 0.10064412 | X460: =N460/V460 -> 0.65094533 | Y460: =USDT_FinalReserves!G459/USDT_FinalReserves!$F459 -> 0.056147347 | Z460: 9.7151575e+10 | AA460: 9.1696771e+10
A461: 45292 | B461: 0 | C461: 63852.254 | D461: =_xlfn.XLOOKUP(A461,'BBG Data'!A:A,'BBG Data'!B:B) -> 43628.4 | E461: =C461*D461 -> 2.7857717e+09 | F461: 1703814.7 | G461: =_xlfn.XLOOKUP(A461,'BBG Data'!A:A,'BBG Data'!C:C) -> 2062.98 | H461: =G461*F461 -> 3514935634 | I461: 394746540 | J461: =J460-$J$1*J460*_xlfn.XLOOKUP(A461,'BBG Data'!A:A,'BBG Data'!F:F) -> 9359124175 | K461: =K460-K460*L461/360*_xlfn.XLOOKUP(A461,'BBG Data'!A:A,'BBG Data'!J:J) -> 815301051 | L461: 90 | M461: =M460-M460*$M$1*_xlfn.XLOOKUP(A461,'BBG Data'!A:A,'BBG Data'!F:F) -> 8339339590 | N461: =N460-N460*O461/360*_xlfn.XLOOKUP('Tether Assets'!A461,'BBG Data'!A:A,'BBG Data'!V:V) -> 63086013400 | O461: 83 | P461: =P460-P460*Q461/360*_xlfn.XLOOKUP(A461,'BBG Data'!A:A,'BBG Data'!AF:AF) -> 69259151 | Q461: 423 | R461: 4804666695 | S461: =S460-S460*T461/360*_xlfn.XLOOKUP('Tether Assets'!A461,'BBG Data'!A:A,'BBG Data'!AB:AB) -> 44412069 | T461: 137 | U461: =3772433767 -> 3772433767 | V461: =U461+S461+R461+P461+N461+M461+K461+J461+I461+H461+E461+B461 -> 9.6986004e+10 | W461: =(I461+J461)/V461 -> 0.10056988 | X461: =N461/V461 -> 0.65046513 | Y461: =USDT_FinalReserves!G460/USDT_FinalReserves!$F460 -> 0.056843626 | Z461: 9.7252669e+10 | AA461: 9.1724474e+10
A462: 45293 | B462: 0 | C462: 63852.254 | D462: =_xlfn.XLOOKUP(A462,'BBG Data'!A:A,'BBG Data'!B:B) -> 45127.01 | E462: =C462*D462 -> 2.8814613e+09 | F462: 1703814.7 | G462: =_xlfn.XLOOKUP(A462,'BBG Data'!A:A,'BBG Data'!C:C) -> 2058.96 | H462: =G462*F462 -> 3.5080863e+09 | I462: 394746540 | J462: =J461-$J$1*J461*_xlfn.XLOOKUP(A462,'BBG Data'!A:A,'BBG Data'!F:F) -> 9.3586042e+09 | K462: =K461-K461*L462/360*_xlfn.XLOOKUP(A462,'BBG Data'!A:A,'BBG Data'!J:J) -> 8.1613062e+08 | L462: 90 | M462: =M461-M461*$M$1*_xlfn.XLOOKUP(A462,'BBG Data'!A:A,'BBG Data'!F:F) -> 8.338413e+09 | N462: =N461-N461*O462/360*_xlfn.XLOOKUP('Tether Assets'!A462,'BBG Data'!A:A,'BBG Data'!V:V) -> 6.2736937e+10 | O462: 83 | P462: =P461-P461*Q462/360*_xlfn.XLOOKUP(A462,'BBG Data'!A:A,'BBG Data'!AF:AF) -> 66817766 | Q462: 423 | R462: 4804666695 | S462: =S461-S461*T462/360*_xlfn.XLOOKUP('Tether Assets'!A462,'BBG Data'!A:A,'BBG Data'!AB:AB) -> 44241366 | T462: 137 | U462: =3772433767 -> 3772433767 | V462: =U462+S462+R462+P462+N462+M462+K462+J462+I462+H462+E462+B462 -> 9.6722539e+10 | W462: =(I462+J462)/V462 -> 0.10083845 | X462: =N462/V462 -> 0.6486279 | Y462: =USDT_FinalReserves!G461/USDT_FinalReserves!$F461 -> 0.053576365 | Z462: 9.6923026e+10 | AA462: 9.1730242e+10
A463: 45294 | B463: 0 | C463: 63852.254 | D463: =_xlfn.XLOOKUP(A463,'BBG Data'!A:A,'BBG Data'!B:B) -> 42938.06 | E463: =C463*D463 -> 2.7416919e+09 | F463: 1703814.7 | G463: =_xlfn.XLOOKUP(A463,'BBG Data'!A:A,'BBG Data'!C:C) -> 2041.49 | H463: =G463*F463 -> 3.4783207e+09 | I463: 394746540 | J463: =J462-$J$1*J462*_xlfn.XLOOKUP(A463,'BBG Data'!A:A,'BBG Data'!F:F) -> 9.3588642e+09 | K463: =K462-K462*L463/360*_xlfn.XLOOKUP(A463,'BBG Data'!A:A,'BBG Data'!J:J) -> 8.1554913e+08 | L463: 90 | M463: =M462-M462*$M$1*_xlfn.XLOOKUP(A463,'BBG Data'!A:A,'BBG Data'!F:F) -> 8.3388762e+09 | N463: =N462-N462*O463/360*_xlfn.XLOOKUP('Tether Assets'!A463,'BBG Data'!A:A,'BBG Data'!V:V) -> 6.2389793e+10 | O463: 83 | P463: =P462-P462*Q463/360*_xlfn.XLOOKUP(A463,'BBG Data'!A:A,'BBG Data'!AF:AF) -> 66032657 | Q463: 423 | R463: 4804666695 | S463: =S462-S462*T463/360*_xlfn.XLOOKUP('Tether Assets'!A463,'BBG Data'!A:A,'BBG Data'!AB:AB) -> 43483733 | T463: 137 | U463: =3772433767 -> 3772433767 | V463: =U463+S463+R463+P463+N463+M463+K463+J463+I463+H463+E463+B463 -> 9.6204459e+10 | W463: =(I463+J463)/V463 -> 0.10138419 | X463: =N463/V463 -> 0.64851249 | Y463: =USDT_FinalReserves!G462/USDT_FinalReserves!$F462 -> 0.05106451 | Z463: 9.6653336e+10 | AA463: 9.1717781e+10
A464: 45295 | B464: 0 | C464: 63852.254 | D464: =_xlfn.XLOOKUP(A464,'BBG Data'!A:A,'BBG Data'!B:B) -> 44488.33 | E464: =C464*D464 -> 2.8406801e+09 | F464: 1703814.7 | G464: =_xlfn.XLOOKUP(A464,'BBG Data'!A:A,'BBG Data'!C:C) -> 2043.65 | H464: =G464*F464 -> 3.4820009e+09 | I464: 394746540 | J464: =J463-$J$1*J463*_xlfn.XLOOKUP(A464,'BBG Data'!A:A,'BBG Data'!F:F) -> 9.360684e+09 | K464: =K463-K463*L464/360*_xlfn.XLOOKUP(A464,'BBG Data'!A:A,'BBG Data'!J:J) -> 8.1572651e+08 | L464: 90 | M464: =M463-M463*$M$1*_xlfn.XLOOKUP(A464,'BBG Data'!A:A,'BBG Data'!F:F) -> 8.3421191e+09 | N464: =N463-N463*O464/360*_xlfn.XLOOKUP('Tether Assets'!A464,'BBG Data'!A:A,'BBG Data'!V:V) -> 6.2389793e+10 | O464: 83 | P464: =P463-P463*Q464/360*_xlfn.XLOOKUP(A464,'BBG Data'!A:A,'BBG Data'!AF:AF) -> 63317064 | Q464: 423 | R464: 4804666695 | S464: =S463-S463*T464/360*_xlfn.XLOOKUP('Tether Assets'!A464,'BBG Data'!A:A,'BBG Data'!AB:AB) -> 42886351 | T464: 137 | U464: =3772433767 -> 3772433767 | V464: =U464+S464+R464+P464+N464+M464+K464+J464+I464+H464+E464+B464 -> 9.6309054e+10 | W464: =(I464+J464)/V464 -> 0.10129297 | X464: =N464/V464 -> 0.64780818 | Y464: =USDT_FinalReserves!G463/USDT_FinalReserves!$F463 -> 0.057172409 | Z464: 9.7730226e+10 | AA464: 9.2142753e+10
A465: 45296 | B465: 0 | C465: 63852.254 | D465: =_xlfn.XLOOKUP(A465,'BBG Data'!A:A,'BBG Data'!B:B) -> 43970.52 | E465: =C465*D465 -> 2.8076168e+09 | F465: 1703814.7 | G465: =_xlfn.XLOOKUP(A465,'BBG Data'!A:A,'BBG Data'!C:C) -> 2045.45 | H465: =G465*F465 -> 3.4850678e+09 | I465: 394746540 | J465: =J464-$J$1*J464*_xlfn.XLOOKUP(A465,'BBG Data'!A:A,'BBG Data'!F:F) -> 9.360944e+09 | K465: =K464-K464*L465/360*_xlfn.XLOOKUP(A465,'BBG Data'!A:A,'BBG Data'!J:J) -> 8.1573671e+08 | L465: 90 | M465: =M464-M464*$M$1*_xlfn.XLOOKUP(A465,'BBG Data'!A:A,'BBG Data'!F:F) -> 8.3425826e+09 | N465: =N464-N464*O465/360*_xlfn.XLOOKUP('Tether Assets'!A465,'BBG Data'!A:A,'BBG Data'!V:V) -> 6.2576789e+10 | O465: 83 | P465: =P464-P464*Q465/360*_xlfn.XLOOKUP(A465,'BBG Data'!A:A,'BBG Data'!AF:AF) -> 63614654 | Q465: 423 | R465: 4804666695 | S465: =S464-S464*T465/360*_xlfn.XLOOKUP('Tether Assets'!A465,'BBG Data'!A:A,'BBG Data'!AB:AB) -> 43204603 | T465: 137 | U465: =3772433767 -> 3772433767 | V465: =U465+S465+R465+P465+N465+M465+K465+J465+I465+H465+E465+B465 -> 9.6467403e+10 | W465: =(I465+J465)/V465 -> 0.1011294 | X465: =N465/V465 -> 0.64868326 | Y465: =USDT_FinalReserves!G464/USDT_FinalReserves!$F464 -> 0.05769666 | Z465: 9.819217e+10 | AA465: 9.2526809e+10
A466: 45297 | B466: 0 | C466: 63852.254 | D466: =_xlfn.XLOOKUP(A466,'BBG Data'!A:A,'BBG Data'!B:B) -> 43921.45 | E466: =C466*D466 -> 2.8044836e+09 | F466: 1703814.7 | G466: =_xlfn.XLOOKUP(A466,'BBG Data'!A:A,'BBG Data'!C:C) -> 2045.45 | H466: =G466*F466 -> 3.4850678e+09 | I466: 394746540 | J466: =J465-$J$1*J465*_xlfn.XLOOKUP(A466,'BBG Data'!A:A,'BBG Data'!F:F) -> 9.360944e+09 | K466: =K465-K465*L466/360*_xlfn.XLOOKUP(A466,'BBG Data'!A:A,'BBG Data'!J:J) -> 8.1573671e+08 | L466: 90 | M466: =M465-M465*$M$1*_xlfn.XLOOKUP(A466,'BBG Data'!A:A,'BBG Data'!F:F) -> 8.3425826e+09 | N466: =N465-N465*O466/360*_xlfn.XLOOKUP('Tether Assets'!A466,'BBG Data'!A:A,'BBG Data'!V:V) -> 6.2576789e+10 | O466: 83 | P466: =P465-P465*Q466/360*_xlfn.XLOOKUP(A466,'BBG Data'!A:A,'BBG Data'!AF:AF) -> 63614654 | Q466: 423 | R466: 4804666695 | S466: =S465-S465*T466/360*_xlfn.XLOOKUP('Tether Assets'!A466,'BBG Data'!A:A,'BBG Data'!AB:AB) -> 43204603 | T466: 137 | U466: =3772433767 -> 3772433767 | V466: =U466+S466+R466+P466+N466+M466+K466+J466+I466+H466+E466+B466 -> 9.646427e+10 | W466: =(I466+J466)/V466 -> 0.10113268 | X466: =N466/V466 -> 0.64870432 | Y466: =USDT_FinalReserves!G465/USDT_FinalReserves!$F465 -> 0.05611669 | Z466: 9.8379535e+10 | AA466: 9.2858801e+10
A467: 45298 | B467: 0 | C467: 63852.254 | D467: =_xlfn.XLOOKUP(A467,'BBG Data'!A:A,'BBG Data'!B:B) -> 44258.51 | E467: =C467*D467 -> 2.8260056e+09 | F467: 1703814.7 | G467: =_xlfn.XLOOKUP(A467,'BBG Data'!A:A,'BBG Data'!C:C) -> 2045.45 | H467: =G467*F467 -> 3.4850678e+09 | I467: 394746540 | J467: =J466-$J$1*J466*_xlfn.XLOOKUP(A467,'BBG Data'!A:A,'BBG Data'!F:F) -> 9.360944e+09 | K467: =K466-K466*L467/360*_xlfn.XLOOKUP(A467,'BBG Data'!A:A,'BBG Data'!J:J) -> 8.1573671e+08 | L467: 90 | M467: =M466-M466*$M$1*_xlfn.XLOOKUP(A467,'BBG Data'!A:A,'BBG Data'!F:F) -> 8.3425826e+09 | N467: =N466-N466*O467/360*_xlfn.XLOOKUP('Tether Assets'!A467,'BBG Data'!A:A,'BBG Data'!V:V) -> 6.2576789e+10 | O467: 83 | P467: =P466-P466*Q467/360*_xlfn.XLOOKUP(A467,'BBG Data'!A:A,'BBG Data'!AF:AF) -> 63614654 | Q467: 423 | R467: 4804666695 | S467: =S466-S466*T467/360*_xlfn.XLOOKUP('Tether Assets'!A467,'BBG Data'!A:A,'BBG Data'!AB:AB) -> 43204603 | T467: 137 | U467: =3772433767 -> 3772433767 | V467: =U467+S467+R467+P467+N467+M467+K467+J467+I467+H467+E467+B467 -> 9.6485792e+10 | W467: =(I467+J467)/V467 -> 0.10111013 | X467: =N467/V467 -> 0.64855963 | Y467: =USDT_FinalReserves!G466/USDT_FinalReserves!$F466 -> 0.056357882 | Z467: 9.9026343e+10 | AA467: 9.3445428e+10
A468: 45299 | B468: 0 | C468: 63852.254 | D468: =_xlfn.XLOOKUP(A468,'BBG Data'!A:A,'BBG Data'!B:B) -> 47114.68 | E468: =C468*D468 -> 3.0083785e+09 | F468: 1703814.7 | G468: =_xlfn.XLOOKUP(A468,'BBG Data'!A:A,'BBG Data'!C:C) -> 2028.07 | H468: =G468*F468 -> 3.4554555e+09 | I468: 394746540 | J468: =J467-$J$1*J467*_xlfn.XLOOKUP(A468,'BBG Data'!A:A,'BBG Data'!F:F) -> 9.360944e+09 | K468: =K467-K467*L468/360*_xlfn.XLOOKUP(A468,'BBG Data'!A:A,'BBG Data'!J:J) -> 8.1645455e+08 | L468: 90 | M468: =M467-M467*$M$1*_xlfn.XLOOKUP(A468,'BBG Data'!A:A,'BBG Data'!F:F) -> 8.3425826e+09 | N468: =N467-N467*O468/360*_xlfn.XLOOKUP('Tether Assets'!A468,'BBG Data'!A:A,'BBG Data'!V:V) -> 6.246137e+10 | O468: 83 | P468: =P467-P467*Q468/360*_xlfn.XLOOKUP(A468,'BBG Data'!A:A,'BBG Data'!AF:AF) -> 63838896 | Q468: 423 | R468: 4804666695 | S468: =S467-S467*T468/360*_xlfn.XLOOKUP('Tether Assets'!A468,'BBG Data'!A:A,'BBG Data'!AB:AB) -> 43732384 | T468: 137 | U468: =3772433767 -> 3772433767 | V468: =U468+S468+R468+P468+N468+M468+K468+J468+I468+H468+E468+B468 -> 9.6524603e+10 | W468: =(I468+J468)/V468 -> 0.10106947 | X468: =N468/V468 -> 0.6471031 | Y468: =USDT_FinalReserves!G467/USDT_FinalReserves!$F467 -> 0.056526856 | Z468: 9.9319152e+10 | AA468: 9.3704953e+10
A469: 45300 | B469: 0 | C469: 63852.254 | D469: =_xlfn.XLOOKUP(A469,'BBG Data'!A:A,'BBG Data'!B:B) -> 45427.01 | E469: =C469*D469 -> 2.900617e+09 | F469: 1703814.7 | G469: =_xlfn.XLOOKUP(A469,'BBG Data'!A:A,'BBG Data'!C:C) -> 2030.2 | H469: =G469*F469 -> 3.4590846e+09 | I469: 394746540 | J469: =J468-$J$1*J468*_xlfn.XLOOKUP(A469,'BBG Data'!A:A,'BBG Data'!F:F) -> 9.360944e+09 | K469: =K468-K468*L469/360*_xlfn.XLOOKUP(A469,'BBG Data'!A:A,'BBG Data'!J:J) -> 8.1692401e+08 | L469: 90 | M469: =M468-M468*$M$1*_xlfn.XLOOKUP(A469,'BBG Data'!A:A,'BBG Data'!F:F) -> 8.3425826e+09 | N469: =N468-N468*O469/360*_xlfn.XLOOKUP('Tether Assets'!A469,'BBG Data'!A:A,'BBG Data'!V:V) -> 6.2518973e+10 | O469: 83 | P469: =P468-P468*Q469/360*_xlfn.XLOOKUP(A469,'BBG Data'!A:A,'BBG Data'!AF:AF) -> 64739024 | Q469: 423 | R469: 4804666695 | S469: =S468-S468*T469/360*_xlfn.XLOOKUP('Tether Assets'!A469,'BBG Data'!A:A,'BBG Data'!AB:AB) -> 44309882 | T469: 137 | U469: =3772433767 -> 3772433767 | V469: =U469+S469+R469+P469+N469+M469+K469+J469+I469+H469+E469+B469 -> 9.6480021e+10 | W469: =(I469+J469)/V469 -> 0.10111617 | X469: =N469/V469 -> 0.64799916 | Y469: =USDT_FinalReserves!G468/USDT_FinalReserves!$F468 -> 0.055711206 | Z469: 9.963447e+10 | AA469: 9.4083713e+10
A470: 45301 | B470: 0 | C470: 63852.254 | D470: =_xlfn.XLOOKUP(A470,'BBG Data'!A:A,'BBG Data'!B:B) -> 45945.61 | E470: =C470*D470 -> 2.9337307e+09 | F470: 1703814.7 | G470: =_xlfn.XLOOKUP(A470,'BBG Data'!A:A,'BBG Data'!C:C) -> 2024.41 | H470: =G470*F470 -> 3.4492195e+09 | I470: 394746540 | J470: =J469-$J$1*J469*_xlfn.XLOOKUP(A470,'BBG Data'!A:A,'BBG Data'!F:F) -> 9.360944e+09 | K470: =K469-K469*L470/360*_xlfn.XLOOKUP(A470,'BBG Data'!A:A,'BBG Data'!J:J) -> 8.1630724e+08 | L470: 90 | M470: =M469-M469*$M$1*_xlfn.XLOOKUP(A470,'BBG Data'!A:A,'BBG Data'!F:F) -> 8.3425826e+09 | N470: =N469-N469*O470/360*_xlfn.XLOOKUP('Tether Assets'!A470,'BBG Data'!A:A,'BBG Data'!V:V) -> 6.2518973e+10 | O470: 83 | P470: =P469-P469*Q470/360*_xlfn.XLOOKUP(A470,'BBG Data'!A:A,'BBG Data'!AF:AF) -> 65043298 | Q470: 423 | R470: 4804666695 | S470: =S469-S469*T470/360*_xlfn.XLOOKUP('Tether Assets'!A470,'BBG Data'!A:A,'BBG Data'!AB:AB) -> 43814128 | T470: 137 | U470: =3772433767 -> 3772433767 | V470: =U470+S470+R470+P470+N470+M470+K470+J470+I470+H470+E470+B470 -> 9.6502461e+10 | W470: =(I470+J470)/V470 -> 0.10109266 | X470: =N470/V470 -> 0.64784848 | Y470: =USDT_FinalReserves!G469/USDT_FinalReserves!$F469 -> 0.056366828 | Z470: 9.9683022e+10 | AA470: 9.4064206e+10
A471: 45302 | B471: 0 | C471: 63852.254 | D471: =_xlfn.XLOOKUP(A471,'BBG Data'!A:A,'BBG Data'!B:B) -> 46163.13 | E471: =C471*D471 -> 2.9476199e+09 | F471: 1703814.7 | G471: =_xlfn.XLOOKUP(A471,'BBG Data'!A:A,'BBG Data'!C:C) -> 2028.91 | H471: =G471*F471 -> 3.4568867e+09 | I471: 394746540 | J471: =J470-$J$1*J470*_xlfn.XLOOKUP(A471,'BBG Data'!A:A,'BBG Data'!F:F) -> 9.360944e+09 | K471: =K470-K470*L471/360*_xlfn.XLOOKUP(A471,'BBG Data'!A:A,'BBG Data'!J:J) -> 8.1885208e+08 | L471: 90 | M471: =M470-M470*$M$1*_xlfn.XLOOKUP(A471,'BBG Data'!A:A,'BBG Data'!F:F) -> 8.3425826e+09 | N471: =N470-N470*O471/360*_xlfn.XLOOKUP('Tether Assets'!A471,'BBG Data'!A:A,'BBG Data'!V:V) -> 6.2605458e+10 | O471: 83 | P471: =P470-P470*Q471/360*_xlfn.XLOOKUP(A471,'BBG Data'!A:A,'BBG Data'!AF:AF) -> 71004516 | Q471: 423 | R471: 4804666695 | S471: =S470-S470*T471/360*_xlfn.XLOOKUP('Tether Assets'!A471,'BBG Data'!A:A,'BBG Data'!AB:AB) -> 45298088 | T471: 137 | U471: =3772433767 -> 3772433767 | V471: =U471+S471+R471+P471+N471+M471+K471+J471+I471+H471+E471+B471 -> 9.6620492e+10 | W471: =(I471+J471)/V471 -> 0.10096917 | X471: =N471/V471 -> 0.64795217 | Y471: =USDT_FinalReserves!G470/USDT_FinalReserves!$F470 -> 0.057300351 | Z471: 1.0024907e+11 | AA471: 9.4504766e+10
A472: 45303 | B472: 0 | C472: 63852.254 | D472: =_xlfn.XLOOKUP(A472,'BBG Data'!A:A,'BBG Data'!B:B) -> 43426.6 | E472: =C472*D472 -> 2.7728863e+09 | F472: 1703814.7 | G472: =_xlfn.XLOOKUP(A472,'BBG Data'!A:A,'BBG Data'!C:C) -> 2049.06 | H472: =G472*F472 -> 3.4912185e+09 | I472: 394746540 | J472: =J471-$J$1*J471*_xlfn.XLOOKUP(A472,'BBG Data'!A:A,'BBG Data'!F:F) -> 9.360944e+09 | K472: =K471-K471*L472/360*_xlfn.XLOOKUP(A472,'BBG Data'!A:A,'BBG Data'!J:J) -> 8.183321e+08 | L472: 90 | M472: =M471-M471*$M$1*_xlfn.XLOOKUP(A472,'BBG Data'!A:A,'BBG Data'!F:F) -> 8.3425826e+09 | N472: =N471-N471*O472/360*_xlfn.XLOOKUP('Tether Assets'!A472,'BBG Data'!A:A,'BBG Data'!V:V) -> 6.2764232e+10 | O472: 83 | P472: =P471-P471*Q472/360*_xlfn.XLOOKUP(A472,'BBG Data'!A:A,'BBG Data'!AF:AF) -> 77428650 | Q472: 423 | R472: 4804666695 | S472: =S471-S471*T472/360*_xlfn.XLOOKUP('Tether Assets'!A472,'BBG Data'!A:A,'BBG Data'!AB:AB) -> 45458406 | T472: 137 | U472: =3772433767 -> 3772433767 | V472: =U472+S472+R472+P472+N472+M472+K472+J472+I472+H472+E472+B472 -> 9.664493e+10 | W472: =(I472+J472)/V472 -> 0.10094364 | X472: =N472/V472 -> 0.64943119 | Y472: =USDT_FinalReserves!G471/USDT_FinalReserves!$F471 -> 0.056386005 | Z472: 1.0074312e+11 | AA472: 9.506262e+10
... A550: 45381 | B550: 0 | C550: 63852.254 | D550: =_xlfn.XLOOKUP(A550,'BBG Data'!A:A,'BBG Data'!B:B) -> 69857.12 | E550: =C550*D550 -> 4.4605345e+09 | F550: 1703814.7 | G550: =_xlfn.XLOOKUP(A550,'BBG Data'!A:A,'BBG Data'!C:C) -> 2229.87 | H550: =G550*F550 -> 3.7992853e+09 | I550: 394746540 | J550: =J549-$J$1*J549*_xlfn.XLOOKUP(A550,'BBG Data'!A:A,'BBG Data'!F:F) -> 9.3601639e+09 | K550: =K549-K549*L550/360*_xlfn.XLOOKUP(A550,'BBG Data'!A:A,'BBG Data'!J:J) -> 8.2195197e+08 | L550: 90 | M550: =M549-M549*$M$1*_xlfn.XLOOKUP(A550,'BBG Data'!A:A,'BBG Data'!F:F) -> 8.3411921e+09 | N550: =N549-N549*O550/360*_xlfn.XLOOKUP('Tether Assets'!A550,'BBG Data'!A:A,'BBG Data'!V:V) -> 6.2682982e+10 | O550: 83 | P550: =P549-P549*Q550/360*_xlfn.XLOOKUP(A550,'BBG Data'!A:A,'BBG Data'!AF:AF) -> 47110405 | Q550: 423 | R550: 4804666695 | S550: =S549-S549*T550/360*_xlfn.XLOOKUP('Tether Assets'!A550,'BBG Data'!A:A,'BBG Data'!AB:AB) -> 41931837 | T550: 137 | U550: =3772433767 -> 3772433767 | V550: =U550+S550+R550+P550+N550+M550+K550+J550+I550+H550+E550+B550 -> 9.8526999e+10 | W550: =(I550+J550)/V550 -> 0.099007485 | X550: =N550/V550 -> 0.63620107 | Y550: =USDT_FinalReserves!G549/USDT_FinalReserves!$F549 -> 0.056271494 | Z550: 1.1078724e+11 | AA550: 1.0455308e+11
A551: 45382 | B551: 0 | C551: 75354.386 | D551: =_xlfn.XLOOKUP(A551,'BBG Data'!A:A,'BBG Data'!B:B) -> 70845.76 | E551: =C551*D551 -> 5.3385387e+09 | F551: 1637135.8 | G551: =_xlfn.XLOOKUP(A551,'BBG Data'!A:A,'BBG Data'!C:C) -> 2229.87 | H551: =G551*F551 -> 3650599989 | I551: 100264024 | J551: =11311946813 -> 11311946813 | K551: 838514084 | L551: 90 | M551: 6279586483 | N551: 74045290303 | O551: 90 | P551: 122452086 | Q551: 250 | R551: 4735309369 | S551: 25111317 | T551: 150 | U551: =3805605037 -> 3805605037 | V551: =U551+S551+R551+P551+N551+M551+K551+J551+I551+H551+E551+B551 -> 1.1025322e+11 | W551: =(I551+J551)/V551 -> 0.10350909 | X551: =N551/V551 -> 0.67159301 | Y551: =USDT_FinalReserves!G550/USDT_FinalReserves!$F550 -> 0.056851577 | Z551: 1.1083977e+11 | AA551: 1.0453835e+11
A552: 45383 | B552: 0 | C552: 75354.386 | D552: =_xlfn.XLOOKUP(A552,'BBG Data'!A:A,'BBG Data'!B:B) -> 69767.89 | E552: =C552*D552 -> 5.2573165e+09 | F552: 1637135.8 | G552: =_xlfn.XLOOKUP(A552,'BBG Data'!A:A,'BBG Data'!C:C) -> 2251.44 | H552: =G552*F552 -> 3.685913e+09 | I552: 100264024 | J552: =J551-$J$1*J551*_xlfn.XLOOKUP(A552,'BBG Data'!A:A,'BBG Data'!F:F) -> 1.1311633e+10 | K552: =K551-K551*L552/360*_xlfn.XLOOKUP(A552,'BBG Data'!A:A,'BBG Data'!J:J) -> 8.3770073e+08 | L552: 90 | M552: =M551-M551*$M$1*_xlfn.XLOOKUP(A552,'BBG Data'!A:A,'BBG Data'!F:F) -> 6.2792376e+09 | N552: =N551-N551*O552/360*_xlfn.XLOOKUP('Tether Assets'!A552,'BBG Data'!A:A,'BBG Data'!V:V) -> 7.3971245e+10 | O552: 90 | P552: =P551-P551*Q552/360*_xlfn.XLOOKUP(A552,'BBG Data'!A:A,'BBG Data'!AI:AI) -> 1.2058129e+08 | Q552: 250 | R552: 4735309369 | S552: =S551-S551*T552/360*_xlfn.XLOOKUP('Tether Assets'!A552,'BBG Data'!A:A,'BBG Data'!AB:AB) -> 24761851 | T552: 150 | U552: =3805605037 -> 3805605037 | V552: =U552+S552+R552+P552+N552+M552+K552+J552+I552+H552+E552+B552 -> 1.1012957e+11 | W552: =(I552+J552)/V552 -> 0.10362246 | X552: =N552/V552 -> 0.67167471 | Y552: =USDT_FinalReserves!G551/USDT_FinalReserves!$F551 -> 0.055792629 | Z552: 1.106858e+11 | AA552: 1.0451035e+11
A553: 45384 | B553: 0 | C553: 75354.386 | D553: =_xlfn.XLOOKUP(A553,'BBG Data'!A:A,'BBG Data'!B:B) -> 65702.14 | E553: =C553*D553 -> 4.9509444e+09 | F553: 1637135.8 | G553: =_xlfn.XLOOKUP(A553,'BBG Data'!A:A,'BBG Data'!C:C) -> 2280.67 | H553: =G553*F553 -> 3.7337665e+09 | I553: 100264024 | J553: =J552-$J$1*J552*_xlfn.XLOOKUP(A553,'BBG Data'!A:A,'BBG Data'!F:F) -> 1.1311947e+10 | K553: =K552-K552*L553/360*_xlfn.XLOOKUP(A553,'BBG Data'!A:A,'BBG Data'!J:J) -> 8.3644208e+08 | L553: 90 | M553: =M552-M552*$M$1*_xlfn.XLOOKUP(A553,'BBG Data'!A:A,'BBG Data'!F:F) -> 6.2795865e+09 | N553: =N552-N552*O553/360*_xlfn.XLOOKUP('Tether Assets'!A553,'BBG Data'!A:A,'BBG Data'!V:V) -> 7.4156173e+10 | O553: 90 | P553: =P552-P552*Q553/360*_xlfn.XLOOKUP(A553,'BBG Data'!A:A,'BBG Data'!AI:AI) -> 1.2275845e+08 | Q553: 250 | R553: 4735309369 | S553: =S552-S552*T553/360*_xlfn.XLOOKUP('Tether Assets'!A553,'BBG Data'!A:A,'BBG Data'!AB:AB) -> 25161136 | T553: 150 | U553: =3805605037 -> 3805605037 | V553: =U553+S553+R553+P553+N553+M553+K553+J553+I553+H553+E553+B553 -> 1.1005796e+11 | W553: =(I553+J553)/V553 -> 0.10369274 | X553: =N553/V553 -> 0.67379202 | Y553: =USDT_FinalReserves!G552/USDT_FinalReserves!$F552 -> 0.056237914 | Z553: 1.1069132e+11 | AA553: 1.0446627e+11
A554: 45385 | B554: 0 | C554: 75354.386 | D554: =_xlfn.XLOOKUP(A554,'BBG Data'!A:A,'BBG Data'!B:B) -> 65742.2 | E554: =C554*D554 -> 4.9539631e+09 | F554: 1637135.8 | G554: =_xlfn.XLOOKUP(A554,'BBG Data'!A:A,'BBG Data'!C:C) -> 2300 | H554: =G554*F554 -> 3.7654123e+09 | I554: 100264024 | J554: =J553-$J$1*J553*_xlfn.XLOOKUP(A554,'BBG Data'!A:A,'BBG Data'!F:F) -> 1.1312575e+10 | K554: =K553-K553*L554/360*_xlfn.XLOOKUP(A554,'BBG Data'!A:A,'BBG Data'!J:J) -> 8.3681639e+08 | L554: 90 | M554: =M553-M553*$M$1*_xlfn.XLOOKUP(A554,'BBG Data'!A:A,'BBG Data'!F:F) -> 6.2802842e+09 | N554: =N553-N553*O554/360*_xlfn.XLOOKUP('Tether Assets'!A554,'BBG Data'!A:A,'BBG Data'!V:V) -> 7.4137634e+10 | O554: 90 | P554: =P553-P553*Q554/360*_xlfn.XLOOKUP(A554,'BBG Data'!A:A,'BBG Data'!AI:AI) -> 1.2182071e+08 | Q554: 250 | R554: 4735309369 | S554: =S553-S553*T554/360*_xlfn.XLOOKUP('Tether Assets'!A554,'BBG Data'!A:A,'BBG Data'!AB:AB) -> 24932589 | T554: 150 | U554: =3805605037 -> 3805605037 | V554: =U554+S554+R554+P554+N554+M554+K554+J554+I554+H554+E554+B554 -> 1.1007462e+11 | W554: =(I554+J554)/V554 -> 0.10368275 | X554: =N554/V554 -> 0.67352162 | Y554: =USDT_FinalReserves!G553/USDT_FinalReserves!$F553 -> 0.056994322 | Z554: 1.109918e+11 | AA554: 1.046659e+11
A555: 45386 | B555: 0 | C555: 75354.386 | D555: =_xlfn.XLOOKUP(A555,'BBG Data'!A:A,'BBG Data'!B:B) -> 67948.37 | E555: =C555*D555 -> 5.1202077e+09 | F555: 1637135.8 | G555: =_xlfn.XLOOKUP(A555,'BBG Data'!A:A,'BBG Data'!C:C) -> 2290.94 | H555: =G555*F555 -> 3.7505799e+09 | I555: 100264024 | J555: =J554-$J$1*J554*_xlfn.XLOOKUP(A555,'BBG Data'!A:A,'BBG Data'!F:F) -> 1.1312575e+10 | K555: =K554-K554*L555/360*_xlfn.XLOOKUP(A555,'BBG Data'!A:A,'BBG Data'!J:J) -> 8.3775571e+08 | L555: 90 | M555: =M554-M554*$M$1*_xlfn.XLOOKUP(A555,'BBG Data'!A:A,'BBG Data'!F:F) -> 6.2802842e+09 | N555: =N554-N554*O555/360*_xlfn.XLOOKUP('Tether Assets'!A555,'BBG Data'!A:A,'BBG Data'!V:V) -> 7.4230306e+10 | O555: 90 | P555: =P554-P554*Q555/360*_xlfn.XLOOKUP(A555,'BBG Data'!A:A,'BBG Data'!AI:AI) -> 1.2435865e+08 | Q555: 250 | R555: 4735309369 | S555: =S554-S554*T555/360*_xlfn.XLOOKUP('Tether Assets'!A555,'BBG Data'!A:A,'BBG Data'!AB:AB) -> 25275412 | T555: 150 | U555: =3805605037 -> 3805605037 | V555: =U555+S555+R555+P555+N555+M555+K555+J555+I555+H555+E555+B555 -> 1.1032252e+11 | W555: =(I555+J555)/V555 -> 0.10344977 | X555: =N555/V555 -> 0.67284817 | Y555: =USDT_FinalReserves!G554/USDT_FinalReserves!$F554 -> 0.058970913 | Z555: 1.1193273e+11 | AA555: 1.0533196e+11
A556: 45387 | B556: 0 | C556: 75354.386 | D556: =_xlfn.XLOOKUP(A556,'BBG Data'!A:A,'BBG Data'!B:B) -> 67660.41 | E556: =C556*D556 -> 5.0985086e+09 | F556: 1637135.8 | G556: =_xlfn.XLOOKUP(A556,'BBG Data'!A:A,'BBG Data'!C:C) -> 2329.75 | H556: =G556*F556 -> 3.8141171e+09 | I556: 100264024 | J556: =J555-$J$1*J555*_xlfn.XLOOKUP(A556,'BBG Data'!A:A,'BBG Data'!F:F) -> 1.1312575e+10 | K556: =K555-K555*L556/360*_xlfn.XLOOKUP(A556,'BBG Data'!A:A,'BBG Data'!J:J) -> 8.3952547e+08 | L556: 90 | M556: =M555-M555*$M$1*_xlfn.XLOOKUP(A556,'BBG Data'!A:A,'BBG Data'!F:F) -> 6.2802842e+09 | N556: =N555-N555*O556/360*_xlfn.XLOOKUP('Tether Assets'!A556,'BBG Data'!A:A,'BBG Data'!V:V) -> 7.4007615e+10 | O556: 90 | P556: =P555-P555*Q556/360*_xlfn.XLOOKUP(A556,'BBG Data'!A:A,'BBG Data'!AI:AI) -> 1.2029972e+08 | Q556: 250 | R556: 4735309369 | S556: =S555-S555*T556/360*_xlfn.XLOOKUP('Tether Assets'!A556,'BBG Data'!A:A,'BBG Data'!AB:AB) -> 24980532 | T556: 150 | U556: =3805605037 -> 3805605037 | V556: =U556+S556+R556+P556+N556+M556+K556+J556+I556+H556+E556+B556 -> 1.1013908e+11 | W556: =(I556+J556)/V556 -> 0.10362206 | X556: =N556/V556 -> 0.67194689 | Y556: =USDT_FinalReserves!G555/USDT_FinalReserves!$F555 -> 0.055280762 | Z556: 1.124492e+11 | AA556: 1.0623293e+11
A557: 45388 | B557: 0 | C557: 75354.386 | D557: =_xlfn.XLOOKUP(A557,'BBG Data'!A:A,'BBG Data'!B:B) -> 68409.01 | E557: =C557*D557 -> 5.1549189e+09 | F557: 1637135.8 | G557: =_xlfn.XLOOKUP(A557,'BBG Data'!A:A,'BBG Data'!C:C) -> 2329.75 | H557: =G557*F557 -> 3.8141171e+09 | I557: 100264024 | J557: =J556-$J$1*J556*_xlfn.XLOOKUP(A557,'BBG Data'!A:A,'BBG Data'!F:F) -> 1.1312575e+10 | K557: =K556-K556*L557/360*_xlfn.XLOOKUP(A557,'BBG Data'!A:A,'BBG Data'!J:J) -> 8.3952547e+08 | L557: 90 | M557: =M556-M556*$M$1*_xlfn.XLOOKUP(A557,'BBG Data'!A:A,'BBG Data'!F:F) -> 6.2802842e+09 | N557: =N556-N556*O557/360*_xlfn.XLOOKUP('Tether Assets'!A557,'BBG Data'!A:A,'BBG Data'!V:V) -> 7.4007615e+10 | O557: 90 | P557: =P556-P556*Q557/360*_xlfn.XLOOKUP(A557,'BBG Data'!A:A,'BBG Data'!AI:AI) -> 1.2029972e+08 | Q557: 250 | R557: 4735309369 | S557: =S556-S556*T557/360*_xlfn.XLOOKUP('Tether Assets'!A557,'BBG Data'!A:A,'BBG Data'!AB:AB) -> 24980532 | T557: 150 | U557: =3805605037 -> 3805605037 | V557: =U557+S557+R557+P557+N557+M557+K557+J557+I557+H557+E557+B557 -> 1.1019549e+11 | W557: =(I557+J557)/V557 -> 0.10356902 | X557: =N557/V557 -> 0.67160291 | Y557: =USDT_FinalReserves!G556/USDT_FinalReserves!$F556 -> 0.057334385 | Z557: 1.1317795e+11 | AA557: 1.0668897e+11
A558: 45389 | B558: 0 | C558: 75354.386 | D558: =_xlfn.XLOOKUP(A558,'BBG Data'!A:A,'BBG Data'!B:B) -> 69318.14 | E558: =C558*D558 -> 5.2234258e+09 | F558: 1637135.8 | G558: =_xlfn.XLOOKUP(A558,'BBG Data'!A:A,'BBG Data'!C:C) -> 2329.75 | H558: =G558*F558 -> 3.8141171e+09 | I558: 100264024 | J558: =J557-$J$1*J557*_xlfn.XLOOKUP(A558,'BBG Data'!A:A,'BBG Data'!F:F) -> 1.1312575e+10 | K558: =K557-K557*L558/360*_xlfn.XLOOKUP(A558,'BBG Data'!A:A,'BBG Data'!J:J) -> 8.3952547e+08 | L558: 90 | M558: =M557-M557*$M$1*_xlfn.XLOOKUP(A558,'BBG Data'!A:A,'BBG Data'!F:F) -> 6.2802842e+09 | N558: =N557-N557*O558/360*_xlfn.XLOOKUP('Tether Assets'!A558,'BBG Data'!A:A,'BBG Data'!V:V) -> 7.4007615e+10 | O558: 90 | P558: =P557-P557*Q558/360*_xlfn.XLOOKUP(A558,'BBG Data'!A:A,'BBG Data'!AI:AI) -> 1.2029972e+08 | Q558: 250 | R558: 4735309369 | S558: =S557-S557*T558/360*_xlfn.XLOOKUP('Tether Assets'!A558,'BBG Data'!A:A,'BBG Data'!AB:AB) -> 24980532 | T558: 150 | U558: =3805605037 -> 3805605037 | V558: =U558+S558+R558+P558+N558+M558+K558+J558+I558+H558+E558+B558 -> 1.10264e+11 | W558: =(I558+J558)/V558 -> 0.10350467 | X558: =N558/V558 -> 0.67118565 | Y558: =USDT_FinalReserves!G557/USDT_FinalReserves!$F557 -> 0.057437554 | Z558: 1.1330106e+11 | AA558: 1.0679333e+11
A559: 45390 | B559: 0 | C559: 75354.386 | D559: =_xlfn.XLOOKUP(A559,'BBG Data'!A:A,'BBG Data'!B:B) -> 71706.37 | E559: =C559*D559 -> 5.4033895e+09 | F559: 1637135.8 | G559: =_xlfn.XLOOKUP(A559,'BBG Data'!A:A,'BBG Data'!C:C) -> 2339.03 | H559: =G559*F559 -> 3.8293097e+09 | I559: 100264024 | J559: =J558-$J$1*J558*_xlfn.XLOOKUP(A559,'BBG Data'!A:A,'BBG Data'!F:F) -> 1.1312889e+10 | K559: =K558-K558*L559/360*_xlfn.XLOOKUP(A559,'BBG Data'!A:A,'BBG Data'!J:J) -> 8.3871953e+08 | L559: 90 | M559: =M558-M558*$M$1*_xlfn.XLOOKUP(A559,'BBG Data'!A:A,'BBG Data'!F:F) -> 6.2806331e+09 | N559: =N558-N558*O559/360*_xlfn.XLOOKUP('Tether Assets'!A559,'BBG Data'!A:A,'BBG Data'!V:V) -> 7.3952109e+10 | O559: 90 | P559: =P558-P558*Q559/360*_xlfn.XLOOKUP(A559,'BBG Data'!A:A,'BBG Data'!AI:AI) -> 1.1925545e+08 | Q559: 250 | R559: 4735309369 | S559: =S558-S558*T559/360*_xlfn.XLOOKUP('Tether Assets'!A559,'BBG Data'!A:A,'BBG Data'!AB:AB) -> 24959715 | T559: 150 | U559: =3805605037 -> 3805605037 | V559: =U559+S559+R559+P559+N559+M559+K559+J559+I559+H559+E559+B559 -> 1.1040244e+11 | W559: =(I559+J559)/V559 -> 0.10337772 | X559: =N559/V559 -> 0.66984123 | Y559: =USDT_FinalReserves!G558/USDT_FinalReserves!$F558 -> 0.058034268 | Z559: 1.134953e+11 | AA559: 1.0690868e+11
A560: 45391 | B560: 0 | C560: 75354.386 | D560: =_xlfn.XLOOKUP(A560,'BBG Data'!A:A,'BBG Data'!B:B) -> 69127.2 | E560: =C560*D560 -> 5.2090377e+09 | F560: 1637135.8 | G560: =_xlfn.XLOOKUP(A560,'BBG Data'!A:A,'BBG Data'!C:C) -> 2352.78 | H560: =G560*F560 -> 3.8518203e+09 | I560: 100264024 | J560: =J559-$J$1*J559*_xlfn.XLOOKUP(A560,'BBG Data'!A:A,'BBG Data'!F:F) -> 1.1312889e+10 | K560: =K559-K559*L560/360*_xlfn.XLOOKUP(A560,'BBG Data'!A:A,'BBG Data'!J:J) -> 8.3690999e+08 | L560: 90 | M560: =M559-M559*$M$1*_xlfn.XLOOKUP(A560,'BBG Data'!A:A,'BBG Data'!F:F) -> 6.2806331e+09 | N560: =N559-N559*O560/360*_xlfn.XLOOKUP('Tether Assets'!A560,'BBG Data'!A:A,'BBG Data'!V:V) -> 7.4192454e+10 | O560: 90 | P560: =P559-P559*Q560/360*_xlfn.XLOOKUP(A560,'BBG Data'!A:A,'BBG Data'!AI:AI) -> 1.2202979e+08 | Q560: 250 | R560: 4735309369 | S560: =S559-S559*T560/360*_xlfn.XLOOKUP('Tether Assets'!A560,'BBG Data'!A:A,'BBG Data'!AB:AB) -> 24990915 | T560: 150 | U560: =3805605037 -> 3805605037 | V560: =U560+S560+R560+P560+N560+M560+K560+J560+I560+H560+E560+B560 -> 1.1047194e+11 | W560: =(I560+J560)/V560 -> 0.10331269 | X560: =N560/V560 -> 0.67159544 | Y560: =USDT_FinalReserves!G559/USDT_FinalReserves!$F559 -> 0.057444923 | Z560: 1.1357534e+11 | AA560: 1.0705101e+11
A561: 45392 | B561: 0 | C561: 75354.386 | D561: =_xlfn.XLOOKUP(A561,'BBG Data'!A:A,'BBG Data'!B:B) -> 69807.51 | E561: =C561*D561 -> 5.260302e+09 | F561: 1637135.8 | G561: =_xlfn.XLOOKUP(A561,'BBG Data'!A:A,'BBG Data'!C:C) -> 2334.04 | H561: =G561*F561 -> 3.8211404e+09 | I561: 100264024 | J561: =J560-$J$1*J560*_xlfn.XLOOKUP(A561,'BBG Data'!A:A,'BBG Data'!F:F) -> 1.1312889e+10 | K561: =K560-K560*L561/360*_xlfn.XLOOKUP(A561,'BBG Data'!A:A,'BBG Data'!J:J) -> 8.3836203e+08 | L561: 90 | M561: =M560-M560*$M$1*_xlfn.XLOOKUP(A561,'BBG Data'!A:A,'BBG Data'!F:F) -> 6.2806331e+09 | N561: =N560-N560*O561/360*_xlfn.XLOOKUP('Tether Assets'!A561,'BBG Data'!A:A,'BBG Data'!V:V) -> 7.3357789e+10 | O561: 90 | P561: =P560-P560*Q561/360*_xlfn.XLOOKUP(A561,'BBG Data'!A:A,'BBG Data'!AI:AI) -> 1.126657e+08 | Q561: 250 | R561: 4735309369 | S561: =S560-S560*T561/360*_xlfn.XLOOKUP('Tether Assets'!A561,'BBG Data'!A:A,'BBG Data'!AB:AB) -> 23660149 | T561: 150 | U561: =3805605037 -> 3805605037 | V561: =U561+S561+R561+P561+N561+M561+K561+J561+I561+H561+E561+B561 -> 1.0964862e+11 | W561: =(I561+J561)/V561 -> 0.10408844 | X561: =N561/V561 -> 0.6690261 | Y561: =USDT_FinalReserves!G560/USDT_FinalReserves!$F560 -> 0.049769716 | Z561: 1.1273546e+11 | AA561: 1.0712465e+11
A562: 45393 | B562: 0 | C562: 75354.386 | D562: =_xlfn.XLOOKUP(A562,'BBG Data'!A:A,'BBG Data'!B:B) -> 70509.59 | E562: =C562*D562 -> 5.3132068e+09 | F562: 1637135.8 | G562: =_xlfn.XLOOKUP(A562,'BBG Data'!A:A,'BBG Data'!C:C) -> 2372.52 | H562: =G562*F562 -> 3.8841374e+09 | I562: 100264024 | J562: =J561-$J$1*J561*_xlfn.XLOOKUP(A562,'BBG Data'!A:A,'BBG Data'!F:F) -> 1.1312889e+10 | K562: =K561-K561*L562/360*_xlfn.XLOOKUP(A562,'BBG Data'!A:A,'BBG Data'!J:J) -> 8.3214977e+08 | L562: 90 | M562: =M561-M561*$M$1*_xlfn.XLOOKUP(A562,'BBG Data'!A:A,'BBG Data'!F:F) -> 6.2806331e+09 | N562: =N561-N561*O562/360*_xlfn.XLOOKUP('Tether Assets'!A562,'BBG Data'!A:A,'BBG Data'!V:V) -> 7.3467825e+10 | O562: 90 | P562: =P561-P561*Q562/360*_xlfn.XLOOKUP(A562,'BBG Data'!A:A,'BBG Data'!AI:AI) -> 1.1477818e+08 | Q562: 250 | R562: 4735309369 | S562: =S561-S561*T562/360*_xlfn.XLOOKUP('Tether Assets'!A562,'BBG Data'!A:A,'BBG Data'!AB:AB) -> 23579310 | T562: 150 | U562: =3805605037 -> 3805605037 | V562: =U562+S562+R562+P562+N562+M562+K562+J562+I562+H562+E562+B562 -> 1.0987038e+11 | W562: =(I562+J562)/V562 -> 0.10387835 | X562: =N562/V562 -> 0.66867728 | Y562: =USDT_FinalReserves!G561/USDT_FinalReserves!$F561 -> 0.058755189 | Z562: 1.1385555e+11 | AA562: 1.0716595e+11
A563: 45394 | B563: 0 | C563: 75354.386 | D563: =_xlfn.XLOOKUP(A563,'BBG Data'!A:A,'BBG Data'!B:B) -> 67127.64 | E563: =C563*D563 -> 5.0583621e+09 | F563: 1637135.8 | G563: =_xlfn.XLOOKUP(A563,'BBG Data'!A:A,'BBG Data'!C:C) -> 2344.37 | H563: =G563*F563 -> 3.838052e+09 | I563: 100264024 | J563: =J562-$J$1*J562*_xlfn.XLOOKUP(A563,'BBG Data'!A:A,'BBG Data'!F:F) -> 1.1312889e+10 | K563: =K562-K562*L563/360*_xlfn.XLOOKUP(A563,'BBG Data'!A:A,'BBG Data'!J:J) -> 8.32337e+08 | L563: 90 | M563: =M562-M562*$M$1*_xlfn.XLOOKUP(A563,'BBG Data'!A:A,'BBG Data'!F:F) -> 6.2806331e+09 | N563: =N562-N562*O563/360*_xlfn.XLOOKUP('Tether Assets'!A563,'BBG Data'!A:A,'BBG Data'!V:V) -> 7.3688229e+10 | O563: 90 | P563: =P562-P562*Q563/360*_xlfn.XLOOKUP(A563,'BBG Data'!A:A,'BBG Data'!AI:AI) -> 1.1645203e+08 | Q563: 250 | R563: 4735309369 | S563: =S562-S562*T563/360*_xlfn.XLOOKUP('Tether Assets'!A563,'BBG Data'!A:A,'BBG Data'!AB:AB) -> 23861279 | T563: 150 | U563: =3805605037 -> 3805605037 | V563: =U563+S563+R563+P563+N563+M563+K563+J563+I563+H563+E563+B563 -> 1.0979199e+11 | W563: =(I563+J563)/V563 -> 0.10395251 | X563: =N563/V563 -> 0.67116213 | Y563: =USDT_FinalReserves!G562/USDT_FinalReserves!$F562 -> 0.056178237 | Z563: 1.1371361e+11 | AA563: 1.0732538e+11
... A641: 45472 | B641: 0 | C641: 75354.386 | D641: =_xlfn.XLOOKUP(A641,'BBG Data'!A:A,'BBG Data'!B:B) -> 60949.7 | E641: =C641*D641 -> 4.5928272e+09 | F641: 1637135.8 | G641: =_xlfn.XLOOKUP(A641,'BBG Data'!A:A,'BBG Data'!C:C) -> 2326.75 | H641: =G641*F641 -> 3.8092057e+09 | I641: 100264024 | J641: =J640-$J$1*J640*_xlfn.XLOOKUP(A641,'BBG Data'!A:A,'BBG Data'!F:F) -> 1.1312261e+10 | K641: =K640-K640*L641/360*_xlfn.XLOOKUP(A641,'BBG Data'!A:A,'BBG Data'!J:J) -> 8.3295096e+08 | L641: 90 | M641: =M640-M640*$M$1*_xlfn.XLOOKUP(A641,'BBG Data'!A:A,'BBG Data'!F:F) -> 6.2799349e+09 | N641: =N640-N640*O641/360*_xlfn.XLOOKUP('Tether Assets'!A641,'BBG Data'!A:A,'BBG Data'!V:V) -> 7.4261537e+10 | O641: 90 | P641: =P640-P640*Q641/360*_xlfn.XLOOKUP(A641,'BBG Data'!A:A,'BBG Data'!AI:AI) -> 1.1734626e+08 | Q641: 250 | R641: 4735309369 | S641: =S640-S640*T641/360*_xlfn.XLOOKUP('Tether Assets'!A641,'BBG Data'!A:A,'BBG Data'!AB:AB) -> 24142183 | T641: 150 | U641: =3805605037 -> 3805605037 | V641: =U641+S641+R641+P641+N641+M641+K641+J641+I641+H641+E641+B641 -> 1.0987138e+11 | W641: =(I641+J641)/V641 -> 0.10387168 | X641: =N641/V641 -> 0.67589517 | Y641: =USDT_FinalReserves!G640/USDT_FinalReserves!$F640 -> 0.057389459 | Z641: 1.194595e+11 | AA641: 1.1260379e+11
...

Sheet Circle Assets
C1: =90/360 -> 0.25 | D1: =1/360 -> 0.0027777778
A2: Date | B2: Cash & Deposits | C2: Tbills | D2: O/N Repo | E2: Total Assets | F2: L | G2: D | H2: K | I2: New Estimate Reserves | J2: USDC Market Cap
A3: 44834 | B3: 9212857953 | C3: 38266665985 | D3: 0 | E3: =D3+C3+B3 -> 47479523938 | F3: =(B3+D3)/E3 -> 0.19403855 | G3: =C3/E3 -> 0.80596145 | H3: ='USDC_Final Reserve'!I2/'USDC_Final Reserve'!F2 -> 0.0045852208 | I3: 4.7698231e+10 | J3: 47479523938
A4: 44835 | B4: 9212857953 | C4: =C3-C3*$C$1*_xlfn.XLOOKUP('Circle Assets'!A4,'BBG Data'!A:A,'BBG Data'!V:V) -> 38266665985 | D4: =D3-D3*$D$1*_xlfn.XLOOKUP(A4,'BBG Data'!A:A,'BBG Data'!F:F) -> 0 | E4: =D4+C4+B4 -> 47479523938 | F4: =(B4+D4)/E4 -> 0.19403855 | G4: =C4/E4 -> 0.80596145 | H4: ='USDC_Final Reserve'!I3/'USDC_Final Reserve'!F3 -> 0.0045852208 | I4: 4.7535527e+10 | J4: 4.7317567e+10
A5: 44836 | B5: 9212857953 | C5: =C4-C4*$C$1*_xlfn.XLOOKUP('Circle Assets'!A5,'BBG Data'!A:A,'BBG Data'!V:V) -> 38266665985 | D5: =D4-D4*$D$1*_xlfn.XLOOKUP(A5,'BBG Data'!A:A,'BBG Data'!F:F) -> 0 | E5: =D5+C5+B5 -> 47479523938 | F5: =(B5+D5)/E5 -> 0.19403855 | G5: =C5/E5 -> 0.80596145 | H5: ='USDC_Final Reserve'!I4/'USDC_Final Reserve'!F4 -> 0.0045852208 | I5: 4.7434526e+10 | J5: 4.7217028e+10
A6: 44837 | B6: 9212857953 | C6: =C5-C5*$C$1*_xlfn.XLOOKUP('Circle Assets'!A6,'BBG Data'!A:A,'BBG Data'!V:V) -> 3.8649333e+10 | D6: =D5-D5*$D$1*_xlfn.XLOOKUP(A6,'BBG Data'!A:A,'BBG Data'!F:F) -> 0 | E6: =D6+C6+B6 -> 4.7862191e+10 | F6: =(B6+D6)/E6 -> 0.19248718 | G6: =C6/E6 -> 0.80751282 | H6: ='USDC_Final Reserve'!I5/'USDC_Final Reserve'!F5 -> 0.012543738 | I6: 4.8031703e+10 | J6: 4.7429206e+10
A7: 44838 | B7: 9212857953 | C7: =C6-C6*$C$1*_xlfn.XLOOKUP('Circle Assets'!A7,'BBG Data'!A:A,'BBG Data'!V:V) -> 3.7170996e+10 | D7: =D6-D6*$D$1*_xlfn.XLOOKUP(A7,'BBG Data'!A:A,'BBG Data'!F:F) -> 0 | E7: =D7+C7+B7 -> 4.6383854e+10 | F7: =(B7+D7)/E7 -> 0.19862209 | G7: =C7/E7 -> 0.80137791 | H7: ='USDC_Final Reserve'!I6/'USDC_Final Reserve'!F6 -> -0.027140441 | I7: 4.5882506e+10 | J7: 4.7127777e+10
A8: 44839 | B8: 9212857953 | C8: =C7-C7*$C$1*_xlfn.XLOOKUP('Circle Assets'!A8,'BBG Data'!A:A,'BBG Data'!V:V) -> 3.7263923e+10 | D8: =D7-D7*$D$1*_xlfn.XLOOKUP(A8,'BBG Data'!A:A,'BBG Data'!F:F) -> 0 | E8: =D8+C8+B8 -> 4.6476781e+10 | F8: =(B8+D8)/E8 -> 0.19822496 | G8: =C8/E8 -> 0.80177504 | H8: ='USDC_Final Reserve'!I7/'USDC_Final Reserve'!F7 -> 0.006575492 | I8: 4.7077017e+10 | J8: 4.6767463e+10
A9: 44840 | B9: 9212857953 | C9: =C8-C8*$C$1*_xlfn.XLOOKUP('Circle Assets'!A9,'BBG Data'!A:A,'BBG Data'!V:V) -> 3.7217343e+10 | D9: =D8-D8*$D$1*_xlfn.XLOOKUP(A9,'BBG Data'!A:A,'BBG Data'!F:F) -> 0 | E9: =D9+C9+B9 -> 4.6430201e+10 | F9: =(B9+D9)/E9 -> 0.19842382 | G9: =C9/E9 -> 0.80157618 | H9: ='USDC_Final Reserve'!I8/'USDC_Final Reserve'!F8 -> 0.0035865966 | I9: 4.6579527e+10 | J9: 4.6412465e+10
A10: 44841 | B10: 9212857953 | C10: =C9-C9*$C$1*_xlfn.XLOOKUP('Circle Assets'!A10,'BBG Data'!A:A,'BBG Data'!V:V) -> 3.7422039e+10 | D10: =D9-D9*$D$1*_xlfn.XLOOKUP(A10,'BBG Data'!A:A,'BBG Data'!F:F) -> 0 | E10: =D10+C10+B10 -> 4.6634897e+10 | F10: =(B10+D10)/E10 -> 0.19755288 | G10: =C10/E10 -> 0.80244712 | H10: ='USDC_Final Reserve'!I9/'USDC_Final Reserve'!F9 -> 0.0089544128 | I10: 4.6606326e+10 | J10: 4.6188993e+10
A11: 44842 | B11: 9212857953 | C11: =C10-C10*$C$1*_xlfn.XLOOKUP('Circle Assets'!A11,'BBG Data'!A:A,'BBG Data'!V:V) -> 3.7422039e+10 | D11: =D10-D10*$D$1*_xlfn.XLOOKUP(A11,'BBG Data'!A:A,'BBG Data'!F:F) -> 0 | E11: =D11+C11+B11 -> 4.6634897e+10 | F11: =(B11+D11)/E11 -> 0.19755288 | G11: =C11/E11 -> 0.80244712 | H11: ='USDC_Final Reserve'!I10/'USDC_Final Reserve'!F10 -> 0.0045852208 | I11: 4.6423801e+10 | J11: 4.6210938e+10
A12: 44843 | B12: 9212857953 | C12: =C11-C11*$C$1*_xlfn.XLOOKUP('Circle Assets'!A12,'BBG Data'!A:A,'BBG Data'!V:V) -> 3.7422039e+10 | D12: =D11-D11*$D$1*_xlfn.XLOOKUP(A12,'BBG Data'!A:A,'BBG Data'!F:F) -> 0 | E12: =D12+C12+B12 -> 4.6634897e+10 | F12: =(B12+D12)/E12 -> 0.19755288 | G12: =C12/E12 -> 0.80244712 | H12: ='USDC_Final Reserve'!I11/'USDC_Final Reserve'!F11 -> 0.0045852208 | I12: 4.6267106e+10 | J12: 4.6054962e+10
A13: 44844 | B13: 9212857953 | C13: =C12-C12*$C$1*_xlfn.XLOOKUP('Circle Assets'!A13,'BBG Data'!A:A,'BBG Data'!V:V) -> 3.7422039e+10 | D13: =D12-D12*$D$1*_xlfn.XLOOKUP(A13,'BBG Data'!A:A,'BBG Data'!F:F) -> 0 | E13: =D13+C13+B13 -> 4.6634897e+10 | F13: =(B13+D13)/E13 -> 0.19755288 | G13: =C13/E13 -> 0.80244712 | H13: ='USDC_Final Reserve'!I12/'USDC_Final Reserve'!F12 -> 0.0045852208 | I13: 4.6186411e+10 | J13: 4.5974636e+10
A14: 44845 | B14: 9212857953 | C14: =C13-C13*$C$1*_xlfn.XLOOKUP('Circle Assets'!A14,'BBG Data'!A:A,'BBG Data'!V:V) -> 3.6636176e+10 | D14: =D13-D13*$D$1*_xlfn.XLOOKUP(A14,'BBG Data'!A:A,'BBG Data'!F:F) -> 0 | E14: =D14+C14+B14 -> 4.5849034e+10 | F14: =(B14+D14)/E14 -> 0.20093898 | G14: =C14/E14 -> 0.79906102 | H14: ='USDC_Final Reserve'!I13/'USDC_Final Reserve'!F13 -> -0.012476414 | I14: 4.5401225e+10 | J14: 4.5967669e+10
A15: 44846 | B15: 9212857953 | C15: =C14-C14*$C$1*_xlfn.XLOOKUP('Circle Assets'!A15,'BBG Data'!A:A,'BBG Data'!V:V) -> 3.5024184e+10 | D15: =D14-D14*$D$1*_xlfn.XLOOKUP(A15,'BBG Data'!A:A,'BBG Data'!F:F) -> 0 | E15: =D15+C15+B15 -> 4.4237042e+10 | F15: =(B15+D15)/E15 -> 0.20826117 | G15: =C15/E15 -> 0.79173883 | H15: ='USDC_Final Reserve'!I14/'USDC_Final Reserve'!F14 -> -0.031687557 | I15: 4.4537319e+10 | J15: 4.5948598e+10
... A94: 44925 | B94: 9212857953 | C94: =C93-C93*$C$1*_xlfn.XLOOKUP('Circle Assets'!A94,'BBG Data'!A:A,'BBG Data'!V:V) -> 2.8881804e+10 | D94: =D93-D93*$D$1*_xlfn.XLOOKUP(A94,'BBG Data'!A:A,'BBG Data'!F:F) -> 0 | E94: =D94+C94+B94 -> 3.8094662e+10 | F94: =(B94+D94)/E94 -> 0.24184118 | G94: =C94/E94 -> 0.75815882 | H94: ='USDC_Final Reserve'!I93/'USDC_Final Reserve'!F93 -> 0.007591924 | I94: 4.4746683e+10 | J94: 4.440697e+10
A95: 44926 | B95: 10588439005 | C95: 3.4105525e+10 | D95: 0 | E95: =D95+C95+B95 -> 44693963701 | F95: =(B95+D95)/E95 -> 0.23690982 | G95: =C95/E95 -> 0.76309018 | H95: ='USDC_Final Reserve'!I94/'USDC_Final Reserve'!F94 -> 0.0031418222 | I95: 4.4663623e+10 | J95: 4.4523298e+10
A96: 44927 | B96: 10588439005 | C96: =C95-C95*$C$1*_xlfn.XLOOKUP('Circle Assets'!A96,'BBG Data'!A:A,'BBG Data'!V:V) -> 3.4105525e+10 | D96: =D95-D95*$D$1*_xlfn.XLOOKUP(A96,'BBG Data'!A:A,'BBG Data'!F:F) -> 0 | E96: =D96+C96+B96 -> 44693963701 | F96: =(B96+D96)/E96 -> 0.23690982 | G96: =C96/E96 -> 0.76309018 | H96: ='USDC_Final Reserve'!I95/'USDC_Final Reserve'!F95 -> 0.0031418222 | I96: 4.4668999e+10 | J96: 4.4528657e+10
A97: 44928 | B97: 10588439005 | C97: =C96-C96*$C$1*_xlfn.XLOOKUP('Circle Assets'!A97,'BBG Data'!A:A,'BBG Data'!V:V) -> 3.4105525e+10 | D97: =D96-D96*$D$1*_xlfn.XLOOKUP(A97,'BBG Data'!A:A,'BBG Data'!F:F) -> 0 | E97: =D97+C97+B97 -> 44693963701 | F97: =(B97+D97)/E97 -> 0.23690982 | G97: =C97/E97 -> 0.76309018 | H97: ='USDC_Final Reserve'!I96/'USDC_Final Reserve'!F96 -> 0.0031418222 | I97: 4.4742376e+10 | J97: 4.4601804e+10
A98: 44929 | B98: 10588439005 | C98: =C97-C97*$C$1*_xlfn.XLOOKUP('Circle Assets'!A98,'BBG Data'!A:A,'BBG Data'!V:V) -> 3.4156683e+10 | D98: =D97-D97*$D$1*_xlfn.XLOOKUP(A98,'BBG Data'!A:A,'BBG Data'!F:F) -> 0 | E98: =D98+C98+B98 -> 4.4745122e+10 | F98: =(B98+D98)/E98 -> 0.23663896 | G98: =C98/E98 -> 0.76336104 | H98: ='USDC_Final Reserve'!I97/'USDC_Final Reserve'!F97 -> 0.0042815567 | I98: 4.4886202e+10 | J98: 4.4694019e+10
A99: 44930 | B99: 10588439005 | C99: =C98-C98*$C$1*_xlfn.XLOOKUP('Circle Assets'!A99,'BBG Data'!A:A,'BBG Data'!V:V) -> 3.295266e+10 | D99: =D98-D98*$D$1*_xlfn.XLOOKUP(A99,'BBG Data'!A:A,'BBG Data'!F:F) -> 0 | E99: =D99+C99+B99 -> 4.3541099e+10 | F99: =(B99+D99)/E99 -> 0.24318263 | G99: =C99/E99 -> 0.75681737 | H99: ='USDC_Final Reserve'!I98/'USDC_Final Reserve'!F98 -> -0.024423863 | I99: 4.3148276e+10 | J99: 4.4202124e+10
A100: 44931 | B100: 10588439005 | C100: =C99-C99*$C$1*_xlfn.XLOOKUP('Circle Assets'!A100,'BBG Data'!A:A,'BBG Data'!V:V) -> 3.2112367e+10 | D100: =D99-D99*$D$1*_xlfn.XLOOKUP(A100,'BBG Data'!A:A,'BBG Data'!F:F) -> 0 | E100: =D100+C100+B100 -> 4.2700806e+10 | F100: =(B100+D100)/E100 -> 0.24796813 | G100: =C100/E100 -> 0.75203187 | H100: ='USDC_Final Reserve'!I99/'USDC_Final Reserve'!F99 -> -0.016474968 | I100: 4.3420081e+10 | J100: 4.4135426e+10
A101: 44932 | B101: 10588439005 | C101: =C100-C100*$C$1*_xlfn.XLOOKUP('Circle Assets'!A101,'BBG Data'!A:A,'BBG Data'!V:V) -> 3.2160536e+10 | D101: =D100-D100*$D$1*_xlfn.XLOOKUP(A101,'BBG Data'!A:A,'BBG Data'!F:F) -> 0 | E101: =D101+C101+B101 -> 4.2748975e+10 | F101: =(B101+D101)/E101 -> 0.24768872 | G101: =C101/E101 -> 0.75231128 | H101: ='USDC_Final Reserve'!I100/'USDC_Final Reserve'!F100 -> 0.0042650589 | I101: 4.3950883e+10 | J101: 4.376343e+10
A102: 44933 | B102: 10588439005 | C102: =C101-C101*$C$1*_xlfn.XLOOKUP('Circle Assets'!A102,'BBG Data'!A:A,'BBG Data'!V:V) -> 3.2160536e+10 | D102: =D101-D101*$D$1*_xlfn.XLOOKUP(A102,'BBG Data'!A:A,'BBG Data'!F:F) -> 0 | E102: =D102+C102+B102 -> 4.2748975e+10 | F102: =(B102+D102)/E102 -> 0.24768872 | G102: =C102/E102 -> 0.75231128 | H102: ='USDC_Final Reserve'!I101/'USDC_Final Reserve'!F101 -> 0.0031418222 | I102: 4.3850638e+10 | J102: 4.3712867e+10
A103: 44934 | B103: 10588439005 | C103: =C102-C102*$C$1*_xlfn.XLOOKUP('Circle Assets'!A103,'BBG Data'!A:A,'BBG Data'!V:V) -> 3.2160536e+10 | D103: =D102-D102*$D$1*_xlfn.XLOOKUP(A103,'BBG Data'!A:A,'BBG Data'!F:F) -> 0 | E103: =D103+C103+B103 -> 4.2748975e+10 | F103: =(B103+D103)/E103 -> 0.24768872 | G103: =C103/E103 -> 0.75231128 | H103: ='USDC_Final Reserve'!I102/'USDC_Final Reserve'!F102 -> 0.0031418222 | I103: 4.3953508e+10 | J103: 4.3815414e+10
A104: 44935 | B104: 10588439005 | C104: =C103-C103*$C$1*_xlfn.XLOOKUP('Circle Assets'!A104,'BBG Data'!A:A,'BBG Data'!V:V) -> 3.2128375e+10 | D104: =D103-D103*$D$1*_xlfn.XLOOKUP(A104,'BBG Data'!A:A,'BBG Data'!F:F) -> 0 | E104: =D104+C104+B104 -> 4.2716814e+10 | F104: =(B104+D104)/E104 -> 0.2478752 | G104: =C104/E104 -> 0.7521248 | H104: ='USDC_Final Reserve'!I103/'USDC_Final Reserve'!F103 -> 0.00239131 | I104: 4.4079364e+10 | J104: 4.3973957e+10
A105: 44936 | B105: 10588439005 | C105: =C104-C104*$C$1*_xlfn.XLOOKUP('Circle Assets'!A105,'BBG Data'!A:A,'BBG Data'!V:V) -> 3.2104279e+10 | D105: =D104-D104*$D$1*_xlfn.XLOOKUP(A105,'BBG Data'!A:A,'BBG Data'!F:F) -> 0 | E105: =D105+C105+B105 -> 4.2692718e+10 | F105: =(B105+D105)/E105 -> 0.24801511 | G105: =C105/E105 -> 0.75198489 | H105: ='USDC_Final Reserve'!I104/'USDC_Final Reserve'!F104 -> 0.0025791835 | I105: 4.4126458e+10 | J105: 4.4012648e+10
A106: 44937 | B106: 10588439005 | C106: =C105-C105*$C$1*_xlfn.XLOOKUP('Circle Assets'!A106,'BBG Data'!A:A,'BBG Data'!V:V) -> 3.1646793e+10 | D106: =D105-D105*$D$1*_xlfn.XLOOKUP(A106,'BBG Data'!A:A,'BBG Data'!F:F) -> 0 | E106: =D106+C106+B106 -> 4.2235232e+10 | F106: =(B106+D106)/E106 -> 0.25070157 | G106: =C106/E106 -> 0.74929843 | H106: ='USDC_Final Reserve'!I105/'USDC_Final Reserve'!F105 -> -0.0076560026 | I106: 4.33532e+10 | J106: 4.3685112e+10
A107: 44938 | B107: 10588439005 | C107: =C106-C106*$C$1*_xlfn.XLOOKUP('Circle Assets'!A107,'BBG Data'!A:A,'BBG Data'!V:V) -> 3.2271817e+10 | D107: =D106-D106*$D$1*_xlfn.XLOOKUP(A107,'BBG Data'!A:A,'BBG Data'!F:F) -> 0 | E107: =D107+C107+B107 -> 4.2860256e+10 | F107: =(B107+D107)/E107 -> 0.24704563 | G107: =C107/E107 -> 0.75295437 | H107: ='USDC_Final Reserve'!I106/'USDC_Final Reserve'!F106 -> 0.017678843 | I107: 4.4720285e+10 | J107: 4.3929682e+10
... A184: 45015 | B184: 10588439005 | C184: =C183-C183*$C$1*_xlfn.XLOOKUP('Circle Assets'!A184,'BBG Data'!A:A,'BBG Data'!V:V) -> 3.0229873e+10 | D184: =D183-D183*$D$1*_xlfn.XLOOKUP(A184,'BBG Data'!A:A,'BBG Data'!F:F) -> 0 | E184: =D184+C184+B184 -> 4.0818312e+10 | F184: =(B184+D184)/E184 -> 0.25940414 | G184: =C184/E184 -> 0.74059586 | H184: ='USDC_Final Reserve'!I183/'USDC_Final Reserve'!F183 -> -0.011156966 | I184: 3.2932199e+10 | J184: 3.3299623e+10
A185: 45016 | B185: 4.0611664e+09 | C185: 28510534939 | D185: 0 | E185: =D185+C185+B185 -> 32571701308 | F185: =(B185+D185)/E185 -> 0.12468389 | G185: =C185/E185 -> 0.87531611 | H185: ='USDC_Final Reserve'!I184/'USDC_Final Reserve'!F184 -> 0 | I185: 3.2875147e+10 | J185: 3.2875147e+10
A186: 45017 | B186: 4.0611664e+09 | C186: =C185-C185*$C$1*_xlfn.XLOOKUP('Circle Assets'!A186,'BBG Data'!A:A,'BBG Data'!V:V) -> 28510534939 | D186: =D185-D185*$D$1*_xlfn.XLOOKUP(A186,'BBG Data'!A:A,'BBG Data'!F:F) -> 0 | E186: =D186+C186+B186 -> 32571701308 | F186: =(B186+D186)/E186 -> 0.12468389 | G186: =C186/E186 -> 0.87531611 | H186: ='USDC_Final Reserve'!I185/'USDC_Final Reserve'!F185 -> 0 | I186: 3.2545003e+10 | J186: 3.2545003e+10
A187: 45018 | B187: 4.0611664e+09 | C187: =C186-C186*$C$1*_xlfn.XLOOKUP('Circle Assets'!A187,'BBG Data'!A:A,'BBG Data'!V:V) -> 28510534939 | D187: =D186-D186*$D$1*_xlfn.XLOOKUP(A187,'BBG Data'!A:A,'BBG Data'!F:F) -> 0 | E187: =D187+C187+B187 -> 32571701308 | F187: =(B187+D187)/E187 -> 0.12468389 | G187: =C187/E187 -> 0.87531611 | H187: ='USDC_Final Reserve'!I186/'USDC_Final Reserve'!F186 -> 0 | I187: 3.2545587e+10 | J187: 3.2545587e+10
A188: 45019 | B188: 4.0611664e+09 | C188: =C187-C187*$C$1*_xlfn.XLOOKUP('Circle Assets'!A188,'BBG Data'!A:A,'BBG Data'!V:V) -> 2.8460642e+10 | D188: =D187-D187*$D$1*_xlfn.XLOOKUP(A188,'BBG Data'!A:A,'BBG Data'!F:F) -> 0 | E188: =D188+C188+B188 -> 3.2521808e+10 | F188: =(B188+D188)/E188 -> 0.12487517 | G188: =C188/E188 -> 0.87512483 | H188: ='USDC_Final Reserve'!I187/'USDC_Final Reserve'!F187 -> -0.0015341532 | I188: 3.2514729e+10 | J188: 3.2564611e+10
A189: 45020 | B189: 4.0611664e+09 | C189: =C188-C188*$C$1*_xlfn.XLOOKUP('Circle Assets'!A189,'BBG Data'!A:A,'BBG Data'!V:V) -> 2.8147574e+10 | D189: =D188-D188*$D$1*_xlfn.XLOOKUP(A189,'BBG Data'!A:A,'BBG Data'!F:F) -> 0 | E189: =D189+C189+B189 -> 3.2208741e+10 | F189: =(B189+D189)/E189 -> 0.12608895 | G189: =C189/E189 -> 0.87391105 | H189: ='USDC_Final Reserve'!I188/'USDC_Final Reserve'!F188 -> -0.0097199409 | I189: 3.2363794e+10 | J189: 3.2678368e+10
A190: 45021 | B190: 4.0611664e+09 | C190: =C189-C189*$C$1*_xlfn.XLOOKUP('Circle Assets'!A190,'BBG Data'!A:A,'BBG Data'!V:V) -> 2.7971652e+10 | D190: =D189-D189*$D$1*_xlfn.XLOOKUP(A190,'BBG Data'!A:A,'BBG Data'!F:F) -> 0 | E190: =D190+C190+B190 -> 3.2032818e+10 | F190: =(B190+D190)/E190 -> 0.12678142 | G190: =C190/E190 -> 0.87321858 | H190: ='USDC_Final Reserve'!I189/'USDC_Final Reserve'!F189 -> -0.0054919407 | I190: 3.2527815e+10 | J190: 3.2706456e+10
A191: 45022 | B191: 4.0611664e+09 | C191: =C190-C190*$C$1*_xlfn.XLOOKUP('Circle Assets'!A191,'BBG Data'!A:A,'BBG Data'!V:V) -> 2.7880744e+10 | D191: =D190-D190*$D$1*_xlfn.XLOOKUP(A191,'BBG Data'!A:A,'BBG Data'!F:F) -> 0 | E191: =D191+C191+B191 -> 3.1941911e+10 | F191: =(B191+D191)/E191 -> 0.12714225 | G191: =C191/E191 -> 0.87285775 | H191: ='USDC_Final Reserve'!I190/'USDC_Final Reserve'!F190 -> -0.0028460373 | I191: 3.2548324e+10 | J191: 3.2640958e+10
A192: 45023 | B192: 4.0611664e+09 | C192: =C191-C191*$C$1*_xlfn.XLOOKUP('Circle Assets'!A192,'BBG Data'!A:A,'BBG Data'!V:V) -> 2.7748311e+10 | D192: =D191-D191*$D$1*_xlfn.XLOOKUP(A192,'BBG Data'!A:A,'BBG Data'!F:F) -> 0 | E192: =D192+C192+B192 -> 3.1809477e+10 | F192: =(B192+D192)/E192 -> 0.12767159 | G192: =C192/E192 -> 0.87232841 | H192: ='USDC_Final Reserve'!I191/'USDC_Final Reserve'!F191 -> -0.0041633358 | I192: 3.2622797e+10 | J192: 3.2758617e+10
A193: 45024 | B193: 4.0611664e+09 | C193: =C192-C192*$C$1*_xlfn.XLOOKUP('Circle Assets'!A193,'BBG Data'!A:A,'BBG Data'!V:V) -> 2.7748311e+10 | D193: =D192-D192*$D$1*_xlfn.XLOOKUP(A193,'BBG Data'!A:A,'BBG Data'!F:F) -> 0 | E193: =D193+C193+B193 -> 3.1809477e+10 | F193: =(B193+D193)/E193 -> 0.12767159 | G193: =C193/E193 -> 0.87232841 | H193: ='USDC_Final Reserve'!I192/'USDC_Final Reserve'!F192 -> 0 | I193: 3.2617421e+10 | J193: 3.2617421e+10
A194: 45025 | B194: 4.0611664e+09 | C194: =C193-C193*$C$1*_xlfn.XLOOKUP('Circle Assets'!A194,'BBG Data'!A:A,'BBG Data'!V:V) -> 2.7748311e+10 | D194: =D193-D193*$D$1*_xlfn.XLOOKUP(A194,'BBG Data'!A:A,'BBG Data'!F:F) -> 0 | E194: =D194+C194+B194 -> 3.1809477e+10 | F194: =(B194+D194)/E194 -> 0.12767159 | G194: =C194/E194 -> 0.87232841 | H194: ='USDC_Final Reserve'!I193/'USDC_Final Reserve'!F193 -> 0 | I194: 3.2622414e+10 | J194: 3.2622414e+10
A195: 45026 | B195: 4.0611664e+09 | C195: =C194-C194*$C$1*_xlfn.XLOOKUP('Circle Assets'!A195,'BBG Data'!A:A,'BBG Data'!V:V) -> 2.6811805e+10 | D195: =D194-D194*$D$1*_xlfn.XLOOKUP(A195,'BBG Data'!A:A,'BBG Data'!F:F) -> 0 | E195: =D195+C195+B195 -> 3.0872972e+10 | F195: =(B195+D195)/E195 -> 0.1315444 | G195: =C195/E195 -> 0.8684556 | H195: ='USDC_Final Reserve'!I194/'USDC_Final Reserve'!F194 -> -0.030334154 | I195: 3.1657696e+10 | J195: 3.2618005e+10
A196: 45027 | B196: 4.0611664e+09 | C196: =C195-C195*$C$1*_xlfn.XLOOKUP('Circle Assets'!A196,'BBG Data'!A:A,'BBG Data'!V:V) -> 2.6838617e+10 | D196: =D195-D195*$D$1*_xlfn.XLOOKUP(A196,'BBG Data'!A:A,'BBG Data'!F:F) -> 0 | E196: =D196+C196+B196 -> 3.0899783e+10 | F196: =(B196+D196)/E196 -> 0.13143025 | G196: =C196/E196 -> 0.86856975 | H196: ='USDC_Final Reserve'!I195/'USDC_Final Reserve'!F195 -> 0.00086770204 | I196: 3.2398022e+10 | J196: 3.236991e+10
